Workbook

Sheet Start
B2: Debt Payoff Calculator (free)
B3: Enter your debts, set one monthly budget, and see the month you become debt-free.
B5: DEBT-FREE BY | E5: MONTHS TO GO | G5: TOTAL INTEREST
B6: =IF(Calc!$B$4=0,"Enter your debts below",IF(Calc!$C$4>$D$9,"Budget must be at least $"&TEXT(Calc!$C$4,"#,##0"),IF(IF($D$10="Avalanche",Calc!$B$3,Calc!$B$2)>120,"Over 10 years — raise your monthly budget by $"&TEXT(Calc!$D$4,"#,##0"),TEXT(EDATE($D$11,IF($D$10="Avalanche",Calc!$B$3,Calc!$B$2)-1),"mmm yyyy")))) | E6: =IF(Calc!$B$4=0,"-",IF(IF($D$10="Avalanche",Calc!$B$3,Calc!$B$2)>120,"120+",IF($D$10="Avalanche",Calc!$B$3,Calc!$B$2))) | G6: =IF(Calc!$B$4=0,"-",IF(IF($D$10="Avalanche",Calc!$B$3,Calc!$B$2)>120,"-",IF($D$10="Avalanche",Calc!$C$3,Calc!$C$2)))
B7: =IF(Calc!$B$4=0,"Tip: start with the debt you feel worst about — it usually is the smallest one.",IF(Calc!$C$4>$D$9,"Your minimum payments add up to more than your budget. Raise the budget or check the amounts.","Paying $"&TEXT($H$11,"#,##0")&" extra every month with the "&$D$10&" method ("&IF($D$10="Avalanche","highest APR first","smallest balance first")&")."))
B9: Monthly budget | F9: Total balance | H9: =SUM(D14:D28)
B10: Payoff method | D10: Snowball | F10: Minimum payments | H10: =Calc!C4
B11: First payment month | D11: =DATE(YEAR(TODAY()),MONTH(TODAY())+1,1) | F11: Extra toward debt | H11: =MAX(0,D9-H10)
B13: # | C13: Debt name | D13: Balance | E13: APR % | F13: Minimum payment | G13: Order | H13: Paid off
B14: 1 | G14: =IF($D$10="Avalanche",Calc!F6,Calc!D6) | H14: =IF(G14="","",IF(IF($D$10="Avalanche",Calc!H6,Calc!G6)>120,"120+ months",TEXT(EDATE($D$11,IF($D$10="Avalanche",Calc!H6,Calc!G6)-1),"mmm yyyy")))
B15: 2 | G15: =IF($D$10="Avalanche",Calc!F7,Calc!D7) | H15: =IF(G15="","",IF(IF($D$10="Avalanche",Calc!H7,Calc!G7)>120,"120+ months",TEXT(EDATE($D$11,IF($D$10="Avalanche",Calc!H7,Calc!G7)-1),"mmm yyyy")))
B16: 3 | G16: =IF($D$10="Avalanche",Calc!F8,Calc!D8) | H16: =IF(G16="","",IF(IF($D$10="Avalanche",Calc!H8,Calc!G8)>120,"120+ months",TEXT(EDATE($D$11,IF($D$10="Avalanche",Calc!H8,Calc!G8)-1),"mmm yyyy")))
B17: 4 | G17: =IF($D$10="Avalanche",Calc!F9,Calc!D9) | H17: =IF(G17="","",IF(IF($D$10="Avalanche",Calc!H9,Calc!G9)>120,"120+ months",TEXT(EDATE($D$11,IF($D$10="Avalanche",Calc!H9,Calc!G9)-1),"mmm yyyy")))
B18: 5 | G18: =IF($D$10="Avalanche",Calc!F10,Calc!D10) | H18: =IF(G18="","",IF(IF($D$10="Avalanche",Calc!H10,Calc!G10)>120,"120+ months",TEXT(EDATE($D$11,IF($D$10="Avalanche",Calc!H10,Calc!G10)-1),"mmm yyyy")))
B19: 6 | G19: =IF($D$10="Avalanche",Calc!F11,Calc!D11) | H19: =IF(G19="","",IF(IF($D$10="Avalanche",Calc!H11,Calc!G11)>120,"120+ months",TEXT(EDATE($D$11,IF($D$10="Avalanche",Calc!H11,Calc!G11)-1),"mmm yyyy")))
B20: 7 | G20: =IF($D$10="Avalanche",Calc!F12,Calc!D12) | H20: =IF(G20="","",IF(IF($D$10="Avalanche",Calc!H12,Calc!G12)>120,"120+ months",TEXT(EDATE($D$11,IF($D$10="Avalanche",Calc!H12,Calc!G12)-1),"mmm yyyy")))
B21: 8 | G21: =IF($D$10="Avalanche",Calc!F13,Calc!D13) | H21: =IF(G21="","",IF(IF($D$10="Avalanche",Calc!H13,Calc!G13)>120,"120+ months",TEXT(EDATE($D$11,IF($D$10="Avalanche",Calc!H13,Calc!G13)-1),"mmm yyyy")))
B22: 9 | G22: =IF($D$10="Avalanche",Calc!F14,Calc!D14) | H22: =IF(G22="","",IF(IF($D$10="Avalanche",Calc!H14,Calc!G14)>120,"120+ months",TEXT(EDATE($D$11,IF($D$10="Avalanche",Calc!H14,Calc!G14)-1),"mmm yyyy")))
B23: 10 | G23: =IF($D$10="Avalanche",Calc!F15,Calc!D15) | H23: =IF(G23="","",IF(IF($D$10="Avalanche",Calc!H15,Calc!G15)>120,"120+ months",TEXT(EDATE($D$11,IF($D$10="Avalanche",Calc!H15,Calc!G15)-1),"mmm yyyy")))
B24: 11 | G24: =IF($D$10="Avalanche",Calc!F16,Calc!D16) | H24: =IF(G24="","",IF(IF($D$10="Avalanche",Calc!H16,Calc!G16)>120,"120+ months",TEXT(EDATE($D$11,IF($D$10="Avalanche",Calc!H16,Calc!G16)-1),"mmm yyyy")))
B25: 12 | G25: =IF($D$10="Avalanche",Calc!F17,Calc!D17) | H25: =IF(G25="","",IF(IF($D$10="Avalanche",Calc!H17,Calc!G17)>120,"120+ months",TEXT(EDATE($D$11,IF($D$10="Avalanche",Calc!H17,Calc!G17)-1),"mmm yyyy")))
... B28: 15 | G28: =IF($D$10="Avalanche",Calc!F20,Calc!D20) | H28: =IF(G28="","",IF(IF($D$10="Avalanche",Calc!H20,Calc!G20)>120,"120+ months",TEXT(EDATE($D$11,IF($D$10="Avalanche",Calc!H20,Calc!G20)-1),"mmm yyyy")))
B30: Type only in the light-yellow cells. Everything else is calculated. APR: type 19.99 for 19.99%.
B31: See what to pay on each debt every month in the Schedule tab. Want to know each month if you're ahead or behind? See 'Track your progress'.

Sheet Schedule
B2: Payment schedule
B3: What to pay on each debt every month with your budget and method (from the Start tab). Balances are at the end of each month.
B5: Month # | C5: Month | D5: Total paid | E5: Interest | F5: Total balance | G5: =IF(Calc!$B$6=0,"",IF(Start!$C$14="","Debt 1",Start!$C$14)) | I5: =IF(Calc!$B$7=0,"",IF(Start!$C$15="","Debt 2",Start!$C$15)) | K5: =IF(Calc!$B$8=0,"",IF(Start!$C$16="","Debt 3",Start!$C$16)) | M5: =IF(Calc!$B$9=0,"",IF(Start!$C$17="","Debt 4",Start!$C$17)) | O5: =IF(Calc!$B$10=0,"",IF(Start!$C$18="","Debt 5",Start!$C$18)) | Q5: =IF(Calc!$B$11=0,"",IF(Start!$C$19="","Debt 6",Start!$C$19)) | S5: =IF(Calc!$B$12=0,"",IF(Start!$C$20="","Debt 7",Start!$C$20)) | U5: =IF(Calc!$B$13=0,"",IF(Start!$C$21="","Debt 8",Start!$C$21)) | W5: =IF(Calc!$B$14=0,"",IF(Start!$C$22="","Debt 9",Start!$C$22)) | Y5: =IF(Calc!$B$15=0,"",IF(Start!$C$23="","Debt 10",Start!$C$23)) | AA5: =IF(Calc!$B$16=0,"",IF(Start!$C$24="","Debt 11",Start!$C$24)) | AC5: =IF(Calc!$B$17=0,"",IF(Start!$C$25="","Debt 12",Start!$C$25)) | AE5: =IF(Calc!$B$18=0,"",IF(Start!$C$26="","Debt 13",Start!$C$26)) | AG5: =IF(Calc!$B$19=0,"",IF(Start!$C$27="","Debt 14",Start!$C$27)) | AI5: =IF(Calc!$B$20=0,"",IF(Start!$C$28="","Debt 15",Start!$C$28))
G6: Payment | H6: Balance | I6: Payment | J6: Balance | K6: Payment | L6: Balance | M6: Payment | N6: Balance | O6: Payment | P6: Balance | Q6: Payment | R6: Balance | S6: Payment | T6: Balance | U6: Payment | V6: Balance | W6: Payment | X6: Balance | Y6: Payment | Z6: Balance | AA6: Payment | AB6: Balance | AC6: Payment | AD6: Balance | AE6: Payment | AF6: Balance | AG6: Payment | AH6: Balance | AI6: Payment | AJ6: Balance
B7: 1 | C7: =IF(Calc!$B$4=0,"",EDATE(Start!$D$11,0)) | D7: =IF(OR(Calc!$B$4=0,$B7>IF(Start!$D$10="Avalanche",Calc!$B$3,Calc!$B$2)),"",SUM(G7,I7,K7,M7,O7,Q7,S7,U7,W7,Y7,AA7,AC7,AE7,AG7,AI7)) | E7: =IF(OR(Calc!$B$4=0,$B7>IF(Start!$D$10="Avalanche",Calc!$B$3,Calc!$B$2)),"",IF(Start!$D$10="Avalanche",Calc!C$72,Calc!C$47)) | F7: =IF(Calc!$B$4=0,"",IF($B7>IF(Start!$D$10="Avalanche",Calc!$B$3,Calc!$B$2),NA(),SUM(H7,J7,L7,N7,P7,R7,T7,V7,X7,Z7,AB7,AD7,AF7,AH7,AJ7))) | G7: =IF(H7="","",Start!$D$14*(1+Start!$E$14/12)-H7) | H7: =IF(OR(OR(Calc!$B$4=0,$B7>IF(Start!$D$10="Avalanche",Calc!$B$3,Calc!$B$2)),Calc!$B$6=0),"",IF(Start!$D$14<=0.005,"",IF(Start!$D$10="Avalanche",INDEX(Calc!E$75:E$89,Calc!$F$6),INDEX(Calc!E$50:E$64,Calc!$D$6)))) | I7: =IF(J7="","",Start!$D$15*(1+Start!$E$15/12)-J7) | J7: =IF(OR(OR(Calc!$B$4=0,$B7>IF(Start!$D$10="Avalanche",Calc!$B$3,Calc!$B$2)),Calc!$B$7=0),"",IF(Start!$D$15<=0.005,"",IF(Start!$D$10="Avalanche",INDEX(Calc!E$75:E$89,Calc!$F$7),INDEX(Calc!E$50:E$64,Calc!$D$7)))) | K7: =IF(L7="","",Start!$D$16*(1+Start!$E$16/12)-L7) | L7: =IF(OR(OR(Calc!$B$4=0,$B7>IF(Start!$D$10="Avalanche",Calc!$B$3,Calc!$B$2)),Calc!$B$8=0),"",IF(Start!$D$16<=0.005,"",IF(Start!$D$10="Avalanche",INDEX(Calc!E$75:E$89,Calc!$F$8),INDEX(Calc!E$50:E$64,Calc!$D$8)))) | M7: =IF(N7="","",Start!$D$17*(1+Start!$E$17/12)-N7) | N7: =IF(OR(OR(Calc!$B$4=0,$B7>IF(Start!$D$10="Avalanche",Calc!$B$3,Calc!$B$2)),Calc!$B$9=0),"",IF(Start!$D$17<=0.005,"",IF(Start!$D$10="Avalanche",INDEX(Calc!E$75:E$89,Calc!$F$9),INDEX(Calc!E$50:E$64,Calc!$D$9)))) | O7: =IF(P7="","",Start!$D$18*(1+Start!$E$18/12)-P7) | P7: =IF(OR(OR(Calc!$B$4=0,$B7>IF(Start!$D$10="Avalanche",Calc!$B$3,Calc!$B$2)),Calc!$B$10=0),"",IF(Start!$D$18<=0.005,"",IF(Start!$D$10="Avalanche",INDEX(Calc!E$75:E$89,Calc!$F$10),INDEX(Calc!E$50:E$64,Calc!$D$10)))) | Q7: =IF(R7="","",Start!$D$19*(1+Start!$E$19/12)-R7) | R7: =IF(OR(OR(Calc!$B$4=0,$B7>IF(Start!$D$10="Avalanche",Calc!$B$3,Calc!$B$2)),Calc!$B$11=0),"",IF(Start!$D$19<=0.005,"",IF(Start!$D$10="Avalanche",INDEX(Calc!E$75:E$89,Calc!$F$11),INDEX(Calc!E$50:E$64,Calc!$D$11)))) | S7: =IF(T7="","",Start!$D$20*(1+Start!$E$20/12)-T7) | T7: =IF(OR(OR(Calc!$B$4=0,$B7>IF(Start!$D$10="Avalanche",Calc!$B$3,Calc!$B$2)),Calc!$B$12=0),"",IF(Start!$D$20<=0.005,"",IF(Start!$D$10="Avalanche",INDEX(Calc!E$75:E$89,Calc!$F$12),INDEX(Calc!E$50:E$64,Calc!$D$12)))) | U7: =IF(V7="","",Start!$D$21*(1+Start!$E$21/12)-V7) | V7: =IF(OR(OR(Calc!$B$4=0,$B7>IF(Start!$D$10="Avalanche",Calc!$B$3,Calc!$B$2)),Calc!$B$13=0),"",IF(Start!$D$21<=0.005,"",IF(Start!$D$10="Avalanche",INDEX(Calc!E$75:E$89,Calc!$F$13),INDEX(Calc!E$50:E$64,Calc!$D$13)))) | W7: =IF(X7="","",Start!$D$22*(1+Start!$E$22/12)-X7) | X7: =IF(OR(OR(Calc!$B$4=0,$B7>IF(Start!$D$10="Avalanche",Calc!$B$3,Calc!$B$2)),Calc!$B$14=0),"",IF(Start!$D$22<=0.005,"",IF(Start!$D$10="Avalanche",INDEX(Calc!E$75:E$89,Calc!$F$14),INDEX(Calc!E$50:E$64,Calc!$D$14)))) | Y7: =IF(Z7="","",Start!$D$23*(1+Start!$E$23/12)-Z7) | Z7: =IF(OR(OR(Calc!$B$4=0,$B7>IF(Start!$D$10="Avalanche",Calc!$B$3,Calc!$B$2)),Calc!$B$15=0),"",IF(Start!$D$23<=0.005,"",IF(Start!$D$10="Avalanche",INDEX(Calc!E$75:E$89,Calc!$F$15),INDEX(Calc!E$50:E$64,Calc!$D$15)))) | AA7: =IF(AB7="","",Start!$D$24*(1+Start!$E$24/12)-AB7) | AB7: =IF(OR(OR(Calc!$B$4=0,$B7>IF(Start!$D$10="Avalanche",Calc!$B$3,Calc!$B$2)),Calc!$B$16=0),"",IF(Start!$D$24<=0.005,"",IF(Start!$D$10="Avalanche",INDEX(Calc!E$75:E$89,Calc!$F$16),INDEX(Calc!E$50:E$64,Calc!$D$16)))) | AC7: =IF(AD7="","",Start!$D$25*(1+Start!$E$25/12)-AD7) | AD7: =IF(OR(OR(Calc!$B$4=0,$B7>IF(Start!$D$10="Avalanche",Calc!$B$3,Calc!$B$2)),Calc!$B$17=0),"",IF(Start!$D$25<=0.005,"",IF(Start!$D$10="Avalanche",INDEX(Calc!E$75:E$89,Calc!$F$17),INDEX(Calc!E$50:E$64,Calc!$D$17)))) | AE7: =IF(AF7="","",Start!$D$26*(1+Start!$E$26/12)-AF7) | AF7: =IF(OR(OR(Calc!$B$4=0,$B7>IF(Start!$D$10="Avalanche",Calc!$B$3,Calc!$B$2)),Calc!$B$18=0),"",IF(Start!$D$26<=0.005,"",IF(Start!$D$10="Avalanche",INDEX(Calc!E$75:E$89,Calc!$F$18),INDEX(Calc!E$50:E$64,Calc!$D$18)))) | AG7: =IF(AH7="","",Start!$D$27*(1+Start!$E$27/12)-AH7) | AH7: =IF(OR(OR(Calc!$B$4=0,$B7>IF(Start!$D$10="Avalanche",Calc!$B$3,Calc!$B$2)),Calc!$B$19=0),"",IF(Start!$D$27<=0.005,"",IF(Start!$D$10="Avalanche",INDEX(Calc!E$75:E$89,Calc!$F$19),INDEX(Calc!E$50:E$64,Calc!$D$19)))) | AI7: =IF(AJ7="","",Start!$D$28*(1+Start!$E$28/12)-AJ7) | AJ7: =IF(OR(OR(Calc!$B$4=0,$B7>IF(Start!$D$10="Avalanche",Calc!$B$3,Calc!$B$2)),Calc!$B$20=0),"",IF(Start!$D$28<=0.005,"",IF(Start!$D$10="Avalanche",INDEX(Calc!E$75:E$89,Calc!$F$20),INDEX(Calc!E$50:E$64,Calc!$D$20))))
B8: 2 | C8: =IF(Calc!$B$4=0,"",EDATE(Start!$D$11,1)) | D8: =IF(OR(Calc!$B$4=0,$B8>IF(Start!$D$10="Avalanche",Calc!$B$3,Calc!$B$2)),"",SUM(G8,I8,K8,M8,O8,Q8,S8,U8,W8,Y8,AA8,AC8,AE8,AG8,AI8)) | E8: =IF(OR(Calc!$B$4=0,$B8>IF(Start!$D$10="Avalanche",Calc!$B$3,Calc!$B$2)),"",IF(Start!$D$10="Avalanche",Calc!F$72,Calc!F$47)) | F8: =IF(Calc!$B$4=0,"",IF($B8>IF(Start!$D$10="Avalanche",Calc!$B$3,Calc!$B$2),NA(),SUM(H8,J8,L8,N8,P8,R8,T8,V8,X8,Z8,AB8,AD8,AF8,AH8,AJ8))) | G8: =IF(H8="","",N(H7)*(1+Start!$E$14/12)-H8) | H8: =IF(OR(OR(Calc!$B$4=0,$B8>IF(Start!$D$10="Avalanche",Calc!$B$3,Calc!$B$2)),Calc!$B$6=0),"",IF(N(H7)<=0.005,"",IF(Start!$D$10="Avalanche",INDEX(Calc!H$75:H$89,Calc!$F$6),INDEX(Calc!H$50:H$64,Calc!$D$6)))) | I8: =IF(J8="","",N(J7)*(1+Start!$E$15/12)-J8) | J8: =IF(OR(OR(Calc!$B$4=0,$B8>IF(Start!$D$10="Avalanche",Calc!$B$3,Calc!$B$2)),Calc!$B$7=0),"",IF(N(J7)<=0.005,"",IF(Start!$D$10="Avalanche",INDEX(Calc!H$75:H$89,Calc!$F$7),INDEX(Calc!H$50:H$64,Calc!$D$7)))) | K8: =IF(L8="","",N(L7)*(1+Start!$E$16/12)-L8) | L8: =IF(OR(OR(Calc!$B$4=0,$B8>IF(Start!$D$10="Avalanche",Calc!$B$3,Calc!$B$2)),Calc!$B$8=0),"",IF(N(L7)<=0.005,"",IF(Start!$D$10="Avalanche",INDEX(Calc!H$75:H$89,Calc!$F$8),INDEX(Calc!H$50:H$64,Calc!$D$8)))) | M8: =IF(N8="","",N(N7)*(1+Start!$E$17/12)-N8) | N8: =IF(OR(OR(Calc!$B$4=0,$B8>IF(Start!$D$10="Avalanche",Calc!$B$3,Calc!$B$2)),Calc!$B$9=0),"",IF(N(N7)<=0.005,"",IF(Start!$D$10="Avalanche",INDEX(Calc!H$75:H$89,Calc!$F$9),INDEX(Calc!H$50:H$64,Calc!$D$9)))) | O8: =IF(P8="","",N(P7)*(1+Start!$E$18/12)-P8) | P8: =IF(OR(OR(Calc!$B$4=0,$B8>IF(Start!$D$10="Avalanche",Calc!$B$3,Calc!$B$2)),Calc!$B$10=0),"",IF(N(P7)<=0.005,"",IF(Start!$D$10="Avalanche",INDEX(Calc!H$75:H$89,Calc!$F$10),INDEX(Calc!H$50:H$64,Calc!$D$10)))) | Q8: =IF(R8="","",N(R7)*(1+Start!$E$19/12)-R8) | R8: =IF(OR(OR(Calc!$B$4=0,$B8>IF(Start!$D$10="Avalanche",Calc!$B$3,Calc!$B$2)),Calc!$B$11=0),"",IF(N(R7)<=0.005,"",IF(Start!$D$10="Avalanche",INDEX(Calc!H$75:H$89,Calc!$F$11),INDEX(Calc!H$50:H$64,Calc!$D$11)))) | S8: =IF(T8="","",N(T7)*(1+Start!$E$20/12)-T8) | T8: =IF(OR(OR(Calc!$B$4=0,$B8>IF(Start!$D$10="Avalanche",Calc!$B$3,Calc!$B$2)),Calc!$B$12=0),"",IF(N(T7)<=0.005,"",IF(Start!$D$10="Avalanche",INDEX(Calc!H$75:H$89,Calc!$F$12),INDEX(Calc!H$50:H$64,Calc!$D$12)))) | U8: =IF(V8="","",N(V7)*(1+Start!$E$21/12)-V8) | V8: =IF(OR(OR(Calc!$B$4=0,$B8>IF(Start!$D$10="Avalanche",Calc!$B$3,Calc!$B$2)),Calc!$B$13=0),"",IF(N(V7)<=0.005,"",IF(Start!$D$10="Avalanche",INDEX(Calc!H$75:H$89,Calc!$F$13),INDEX(Calc!H$50:H$64,Calc!$D$13)))) | W8: =IF(X8="","",N(X7)*(1+Start!$E$22/12)-X8) | X8: =IF(OR(OR(Calc!$B$4=0,$B8>IF(Start!$D$10="Avalanche",Calc!$B$3,Calc!$B$2)),Calc!$B$14=0),"",IF(N(X7)<=0.005,"",IF(Start!$D$10="Avalanche",INDEX(Calc!H$75:H$89,Calc!$F$14),INDEX(Calc!H$50:H$64,Calc!$D$14)))) | Y8: =IF(Z8="","",N(Z7)*(1+Start!$E$23/12)-Z8) | Z8: =IF(OR(OR(Calc!$B$4=0,$B8>IF(Start!$D$10="Avalanche",Calc!$B$3,Calc!$B$2)),Calc!$B$15=0),"",IF(N(Z7)<=0.005,"",IF(Start!$D$10="Avalanche",INDEX(Calc!H$75:H$89,Calc!$F$15),INDEX(Calc!H$50:H$64,Calc!$D$15)))) | AA8: =IF(AB8="","",N(AB7)*(1+Start!$E$24/12)-AB8) | AB8: =IF(OR(OR(Calc!$B$4=0,$B8>IF(Start!$D$10="Avalanche",Calc!$B$3,Calc!$B$2)),Calc!$B$16=0),"",IF(N(AB7)<=0.005,"",IF(Start!$D$10="Avalanche",INDEX(Calc!H$75:H$89,Calc!$F$16),INDEX(Calc!H$50:H$64,Calc!$D$16)))) | AC8: =IF(AD8="","",N(AD7)*(1+Start!$E$25/12)-AD8) | AD8: =IF(OR(OR(Calc!$B$4=0,$B8>IF(Start!$D$10="Avalanche",Calc!$B$3,Calc!$B$2)),Calc!$B$17=0),"",IF(N(AD7)<=0.005,"",IF(Start!$D$10="Avalanche",INDEX(Calc!H$75:H$89,Calc!$F$17),INDEX(Calc!H$50:H$64,Calc!$D$17)))) | AE8: =IF(AF8="","",N(AF7)*(1+Start!$E$26/12)-AF8) | AF8: =IF(OR(OR(Calc!$B$4=0,$B8>IF(Start!$D$10="Avalanche",Calc!$B$3,Calc!$B$2)),Calc!$B$18=0),"",IF(N(AF7)<=0.005,"",IF(Start!$D$10="Avalanche",INDEX(Calc!H$75:H$89,Calc!$F$18),INDEX(Calc!H$50:H$64,Calc!$D$18)))) | AG8: =IF(AH8="","",N(AH7)*(1+Start!$E$27/12)-AH8) | AH8: =IF(OR(OR(Calc!$B$4=0,$B8>IF(Start!$D$10="Avalanche",Calc!$B$3,Calc!$B$2)),Calc!$B$19=0),"",IF(N(AH7)<=0.005,"",IF(Start!$D$10="Avalanche",INDEX(Calc!H$75:H$89,Calc!$F$19),INDEX(Calc!H$50:H$64,Calc!$D$19)))) | AI8: =IF(AJ8="","",N(AJ7)*(1+Start!$E$28/12)-AJ8) | AJ8: =IF(OR(OR(Calc!$B$4=0,$B8>IF(Start!$D$10="Avalanche",Calc!$B$3,Calc!$B$2)),Calc!$B$20=0),"",IF(N(AJ7)<=0.005,"",IF(Start!$D$10="Avalanche",INDEX(Calc!H$75:H$89,Calc!$F$20),INDEX(Calc!H$50:H$64,Calc!$D$20))))
B9: 3 | C9: =IF(Calc!$B$4=0,"",EDATE(Start!$D$11,2)) | D9: =IF(OR(Calc!$B$4=0,$B9>IF(Start!$D$10="Avalanche",Calc!$B$3,Calc!$B$2)),"",SUM(G9,I9,K9,M9,O9,Q9,S9,U9,W9,Y9,AA9,AC9,AE9,AG9,AI9)) | E9: =IF(OR(Calc!$B$4=0,$B9>IF(Start!$D$10="Avalanche",Calc!$B$3,Calc!$B$2)),"",IF(Start!$D$10="Avalanche",Calc!I$72,Calc!I$47)) | F9: =IF(Calc!$B$4=0,"",IF($B9>IF(Start!$D$10="Avalanche",Calc!$B$3,Calc!$B$2),NA(),SUM(H9,J9,L9,N9,P9,R9,T9,V9,X9,Z9,AB9,AD9,AF9,AH9,AJ9))) | G9: =IF(H9="","",N(H8)*(1+Start!$E$14/12)-H9) | H9: =IF(OR(OR(Calc!$B$4=0,$B9>IF(Start!$D$10="Avalanche",Calc!$B$3,Calc!$B$2)),Calc!$B$6=0),"",IF(N(H8)<=0.005,"",IF(Start!$D$10="Avalanche",INDEX(Calc!K$75:K$89,Calc!$F$6),INDEX(Calc!K$50:K$64,Calc!$D$6)))) | I9: =IF(J9="","",N(J8)*(1+Start!$E$15/12)-J9) | J9: =IF(OR(OR(Calc!$B$4=0,$B9>IF(Start!$D$10="Avalanche",Calc!$B$3,Calc!$B$2)),Calc!$B$7=0),"",IF(N(J8)<=0.005,"",IF(Start!$D$10="Avalanche",INDEX(Calc!K$75:K$89,Calc!$F$7),INDEX(Calc!K$50:K$64,Calc!$D$7)))) | K9: =IF(L9="","",N(L8)*(1+Start!$E$16/12)-L9) | L9: =IF(OR(OR(Calc!$B$4=0,$B9>IF(Start!$D$10="Avalanche",Calc!$B$3,Calc!$B$2)),Calc!$B$8=0),"",IF(N(L8)<=0.005,"",IF(Start!$D$10="Avalanche",INDEX(Calc!K$75:K$89,Calc!$F$8),INDEX(Calc!K$50:K$64,Calc!$D$8)))) | M9: =IF(N9="","",N(N8)*(1+Start!$E$17/12)-N9) | N9: =IF(OR(OR(Calc!$B$4=0,$B9>IF(Start!$D$10="Avalanche",Calc!$B$3,Calc!$B$2)),Calc!$B$9=0),"",IF(N(N8)<=0.005,"",IF(Start!$D$10="Avalanche",INDEX(Calc!K$75:K$89,Calc!$F$9),INDEX(Calc!K$50:K$64,Calc!$D$9)))) | O9: =IF(P9="","",N(P8)*(1+Start!$E$18/12)-P9) | P9: =IF(OR(OR(Calc!$B$4=0,$B9>IF(Start!$D$10="Avalanche",Calc!$B$3,Calc!$B$2)),Calc!$B$10=0),"",IF(N(P8)<=0.005,"",IF(Start!$D$10="Avalanche",INDEX(Calc!K$75:K$89,Calc!$F$10),INDEX(Calc!K$50:K$64,Calc!$D$10)))) | Q9: =IF(R9="","",N(R8)*(1+Start!$E$19/12)-R9) | R9: =IF(OR(OR(Calc!$B$4=0,$B9>IF(Start!$D$10="Avalanche",Calc!$B$3,Calc!$B$2)),Calc!$B$11=0),"",IF(N(R8)<=0.005,"",IF(Start!$D$10="Avalanche",INDEX(Calc!K$75:K$89,Calc!$F$11),INDEX(Calc!K$50:K$64,Calc!$D$11)))) | S9: =IF(T9="","",N(T8)*(1+Start!$E$20/12)-T9) | T9: =IF(OR(OR(Calc!$B$4=0,$B9>IF(Start!$D$10="Avalanche",Calc!$B$3,Calc!$B$2)),Calc!$B$12=0),"",IF(N(T8)<=0.005,"",IF(Start!$D$10="Avalanche",INDEX(Calc!K$75:K$89,Calc!$F$12),INDEX(Calc!K$50:K$64,Calc!$D$12)))) | U9: =IF(V9="","",N(V8)*(1+Start!$E$21/12)-V9) | V9: =IF(OR(OR(Calc!$B$4=0,$B9>IF(Start!$D$10="Avalanche",Calc!$B$3,Calc!$B$2)),Calc!$B$13=0),"",IF(N(V8)<=0.005,"",IF(Start!$D$10="Avalanche",INDEX(Calc!K$75:K$89,Calc!$F$13),INDEX(Calc!K$50:K$64,Calc!$D$13)))) | W9: =IF(X9="","",N(X8)*(1+Start!$E$22/12)-X9) | X9: =IF(OR(OR(Calc!$B$4=0,$B9>IF(Start!$D$10="Avalanche",Calc!$B$3,Calc!$B$2)),Calc!$B$14=0),"",IF(N(X8)<=0.005,"",IF(Start!$D$10="Avalanche",INDEX(Calc!K$75:K$89,Calc!$F$14),INDEX(Calc!K$50:K$64,Calc!$D$14)))) | Y9: =IF(Z9="","",N(Z8)*(1+Start!$E$23/12)-Z9) | Z9: =IF(OR(OR(Calc!$B$4=0,$B9>IF(Start!$D$10="Avalanche",Calc!$B$3,Calc!$B$2)),Calc!$B$15=0),"",IF(N(Z8)<=0.005,"",IF(Start!$D$10="Avalanche",INDEX(Calc!K$75:K$89,Calc!$F$15),INDEX(Calc!K$50:K$64,Calc!$D$15)))) | AA9: =IF(AB9="","",N(AB8)*(1+Start!$E$24/12)-AB9) | AB9: =IF(OR(OR(Calc!$B$4=0,$B9>IF(Start!$D$10="Avalanche",Calc!$B$3,Calc!$B$2)),Calc!$B$16=0),"",IF(N(AB8)<=0.005,"",IF(Start!$D$10="Avalanche",INDEX(Calc!K$75:K$89,Calc!$F$16),INDEX(Calc!K$50:K$64,Calc!$D$16)))) | AC9: =IF(AD9="","",N(AD8)*(1+Start!$E$25/12)-AD9) | AD9: =IF(OR(OR(Calc!$B$4=0,$B9>IF(Start!$D$10="Avalanche",Calc!$B$3,Calc!$B$2)),Calc!$B$17=0),"",IF(N(AD8)<=0.005,"",IF(Start!$D$10="Avalanche",INDEX(Calc!K$75:K$89,Calc!$F$17),INDEX(Calc!K$50:K$64,Calc!$D$17)))) | AE9: =IF(AF9="","",N(AF8)*(1+Start!$E$26/12)-AF9) | AF9: =IF(OR(OR(Calc!$B$4=0,$B9>IF(Start!$D$10="Avalanche",Calc!$B$3,Calc!$B$2)),Calc!$B$18=0),"",IF(N(AF8)<=0.005,"",IF(Start!$D$10="Avalanche",INDEX(Calc!K$75:K$89,Calc!$F$18),INDEX(Calc!K$50:K$64,Calc!$D$18)))) | AG9: =IF(AH9="","",N(AH8)*(1+Start!$E$27/12)-AH9) | AH9: =IF(OR(OR(Calc!$B$4=0,$B9>IF(Start!$D$10="Avalanche",Calc!$B$3,Calc!$B$2)),Calc!$B$19=0),"",IF(N(AH8)<=0.005,"",IF(Start!$D$10="Avalanche",INDEX(Calc!K$75:K$89,Calc!$F$19),INDEX(Calc!K$50:K$64,Calc!$D$19)))) | AI9: =IF(AJ9="","",N(AJ8)*(1+Start!$E$28/12)-AJ9) | AJ9: =IF(OR(OR(Calc!$B$4=0,$B9>IF(Start!$D$10="Avalanche",Calc!$B$3,Calc!$B$2)),Calc!$B$20=0),"",IF(N(AJ8)<=0.005,"",IF(Start!$D$10="Avalanche",INDEX(Calc!K$75:K$89,Calc!$F$20),INDEX(Calc!K$50:K$64,Calc!$D$20))))
B10: 4 | C10: =IF(Calc!$B$4=0,"",EDATE(Start!$D$11,3)) | D10: =IF(OR(Calc!$B$4=0,$B10>IF(Start!$D$10="Avalanche",Calc!$B$3,Calc!$B$2)),"",SUM(G10,I10,K10,M10,O10,Q10,S10,U10,W10,Y10,AA10,AC10,AE10,AG10,AI10)) | E10: =IF(OR(Calc!$B$4=0,$B10>IF(Start!$D$10="Avalanche",Calc!$B$3,Calc!$B$2)),"",IF(Start!$D$10="Avalanche",Calc!L$72,Calc!L$47)) | F10: =IF(Calc!$B$4=0,"",IF($B10>IF(Start!$D$10="Avalanche",Calc!$B$3,Calc!$B$2),NA(),SUM(H10,J10,L10,N10,P10,R10,T10,V10,X10,Z10,AB10,AD10,AF10,AH10,AJ10))) | G10: =IF(H10="","",N(H9)*(1+Start!$E$14/12)-H10) | H10: =IF(OR(OR(Calc!$B$4=0,$B10>IF(Start!$D$10="Avalanche",Calc!$B$3,Calc!$B$2)),Calc!$B$6=0),"",IF(N(H9)<=0.005,"",IF(Start!$D$10="Avalanche",INDEX(Calc!N$75:N$89,Calc!$F$6),INDEX(Calc!N$50:N$64,Calc!$D$6)))) | I10: =IF(J10="","",N(J9)*(1+Start!$E$15/12)-J10) | J10: =IF(OR(OR(Calc!$B$4=0,$B10>IF(Start!$D$10="Avalanche",Calc!$B$3,Calc!$B$2)),Calc!$B$7=0),"",IF(N(J9)<=0.005,"",IF(Start!$D$10="Avalanche",INDEX(Calc!N$75:N$89,Calc!$F$7),INDEX(Calc!N$50:N$64,Calc!$D$7)))) | K10: =IF(L10="","",N(L9)*(1+Start!$E$16/12)-L10) | L10: =IF(OR(OR(Calc!$B$4=0,$B10>IF(Start!$D$10="Avalanche",Calc!$B$3,Calc!$B$2)),Calc!$B$8=0),"",IF(N(L9)<=0.005,"",IF(Start!$D$10="Avalanche",INDEX(Calc!N$75:N$89,Calc!$F$8),INDEX(Calc!N$50:N$64,Calc!$D$8)))) | M10: =IF(N10="","",N(N9)*(1+Start!$E$17/12)-N10) | N10: =IF(OR(OR(Calc!$B$4=0,$B10>IF(Start!$D$10="Avalanche",Calc!$B$3,Calc!$B$2)),Calc!$B$9=0),"",IF(N(N9)<=0.005,"",IF(Start!$D$10="Avalanche",INDEX(Calc!N$75:N$89,Calc!$F$9),INDEX(Calc!N$50:N$64,Calc!$D$9)))) | O10: =IF(P10="","",N(P9)*(1+Start!$E$18/12)-P10) | P10: =IF(OR(OR(Calc!$B$4=0,$B10>IF(Start!$D$10="Avalanche",Calc!$B$3,Calc!$B$2)),Calc!$B$10=0),"",IF(N(P9)<=0.005,"",IF(Start!$D$10="Avalanche",INDEX(Calc!N$75:N$89,Calc!$F$10),INDEX(Calc!N$50:N$64,Calc!$D$10)))) | Q10: =IF(R10="","",N(R9)*(1+Start!$E$19/12)-R10) | R10: =IF(OR(OR(Calc!$B$4=0,$B10>IF(Start!$D$10="Avalanche",Calc!$B$3,Calc!$B$2)),Calc!$B$11=0),"",IF(N(R9)<=0.005,"",IF(Start!$D$10="Avalanche",INDEX(Calc!N$75:N$89,Calc!$F$11),INDEX(Calc!N$50:N$64,Calc!$D$11)))) | S10: =IF(T10="","",N(T9)*(1+Start!$E$20/12)-T10) | T10: =IF(OR(OR(Calc!$B$4=0,$B10>IF(Start!$D$10="Avalanche",Calc!$B$3,Calc!$B$2)),Calc!$B$12=0),"",IF(N(T9)<=0.005,"",IF(Start!$D$10="Avalanche",INDEX(Calc!N$75:N$89,Calc!$F$12),INDEX(Calc!N$50:N$64,Calc!$D$12)))) | U10: =IF(V10="","",N(V9)*(1+Start!$E$21/12)-V10) | V10: =IF(OR(OR(Calc!$B$4=0,$B10>IF(Start!$D$10="Avalanche",Calc!$B$3,Calc!$B$2)),Calc!$B$13=0),"",IF(N(V9)<=0.005,"",IF(Start!$D$10="Avalanche",INDEX(Calc!N$75:N$89,Calc!$F$13),INDEX(Calc!N$50:N$64,Calc!$D$13)))) | W10: =IF(X10="","",N(X9)*(1+Start!$E$22/12)-X10) | X10: =IF(OR(OR(Calc!$B$4=0,$B10>IF(Start!$D$10="Avalanche",Calc!$B$3,Calc!$B$2)),Calc!$B$14=0),"",IF(N(X9)<=0.005,"",IF(Start!$D$10="Avalanche",INDEX(Calc!N$75:N$89,Calc!$F$14),INDEX(Calc!N$50:N$64,Calc!$D$14)))) | Y10: =IF(Z10="","",N(Z9)*(1+Start!$E$23/12)-Z10) | Z10: =IF(OR(OR(Calc!$B$4=0,$B10>IF(Start!$D$10="Avalanche",Calc!$B$3,Calc!$B$2)),Calc!$B$15=0),"",IF(N(Z9)<=0.005,"",IF(Start!$D$10="Avalanche",INDEX(Calc!N$75:N$89,Calc!$F$15),INDEX(Calc!N$50:N$64,Calc!$D$15)))) | AA10: =IF(AB10="","",N(AB9)*(1+Start!$E$24/12)-AB10) | AB10: =IF(OR(OR(Calc!$B$4=0,$B10>IF(Start!$D$10="Avalanche",Calc!$B$3,Calc!$B$2)),Calc!$B$16=0),"",IF(N(AB9)<=0.005,"",IF(Start!$D$10="Avalanche",INDEX(Calc!N$75:N$89,Calc!$F$16),INDEX(Calc!N$50:N$64,Calc!$D$16)))) | AC10: =IF(AD10="","",N(AD9)*(1+Start!$E$25/12)-AD10) | AD10: =IF(OR(OR(Calc!$B$4=0,$B10>IF(Start!$D$10="Avalanche",Calc!$B$3,Calc!$B$2)),Calc!$B$17=0),"",IF(N(AD9)<=0.005,"",IF(Start!$D$10="Avalanche",INDEX(Calc!N$75:N$89,Calc!$F$17),INDEX(Calc!N$50:N$64,Calc!$D$17)))) | AE10: =IF(AF10="","",N(AF9)*(1+Start!$E$26/12)-AF10) | AF10: =IF(OR(OR(Calc!$B$4=0,$B10>IF(Start!$D$10="Avalanche",Calc!$B$3,Calc!$B$2)),Calc!$B$18=0),"",IF(N(AF9)<=0.005,"",IF(Start!$D$10="Avalanche",INDEX(Calc!N$75:N$89,Calc!$F$18),INDEX(Calc!N$50:N$64,Calc!$D$18)))) | AG10: =IF(AH10="","",N(AH9)*(1+Start!$E$27/12)-AH10) | AH10: =IF(OR(OR(Calc!$B$4=0,$B10>IF(Start!$D$10="Avalanche",Calc!$B$3,Calc!$B$2)),Calc!$B$19=0),"",IF(N(AH9)<=0.005,"",IF(Start!$D$10="Avalanche",INDEX(Calc!N$75:N$89,Calc!$F$19),INDEX(Calc!N$50:N$64,Calc!$D$19)))) | AI10: =IF(AJ10="","",N(AJ9)*(1+Start!$E$28/12)-AJ10) | AJ10: =IF(OR(OR(Calc!$B$4=0,$B10>IF(Start!$D$10="Avalanche",Calc!$B$3,Calc!$B$2)),Calc!$B$20=0),"",IF(N(AJ9)<=0.005,"",IF(Start!$D$10="Avalanche",INDEX(Calc!N$75:N$89,Calc!$F$20),INDEX(Calc!N$50:N$64,Calc!$D$20))))
B11: 5 | C11: =IF(Calc!$B$4=0,"",EDATE(Start!$D$11,4)) | D11: =IF(OR(Calc!$B$4=0,$B11>IF(Start!$D$10="Avalanche",Calc!$B$3,Calc!$B$2)),"",SUM(G11,I11,K11,M11,O11,Q11,S11,U11,W11,Y11,AA11,AC11,AE11,AG11,AI11)) | E11: =IF(OR(Calc!$B$4=0,$B11>IF(Start!$D$10="Avalanche",Calc!$B$3,Calc!$B$2)),"",IF(Start!$D$10="Avalanche",Calc!O$72,Calc!O$47)) | F11: =IF(Calc!$B$4=0,"",IF($B11>IF(Start!$D$10="Avalanche",Calc!$B$3,Calc!$B$2),NA(),SUM(H11,J11,L11,N11,P11,R11,T11,V11,X11,Z11,AB11,AD11,AF11,AH11,AJ11))) | G11: =IF(H11="","",N(H10)*(1+Start!$E$14/12)-H11) | H11: =IF(OR(OR(Calc!$B$4=0,$B11>IF(Start!$D$10="Avalanche",Calc!$B$3,Calc!$B$2)),Calc!$B$6=0),"",IF(N(H10)<=0.005,"",IF(Start!$D$10="Avalanche",INDEX(Calc!Q$75:Q$89,Calc!$F$6),INDEX(Calc!Q$50:Q$64,Calc!$D$6)))) | I11: =IF(J11="","",N(J10)*(1+Start!$E$15/12)-J11) | J11: =IF(OR(OR(Calc!$B$4=0,$B11>IF(Start!$D$10="Avalanche",Calc!$B$3,Calc!$B$2)),Calc!$B$7=0),"",IF(N(J10)<=0.005,"",IF(Start!$D$10="Avalanche",INDEX(Calc!Q$75:Q$89,Calc!$F$7),INDEX(Calc!Q$50:Q$64,Calc!$D$7)))) | K11: =IF(L11="","",N(L10)*(1+Start!$E$16/12)-L11) | L11: =IF(OR(OR(Calc!$B$4=0,$B11>IF(Start!$D$10="Avalanche",Calc!$B$3,Calc!$B$2)),Calc!$B$8=0),"",IF(N(L10)<=0.005,"",IF(Start!$D$10="Avalanche",INDEX(Calc!Q$75:Q$89,Calc!$F$8),INDEX(Calc!Q$50:Q$64,Calc!$D$8)))) | M11: =IF(N11="","",N(N10)*(1+Start!$E$17/12)-N11) | N11: =IF(OR(OR(Calc!$B$4=0,$B11>IF(Start!$D$10="Avalanche",Calc!$B$3,Calc!$B$2)),Calc!$B$9=0),"",IF(N(N10)<=0.005,"",IF(Start!$D$10="Avalanche",INDEX(Calc!Q$75:Q$89,Calc!$F$9),INDEX(Calc!Q$50:Q$64,Calc!$D$9)))) | O11: =IF(P11="","",N(P10)*(1+Start!$E$18/12)-P11) | P11: =IF(OR(OR(Calc!$B$4=0,$B11>IF(Start!$D$10="Avalanche",Calc!$B$3,Calc!$B$2)),Calc!$B$10=0),"",IF(N(P10)<=0.005,"",IF(Start!$D$10="Avalanche",INDEX(Calc!Q$75:Q$89,Calc!$F$10),INDEX(Calc!Q$50:Q$64,Calc!$D$10)))) | Q11: =IF(R11="","",N(R10)*(1+Start!$E$19/12)-R11) | R11: =IF(OR(OR(Calc!$B$4=0,$B11>IF(Start!$D$10="Avalanche",Calc!$B$3,Calc!$B$2)),Calc!$B$11=0),"",IF(N(R10)<=0.005,"",IF(Start!$D$10="Avalanche",INDEX(Calc!Q$75:Q$89,Calc!$F$11),INDEX(Calc!Q$50:Q$64,Calc!$D$11)))) | S11: =IF(T11="","",N(T10)*(1+Start!$E$20/12)-T11) | T11: =IF(OR(OR(Calc!$B$4=0,$B11>IF(Start!$D$10="Avalanche",Calc!$B$3,Calc!$B$2)),Calc!$B$12=0),"",IF(N(T10)<=0.005,"",IF(Start!$D$10="Avalanche",INDEX(Calc!Q$75:Q$89,Calc!$F$12),INDEX(Calc!Q$50:Q$64,Calc!$D$12)))) | U11: =IF(V11="","",N(V10)*(1+Start!$E$21/12)-V11) | V11: =IF(OR(OR(Calc!$B$4=0,$B11>IF(Start!$D$10="Avalanche",Calc!$B$3,Calc!$B$2)),Calc!$B$13=0),"",IF(N(V10)<=0.005,"",IF(Start!$D$10="Avalanche",INDEX(Calc!Q$75:Q$89,Calc!$F$13),INDEX(Calc!Q$50:Q$64,Calc!$D$13)))) | W11: =IF(X11="","",N(X10)*(1+Start!$E$22/12)-X11) | X11: =IF(OR(OR(Calc!$B$4=0,$B11>IF(Start!$D$10="Avalanche",Calc!$B$3,Calc!$B$2)),Calc!$B$14=0),"",IF(N(X10)<=0.005,"",IF(Start!$D$10="Avalanche",INDEX(Calc!Q$75:Q$89,Calc!$F$14),INDEX(Calc!Q$50:Q$64,Calc!$D$14)))) | Y11: =IF(Z11="","",N(Z10)*(1+Start!$E$23/12)-Z11) | Z11: =IF(OR(OR(Calc!$B$4=0,$B11>IF(Start!$D$10="Avalanche",Calc!$B$3,Calc!$B$2)),Calc!$B$15=0),"",IF(N(Z10)<=0.005,"",IF(Start!$D$10="Avalanche",INDEX(Calc!Q$75:Q$89,Calc!$F$15),INDEX(Calc!Q$50:Q$64,Calc!$D$15)))) | AA11: =IF(AB11="","",N(AB10)*(1+Start!$E$24/12)-AB11) | AB11: =IF(OR(OR(Calc!$B$4=0,$B11>IF(Start!$D$10="Avalanche",Calc!$B$3,Calc!$B$2)),Calc!$B$16=0),"",IF(N(AB10)<=0.005,"",IF(Start!$D$10="Avalanche",INDEX(Calc!Q$75:Q$89,Calc!$F$16),INDEX(Calc!Q$50:Q$64,Calc!$D$16)))) | AC11: =IF(AD11="","",N(AD10)*(1+Start!$E$25/12)-AD11) | AD11: =IF(OR(OR(Calc!$B$4=0,$B11>IF(Start!$D$10="Avalanche",Calc!$B$3,Calc!$B$2)),Calc!$B$17=0),"",IF(N(AD10)<=0.005,"",IF(Start!$D$10="Avalanche",INDEX(Calc!Q$75:Q$89,Calc!$F$17),INDEX(Calc!Q$50:Q$64,Calc!$D$17)))) | AE11: =IF(AF11="","",N(AF10)*(1+Start!$E$26/12)-AF11) | AF11: =IF(OR(OR(Calc!$B$4=0,$B11>IF(Start!$D$10="Avalanche",Calc!$B$3,Calc!$B$2)),Calc!$B$18=0),"",IF(N(AF10)<=0.005,"",IF(Start!$D$10="Avalanche",INDEX(Calc!Q$75:Q$89,Calc!$F$18),INDEX(Calc!Q$50:Q$64,Calc!$D$18)))) | AG11: =IF(AH11="","",N(AH10)*(1+Start!$E$27/12)-AH11) | AH11: =IF(OR(OR(Calc!$B$4=0,$B11>IF(Start!$D$10="Avalanche",Calc!$B$3,Calc!$B$2)),Calc!$B$19=0),"",IF(N(AH10)<=0.005,"",IF(Start!$D$10="Avalanche",INDEX(Calc!Q$75:Q$89,Calc!$F$19),INDEX(Calc!Q$50:Q$64,Calc!$D$19)))) | AI11: =IF(AJ11="","",N(AJ10)*(1+Start!$E$28/12)-AJ11) | AJ11: =IF(OR(OR(Calc!$B$4=0,$B11>IF(Start!$D$10="Avalanche",Calc!$B$3,Calc!$B$2)),Calc!$B$20=0),"",IF(N(AJ10)<=0.005,"",IF(Start!$D$10="Avalanche",INDEX(Calc!Q$75:Q$89,Calc!$F$20),INDEX(Calc!Q$50:Q$64,Calc!$D$20))))
B12: 6 | C12: =IF(Calc!$B$4=0,"",EDATE(Start!$D$11,5)) | D12: =IF(OR(Calc!$B$4=0,$B12>IF(Start!$D$10="Avalanche",Calc!$B$3,Calc!$B$2)),"",SUM(G12,I12,K12,M12,O12,Q12,S12,U12,W12,Y12,AA12,AC12,AE12,AG12,AI12)) | E12: =IF(OR(Calc!$B$4=0,$B12>IF(Start!$D$10="Avalanche",Calc!$B$3,Calc!$B$2)),"",IF(Start!$D$10="Avalanche",Calc!R$72,Calc!R$47)) | F12: =IF(Calc!$B$4=0,"",IF($B12>IF(Start!$D$10="Avalanche",Calc!$B$3,Calc!$B$2),NA(),SUM(H12,J12,L12,N12,P12,R12,T12,V12,X12,Z12,AB12,AD12,AF12,AH12,AJ12))) | G12: =IF(H12="","",N(H11)*(1+Start!$E$14/12)-H12) | H12: =IF(OR(OR(Calc!$B$4=0,$B12>IF(Start!$D$10="Avalanche",Calc!$B$3,Calc!$B$2)),Calc!$B$6=0),"",IF(N(H11)<=0.005,"",IF(Start!$D$10="Avalanche",INDEX(Calc!T$75:T$89,Calc!$F$6),INDEX(Calc!T$50:T$64,Calc!$D$6)))) | I12: =IF(J12="","",N(J11)*(1+Start!$E$15/12)-J12) | J12: =IF(OR(OR(Calc!$B$4=0,$B12>IF(Start!$D$10="Avalanche",Calc!$B$3,Calc!$B$2)),Calc!$B$7=0),"",IF(N(J11)<=0.005,"",IF(Start!$D$10="Avalanche",INDEX(Calc!T$75:T$89,Calc!$F$7),INDEX(Calc!T$50:T$64,Calc!$D$7)))) | K12: =IF(L12="","",N(L11)*(1+Start!$E$16/12)-L12) | L12: =IF(OR(OR(Calc!$B$4=0,$B12>IF(Start!$D$10="Avalanche",Calc!$B$3,Calc!$B$2)),Calc!$B$8=0),"",IF(N(L11)<=0.005,"",IF(Start!$D$10="Avalanche",INDEX(Calc!T$75:T$89,Calc!$F$8),INDEX(Calc!T$50:T$64,Calc!$D$8)))) | M12: =IF(N12="","",N(N11)*(1+Start!$E$17/12)-N12) | N12: =IF(OR(OR(Calc!$B$4=0,$B12>IF(Start!$D$10="Avalanche",Calc!$B$3,Calc!$B$2)),Calc!$B$9=0),"",IF(N(N11)<=0.005,"",IF(Start!$D$10="Avalanche",INDEX(Calc!T$75:T$89,Calc!$F$9),INDEX(Calc!T$50:T$64,Calc!$D$9)))) | O12: =IF(P12="","",N(P11)*(1+Start!$E$18/12)-P12) | P12: =IF(OR(OR(Calc!$B$4=0,$B12>IF(Start!$D$10="Avalanche",Calc!$B$3,Calc!$B$2)),Calc!$B$10=0),"",IF(N(P11)<=0.005,"",IF(Start!$D$10="Avalanche",INDEX(Calc!T$75:T$89,Calc!$F$10),INDEX(Calc!T$50:T$64,Calc!$D$10)))) | Q12: =IF(R12="","",N(R11)*(1+Start!$E$19/12)-R12) | R12: =IF(OR(OR(Calc!$B$4=0,$B12>IF(Start!$D$10="Avalanche",Calc!$B$3,Calc!$B$2)),Calc!$B$11=0),"",IF(N(R11)<=0.005,"",IF(Start!$D$10="Avalanche",INDEX(Calc!T$75:T$89,Calc!$F$11),INDEX(Calc!T$50:T$64,Calc!$D$11)))) | S12: =IF(T12="","",N(T11)*(1+Start!$E$20/12)-T12) | T12: =IF(OR(OR(Calc!$B$4=0,$B12>IF(Start!$D$10="Avalanche",Calc!$B$3,Calc!$B$2)),Calc!$B$12=0),"",IF(N(T11)<=0.005,"",IF(Start!$D$10="Avalanche",INDEX(Calc!T$75:T$89,Calc!$F$12),INDEX(Calc!T$50:T$64,Calc!$D$12)))) | U12: =IF(V12="","",N(V11)*(1+Start!$E$21/12)-V12) | V12: =IF(OR(OR(Calc!$B$4=0,$B12>IF(Start!$D$10="Avalanche",Calc!$B$3,Calc!$B$2)),Calc!$B$13=0),"",IF(N(V11)<=0.005,"",IF(Start!$D$10="Avalanche",INDEX(Calc!T$75:T$89,Calc!$F$13),INDEX(Calc!T$50:T$64,Calc!$D$13)))) | W12: =IF(X12="","",N(X11)*(1+Start!$E$22/12)-X12) | X12: =IF(OR(OR(Calc!$B$4=0,$B12>IF(Start!$D$10="Avalanche",Calc!$B$3,Calc!$B$2)),Calc!$B$14=0),"",IF(N(X11)<=0.005,"",IF(Start!$D$10="Avalanche",INDEX(Calc!T$75:T$89,Calc!$F$14),INDEX(Calc!T$50:T$64,Calc!$D$14)))) | Y12: =IF(Z12="","",N(Z11)*(1+Start!$E$23/12)-Z12) | Z12: =IF(OR(OR(Calc!$B$4=0,$B12>IF(Start!$D$10="Avalanche",Calc!$B$3,Calc!$B$2)),Calc!$B$15=0),"",IF(N(Z11)<=0.005,"",IF(Start!$D$10="Avalanche",INDEX(Calc!T$75:T$89,Calc!$F$15),INDEX(Calc!T$50:T$64,Calc!$D$15)))) | AA12: =IF(AB12="","",N(AB11)*(1+Start!$E$24/12)-AB12) | AB12: =IF(OR(OR(Calc!$B$4=0,$B12>IF(Start!$D$10="Avalanche",Calc!$B$3,Calc!$B$2)),Calc!$B$16=0),"",IF(N(AB11)<=0.005,"",IF(Start!$D$10="Avalanche",INDEX(Calc!T$75:T$89,Calc!$F$16),INDEX(Calc!T$50:T$64,Calc!$D$16)))) | AC12: =IF(AD12="","",N(AD11)*(1+Start!$E$25/12)-AD12) | AD12: =IF(OR(OR(Calc!$B$4=0,$B12>IF(Start!$D$10="Avalanche",Calc!$B$3,Calc!$B$2)),Calc!$B$17=0),"",IF(N(AD11)<=0.005,"",IF(Start!$D$10="Avalanche",INDEX(Calc!T$75:T$89,Calc!$F$17),INDEX(Calc!T$50:T$64,Calc!$D$17)))) | AE12: =IF(AF12="","",N(AF11)*(1+Start!$E$26/12)-AF12) | AF12: =IF(OR(OR(Calc!$B$4=0,$B12>IF(Start!$D$10="Avalanche",Calc!$B$3,Calc!$B$2)),Calc!$B$18=0),"",IF(N(AF11)<=0.005,"",IF(Start!$D$10="Avalanche",INDEX(Calc!T$75:T$89,Calc!$F$18),INDEX(Calc!T$50:T$64,Calc!$D$18)))) | AG12: =IF(AH12="","",N(AH11)*(1+Start!$E$27/12)-AH12) | AH12: =IF(OR(OR(Calc!$B$4=0,$B12>IF(Start!$D$10="Avalanche",Calc!$B$3,Calc!$B$2)),Calc!$B$19=0),"",IF(N(AH11)<=0.005,"",IF(Start!$D$10="Avalanche",INDEX(Calc!T$75:T$89,Calc!$F$19),INDEX(Calc!T$50:T$64,Calc!$D$19)))) | AI12: =IF(AJ12="","",N(AJ11)*(1+Start!$E$28/12)-AJ12) | AJ12: =IF(OR(OR(Calc!$B$4=0,$B12>IF(Start!$D$10="Avalanche",Calc!$B$3,Calc!$B$2)),Calc!$B$20=0),"",IF(N(AJ11)<=0.005,"",IF(Start!$D$10="Avalanche",INDEX(Calc!T$75:T$89,Calc!$F$20),INDEX(Calc!T$50:T$64,Calc!$D$20))))
B13: 7 | C13: =IF(Calc!$B$4=0,"",EDATE(Start!$D$11,6)) | D13: =IF(OR(Calc!$B$4=0,$B13>IF(Start!$D$10="Avalanche",Calc!$B$3,Calc!$B$2)),"",SUM(G13,I13,K13,M13,O13,Q13,S13,U13,W13,Y13,AA13,AC13,AE13,AG13,AI13)) | E13: =IF(OR(Calc!$B$4=0,$B13>IF(Start!$D$10="Avalanche",Calc!$B$3,Calc!$B$2)),"",IF(Start!$D$10="Avalanche",Calc!U$72,Calc!U$47)) | F13: =IF(Calc!$B$4=0,"",IF($B13>IF(Start!$D$10="Avalanche",Calc!$B$3,Calc!$B$2),NA(),SUM(H13,J13,L13,N13,P13,R13,T13,V13,X13,Z13,AB13,AD13,AF13,AH13,AJ13))) | G13: =IF(H13="","",N(H12)*(1+Start!$E$14/12)-H13) | H13: =IF(OR(OR(Calc!$B$4=0,$B13>IF(Start!$D$10="Avalanche",Calc!$B$3,Calc!$B$2)),Calc!$B$6=0),"",IF(N(H12)<=0.005,"",IF(Start!$D$10="Avalanche",INDEX(Calc!W$75:W$89,Calc!$F$6),INDEX(Calc!W$50:W$64,Calc!$D$6)))) | I13: =IF(J13="","",N(J12)*(1+Start!$E$15/12)-J13) | J13: =IF(OR(OR(Calc!$B$4=0,$B13>IF(Start!$D$10="Avalanche",Calc!$B$3,Calc!$B$2)),Calc!$B$7=0),"",IF(N(J12)<=0.005,"",IF(Start!$D$10="Avalanche",INDEX(Calc!W$75:W$89,Calc!$F$7),INDEX(Calc!W$50:W$64,Calc!$D$7)))) | K13: =IF(L13="","",N(L12)*(1+Start!$E$16/12)-L13) | L13: =IF(OR(OR(Calc!$B$4=0,$B13>IF(Start!$D$10="Avalanche",Calc!$B$3,Calc!$B$2)),Calc!$B$8=0),"",IF(N(L12)<=0.005,"",IF(Start!$D$10="Avalanche",INDEX(Calc!W$75:W$89,Calc!$F$8),INDEX(Calc!W$50:W$64,Calc!$D$8)))) | M13: =IF(N13="","",N(N12)*(1+Start!$E$17/12)-N13) | N13: =IF(OR(OR(Calc!$B$4=0,$B13>IF(Start!$D$10="Avalanche",Calc!$B$3,Calc!$B$2)),Calc!$B$9=0),"",IF(N(N12)<=0.005,"",IF(Start!$D$10="Avalanche",INDEX(Calc!W$75:W$89,Calc!$F$9),INDEX(Calc!W$50:W$64,Calc!$D$9)))) | O13: =IF(P13="","",N(P12)*(1+Start!$E$18/12)-P13) | P13: =IF(OR(OR(Calc!$B$4=0,$B13>IF(Start!$D$10="Avalanche",Calc!$B$3,Calc!$B$2)),Calc!$B$10=0),"",IF(N(P12)<=0.005,"",IF(Start!$D$10="Avalanche",INDEX(Calc!W$75:W$89,Calc!$F$10),INDEX(Calc!W$50:W$64,Calc!$D$10)))) | Q13: =IF(R13="","",N(R12)*(1+Start!$E$19/12)-R13) | R13: =IF(OR(OR(Calc!$B$4=0,$B13>IF(Start!$D$10="Avalanche",Calc!$B$3,Calc!$B$2)),Calc!$B$11=0),"",IF(N(R12)<=0.005,"",IF(Start!$D$10="Avalanche",INDEX(Calc!W$75:W$89,Calc!$F$11),INDEX(Calc!W$50:W$64,Calc!$D$11)))) | S13: =IF(T13="","",N(T12)*(1+Start!$E$20/12)-T13) | T13: =IF(OR(OR(Calc!$B$4=0,$B13>IF(Start!$D$10="Avalanche",Calc!$B$3,Calc!$B$2)),Calc!$B$12=0),"",IF(N(T12)<=0.005,"",IF(Start!$D$10="Avalanche",INDEX(Calc!W$75:W$89,Calc!$F$12),INDEX(Calc!W$50:W$64,Calc!$D$12)))) | U13: =IF(V13="","",N(V12)*(1+Start!$E$21/12)-V13) | V13: =IF(OR(OR(Calc!$B$4=0,$B13>IF(Start!$D$10="Avalanche",Calc!$B$3,Calc!$B$2)),Calc!$B$13=0),"",IF(N(V12)<=0.005,"",IF(Start!$D$10="Avalanche",INDEX(Calc!W$75:W$89,Calc!$F$13),INDEX(Calc!W$50:W$64,Calc!$D$13)))) | W13: =IF(X13="","",N(X12)*(1+Start!$E$22/12)-X13) | X13: =IF(OR(OR(Calc!$B$4=0,$B13>IF(Start!$D$10="Avalanche",Calc!$B$3,Calc!$B$2)),Calc!$B$14=0),"",IF(N(X12)<=0.005,"",IF(Start!$D$10="Avalanche",INDEX(Calc!W$75:W$89,Calc!$F$14),INDEX(Calc!W$50:W$64,Calc!$D$14)))) | Y13: =IF(Z13="","",N(Z12)*(1+Start!$E$23/12)-Z13) | Z13: =IF(OR(OR(Calc!$B$4=0,$B13>IF(Start!$D$10="Avalanche",Calc!$B$3,Calc!$B$2)),Calc!$B$15=0),"",IF(N(Z12)<=0.005,"",IF(Start!$D$10="Avalanche",INDEX(Calc!W$75:W$89,Calc!$F$15),INDEX(Calc!W$50:W$64,Calc!$D$15)))) | AA13: =IF(AB13="","",N(AB12)*(1+Start!$E$24/12)-AB13) | AB13: =IF(OR(OR(Calc!$B$4=0,$B13>IF(Start!$D$10="Avalanche",Calc!$B$3,Calc!$B$2)),Calc!$B$16=0),"",IF(N(AB12)<=0.005,"",IF(Start!$D$10="Avalanche",INDEX(Calc!W$75:W$89,Calc!$F$16),INDEX(Calc!W$50:W$64,Calc!$D$16)))) | AC13: =IF(AD13="","",N(AD12)*(1+Start!$E$25/12)-AD13) | AD13: =IF(OR(OR(Calc!$B$4=0,$B13>IF(Start!$D$10="Avalanche",Calc!$B$3,Calc!$B$2)),Calc!$B$17=0),"",IF(N(AD12)<=0.005,"",IF(Start!$D$10="Avalanche",INDEX(Calc!W$75:W$89,Calc!$F$17),INDEX(Calc!W$50:W$64,Calc!$D$17)))) | AE13: =IF(AF13="","",N(AF12)*(1+Start!$E$26/12)-AF13) | AF13: =IF(OR(OR(Calc!$B$4=0,$B13>IF(Start!$D$10="Avalanche",Calc!$B$3,Calc!$B$2)),Calc!$B$18=0),"",IF(N(AF12)<=0.005,"",IF(Start!$D$10="Avalanche",INDEX(Calc!W$75:W$89,Calc!$F$18),INDEX(Calc!W$50:W$64,Calc!$D$18)))) | AG13: =IF(AH13="","",N(AH12)*(1+Start!$E$27/12)-AH13) | AH13: =IF(OR(OR(Calc!$B$4=0,$B13>IF(Start!$D$10="Avalanche",Calc!$B$3,Calc!$B$2)),Calc!$B$19=0),"",IF(N(AH12)<=0.005,"",IF(Start!$D$10="Avalanche",INDEX(Calc!W$75:W$89,Calc!$F$19),INDEX(Calc!W$50:W$64,Calc!$D$19)))) | AI13: =IF(AJ13="","",N(AJ12)*(1+Start!$E$28/12)-AJ13) | AJ13: =IF(OR(OR(Calc!$B$4=0,$B13>IF(Start!$D$10="Avalanche",Calc!$B$3,Calc!$B$2)),Calc!$B$20=0),"",IF(N(AJ12)<=0.005,"",IF(Start!$D$10="Avalanche",INDEX(Calc!W$75:W$89,Calc!$F$20),INDEX(Calc!W$50:W$64,Calc!$D$20))))
B14: 8 | C14: =IF(Calc!$B$4=0,"",EDATE(Start!$D$11,7)) | D14: =IF(OR(Calc!$B$4=0,$B14>IF(Start!$D$10="Avalanche",Calc!$B$3,Calc!$B$2)),"",SUM(G14,I14,K14,M14,O14,Q14,S14,U14,W14,Y14,AA14,AC14,AE14,AG14,AI14)) | E14: =IF(OR(Calc!$B$4=0,$B14>IF(Start!$D$10="Avalanche",Calc!$B$3,Calc!$B$2)),"",IF(Start!$D$10="Avalanche",Calc!X$72,Calc!X$47)) | F14: =IF(Calc!$B$4=0,"",IF($B14>IF(Start!$D$10="Avalanche",Calc!$B$3,Calc!$B$2),NA(),SUM(H14,J14,L14,N14,P14,R14,T14,V14,X14,Z14,AB14,AD14,AF14,AH14,AJ14))) | G14: =IF(H14="","",N(H13)*(1+Start!$E$14/12)-H14) | H14: =IF(OR(OR(Calc!$B$4=0,$B14>IF(Start!$D$10="Avalanche",Calc!$B$3,Calc!$B$2)),Calc!$B$6=0),"",IF(N(H13)<=0.005,"",IF(Start!$D$10="Avalanche",INDEX(Calc!Z$75:Z$89,Calc!$F$6),INDEX(Calc!Z$50:Z$64,Calc!$D$6)))) | I14: =IF(J14="","",N(J13)*(1+Start!$E$15/12)-J14) | J14: =IF(OR(OR(Calc!$B$4=0,$B14>IF(Start!$D$10="Avalanche",Calc!$B$3,Calc!$B$2)),Calc!$B$7=0),"",IF(N(J13)<=0.005,"",IF(Start!$D$10="Avalanche",INDEX(Calc!Z$75:Z$89,Calc!$F$7),INDEX(Calc!Z$50:Z$64,Calc!$D$7)))) | K14: =IF(L14="","",N(L13)*(1+Start!$E$16/12)-L14) | L14: =IF(OR(OR(Calc!$B$4=0,$B14>IF(Start!$D$10="Avalanche",Calc!$B$3,Calc!$B$2)),Calc!$B$8=0),"",IF(N(L13)<=0.005,"",IF(Start!$D$10="Avalanche",INDEX(Calc!Z$75:Z$89,Calc!$F$8),INDEX(Calc!Z$50:Z$64,Calc!$D$8)))) | M14: =IF(N14="","",N(N13)*(1+Start!$E$17/12)-N14) | N14: =IF(OR(OR(Calc!$B$4=0,$B14>IF(Start!$D$10="Avalanche",Calc!$B$3,Calc!$B$2)),Calc!$B$9=0),"",IF(N(N13)<=0.005,"",IF(Start!$D$10="Avalanche",INDEX(Calc!Z$75:Z$89,Calc!$F$9),INDEX(Calc!Z$50:Z$64,Calc!$D$9)))) | O14: =IF(P14="","",N(P13)*(1+Start!$E$18/12)-P14) | P14: =IF(OR(OR(Calc!$B$4=0,$B14>IF(Start!$D$10="Avalanche",Calc!$B$3,Calc!$B$2)),Calc!$B$10=0),"",IF(N(P13)<=0.005,"",IF(Start!$D$10="Avalanche",INDEX(Calc!Z$75:Z$89,Calc!$F$10),INDEX(Calc!Z$50:Z$64,Calc!$D$10)))) | Q14: =IF(R14="","",N(R13)*(1+Start!$E$19/12)-R14) | R14: =IF(OR(OR(Calc!$B$4=0,$B14>IF(Start!$D$10="Avalanche",Calc!$B$3,Calc!$B$2)),Calc!$B$11=0),"",IF(N(R13)<=0.005,"",IF(Start!$D$10="Avalanche",INDEX(Calc!Z$75:Z$89,Calc!$F$11),INDEX(Calc!Z$50:Z$64,Calc!$D$11)))) | S14: =IF(T14="","",N(T13)*(1+Start!$E$20/12)-T14) | T14: =IF(OR(OR(Calc!$B$4=0,$B14>IF(Start!$D$10="Avalanche",Calc!$B$3,Calc!$B$2)),Calc!$B$12=0),"",IF(N(T13)<=0.005,"",IF(Start!$D$10="Avalanche",INDEX(Calc!Z$75:Z$89,Calc!$F$12),INDEX(Calc!Z$50:Z$64,Calc!$D$12)))) | U14: =IF(V14="","",N(V13)*(1+Start!$E$21/12)-V14) | V14: =IF(OR(OR(Calc!$B$4=0,$B14>IF(Start!$D$10="Avalanche",Calc!$B$3,Calc!$B$2)),Calc!$B$13=0),"",IF(N(V13)<=0.005,"",IF(Start!$D$10="Avalanche",INDEX(Calc!Z$75:Z$89,Calc!$F$13),INDEX(Calc!Z$50:Z$64,Calc!$D$13)))) | W14: =IF(X14="","",N(X13)*(1+Start!$E$22/12)-X14) | X14: =IF(OR(OR(Calc!$B$4=0,$B14>IF(Start!$D$10="Avalanche",Calc!$B$3,Calc!$B$2)),Calc!$B$14=0),"",IF(N(X13)<=0.005,"",IF(Start!$D$10="Avalanche",INDEX(Calc!Z$75:Z$89,Calc!$F$14),INDEX(Calc!Z$50:Z$64,Calc!$D$14)))) | Y14: =IF(Z14="","",N(Z13)*(1+Start!$E$23/12)-Z14) | Z14: =IF(OR(OR(Calc!$B$4=0,$B14>IF(Start!$D$10="Avalanche",Calc!$B$3,Calc!$B$2)),Calc!$B$15=0),"",IF(N(Z13)<=0.005,"",IF(Start!$D$10="Avalanche",INDEX(Calc!Z$75:Z$89,Calc!$F$15),INDEX(Calc!Z$50:Z$64,Calc!$D$15)))) | AA14: =IF(AB14="","",N(AB13)*(1+Start!$E$24/12)-AB14) | AB14: =IF(OR(OR(Calc!$B$4=0,$B14>IF(Start!$D$10="Avalanche",Calc!$B$3,Calc!$B$2)),Calc!$B$16=0),"",IF(N(AB13)<=0.005,"",IF(Start!$D$10="Avalanche",INDEX(Calc!Z$75:Z$89,Calc!$F$16),INDEX(Calc!Z$50:Z$64,Calc!$D$16)))) | AC14: =IF(AD14="","",N(AD13)*(1+Start!$E$25/12)-AD14) | AD14: =IF(OR(OR(Calc!$B$4=0,$B14>IF(Start!$D$10="Avalanche",Calc!$B$3,Calc!$B$2)),Calc!$B$17=0),"",IF(N(AD13)<=0.005,"",IF(Start!$D$10="Avalanche",INDEX(Calc!Z$75:Z$89,Calc!$F$17),INDEX(Calc!Z$50:Z$64,Calc!$D$17)))) | AE14: =IF(AF14="","",N(AF13)*(1+Start!$E$26/12)-AF14) | AF14: =IF(OR(OR(Calc!$B$4=0,$B14>IF(Start!$D$10="Avalanche",Calc!$B$3,Calc!$B$2)),Calc!$B$18=0),"",IF(N(AF13)<=0.005,"",IF(Start!$D$10="Avalanche",INDEX(Calc!Z$75:Z$89,Calc!$F$18),INDEX(Calc!Z$50:Z$64,Calc!$D$18)))) | AG14: =IF(AH14="","",N(AH13)*(1+Start!$E$27/12)-AH14) | AH14: =IF(OR(OR(Calc!$B$4=0,$B14>IF(Start!$D$10="Avalanche",Calc!$B$3,Calc!$B$2)),Calc!$B$19=0),"",IF(N(AH13)<=0.005,"",IF(Start!$D$10="Avalanche",INDEX(Calc!Z$75:Z$89,Calc!$F$19),INDEX(Calc!Z$50:Z$64,Calc!$D$19)))) | AI14: =IF(AJ14="","",N(AJ13)*(1+Start!$E$28/12)-AJ14) | AJ14: =IF(OR(OR(Calc!$B$4=0,$B14>IF(Start!$D$10="Avalanche",Calc!$B$3,Calc!$B$2)),Calc!$B$20=0),"",IF(N(AJ13)<=0.005,"",IF(Start!$D$10="Avalanche",INDEX(Calc!Z$75:Z$89,Calc!$F$20),INDEX(Calc!Z$50:Z$64,Calc!$D$20))))
B15: 9 | C15: =IF(Calc!$B$4=0,"",EDATE(Start!$D$11,8)) | D15: =IF(OR(Calc!$B$4=0,$B15>IF(Start!$D$10="Avalanche",Calc!$B$3,Calc!$B$2)),"",SUM(G15,I15,K15,M15,O15,Q15,S15,U15,W15,Y15,AA15,AC15,AE15,AG15,AI15)) | E15: =IF(OR(Calc!$B$4=0,$B15>IF(Start!$D$10="Avalanche",Calc!$B$3,Calc!$B$2)),"",IF(Start!$D$10="Avalanche",Calc!AA$72,Calc!AA$47)) | F15: =IF(Calc!$B$4=0,"",IF($B15>IF(Start!$D$10="Avalanche",Calc!$B$3,Calc!$B$2),NA(),SUM(H15,J15,L15,N15,P15,R15,T15,V15,X15,Z15,AB15,AD15,AF15,AH15,AJ15))) | G15: =IF(H15="","",N(H14)*(1+Start!$E$14/12)-H15) | H15: =IF(OR(OR(Calc!$B$4=0,$B15>IF(Start!$D$10="Avalanche",Calc!$B$3,Calc!$B$2)),Calc!$B$6=0),"",IF(N(H14)<=0.005,"",IF(Start!$D$10="Avalanche",INDEX(Calc!AC$75:AC$89,Calc!$F$6),INDEX(Calc!AC$50:AC$64,Calc!$D$6)))) | I15: =IF(J15="","",N(J14)*(1+Start!$E$15/12)-J15) | J15: =IF(OR(OR(Calc!$B$4=0,$B15>IF(Start!$D$10="Avalanche",Calc!$B$3,Calc!$B$2)),Calc!$B$7=0),"",IF(N(J14)<=0.005,"",IF(Start!$D$10="Avalanche",INDEX(Calc!AC$75:AC$89,Calc!$F$7),INDEX(Calc!AC$50:AC$64,Calc!$D$7)))) | K15: =IF(L15="","",N(L14)*(1+Start!$E$16/12)-L15) | L15: =IF(OR(OR(Calc!$B$4=0,$B15>IF(Start!$D$10="Avalanche",Calc!$B$3,Calc!$B$2)),Calc!$B$8=0),"",IF(N(L14)<=0.005,"",IF(Start!$D$10="Avalanche",INDEX(Calc!AC$75:AC$89,Calc!$F$8),INDEX(Calc!AC$50:AC$64,Calc!$D$8)))) | M15: =IF(N15="","",N(N14)*(1+Start!$E$17/12)-N15) | N15: =IF(OR(OR(Calc!$B$4=0,$B15>IF(Start!$D$10="Avalanche",Calc!$B$3,Calc!$B$2)),Calc!$B$9=0),"",IF(N(N14)<=0.005,"",IF(Start!$D$10="Avalanche",INDEX(Calc!AC$75:AC$89,Calc!$F$9),INDEX(Calc!AC$50:AC$64,Calc!$D$9)))) | O15: =IF(P15="","",N(P14)*(1+Start!$E$18/12)-P15) | P15: =IF(OR(OR(Calc!$B$4=0,$B15>IF(Start!$D$10="Avalanche",Calc!$B$3,Calc!$B$2)),Calc!$B$10=0),"",IF(N(P14)<=0.005,"",IF(Start!$D$10="Avalanche",INDEX(Calc!AC$75:AC$89,Calc!$F$10),INDEX(Calc!AC$50:AC$64,Calc!$D$10)))) | Q15: =IF(R15="","",N(R14)*(1+Start!$E$19/12)-R15) | R15: =IF(OR(OR(Calc!$B$4=0,$B15>IF(Start!$D$10="Avalanche",Calc!$B$3,Calc!$B$2)),Calc!$B$11=0),"",IF(N(R14)<=0.005,"",IF(Start!$D$10="Avalanche",INDEX(Calc!AC$75:AC$89,Calc!$F$11),INDEX(Calc!AC$50:AC$64,Calc!$D$11)))) | S15: =IF(T15="","",N(T14)*(1+Start!$E$20/12)-T15) | T15: =IF(OR(OR(Calc!$B$4=0,$B15>IF(Start!$D$10="Avalanche",Calc!$B$3,Calc!$B$2)),Calc!$B$12=0),"",IF(N(T14)<=0.005,"",IF(Start!$D$10="Avalanche",INDEX(Calc!AC$75:AC$89,Calc!$F$12),INDEX(Calc!AC$50:AC$64,Calc!$D$12)))) | U15: =IF(V15="","",N(V14)*(1+Start!$E$21/12)-V15) | V15: =IF(OR(OR(Calc!$B$4=0,$B15>IF(Start!$D$10="Avalanche",Calc!$B$3,Calc!$B$2)),Calc!$B$13=0),"",IF(N(V14)<=0.005,"",IF(Start!$D$10="Avalanche",INDEX(Calc!AC$75:AC$89,Calc!$F$13),INDEX(Calc!AC$50:AC$64,Calc!$D$13)))) | W15: =IF(X15="","",N(X14)*(1+Start!$E$22/12)-X15) | X15: =IF(OR(OR(Calc!$B$4=0,$B15>IF(Start!$D$10="Avalanche",Calc!$B$3,Calc!$B$2)),Calc!$B$14=0),"",IF(N(X14)<=0.005,"",IF(Start!$D$10="Avalanche",INDEX(Calc!AC$75:AC$89,Calc!$F$14),INDEX(Calc!AC$50:AC$64,Calc!$D$14)))) | Y15: =IF(Z15="","",N(Z14)*(1+Start!$E$23/12)-Z15) | Z15: =IF(OR(OR(Calc!$B$4=0,$B15>IF(Start!$D$10="Avalanche",Calc!$B$3,Calc!$B$2)),Calc!$B$15=0),"",IF(N(Z14)<=0.005,"",IF(Start!$D$10="Avalanche",INDEX(Calc!AC$75:AC$89,Calc!$F$15),INDEX(Calc!AC$50:AC$64,Calc!$D$15)))) | AA15: =IF(AB15="","",N(AB14)*(1+Start!$E$24/12)-AB15) | AB15: =IF(OR(OR(Calc!$B$4=0,$B15>IF(Start!$D$10="Avalanche",Calc!$B$3,Calc!$B$2)),Calc!$B$16=0),"",IF(N(AB14)<=0.005,"",IF(Start!$D$10="Avalanche",INDEX(Calc!AC$75:AC$89,Calc!$F$16),INDEX(Calc!AC$50:AC$64,Calc!$D$16)))) | AC15: =IF(AD15="","",N(AD14)*(1+Start!$E$25/12)-AD15) | AD15: =IF(OR(OR(Calc!$B$4=0,$B15>IF(Start!$D$10="Avalanche",Calc!$B$3,Calc!$B$2)),Calc!$B$17=0),"",IF(N(AD14)<=0.005,"",IF(Start!$D$10="Avalanche",INDEX(Calc!AC$75:AC$89,Calc!$F$17),INDEX(Calc!AC$50:AC$64,Calc!$D$17)))) | AE15: =IF(AF15="","",N(AF14)*(1+Start!$E$26/12)-AF15) | AF15: =IF(OR(OR(Calc!$B$4=0,$B15>IF(Start!$D$10="Avalanche",Calc!$B$3,Calc!$B$2)),Calc!$B$18=0),"",IF(N(AF14)<=0.005,"",IF(Start!$D$10="Avalanche",INDEX(Calc!AC$75:AC$89,Calc!$F$18),INDEX(Calc!AC$50:AC$64,Calc!$D$18)))) | AG15: =IF(AH15="","",N(AH14)*(1+Start!$E$27/12)-AH15) | AH15: =IF(OR(OR(Calc!$B$4=0,$B15>IF(Start!$D$10="Avalanche",Calc!$B$3,Calc!$B$2)),Calc!$B$19=0),"",IF(N(AH14)<=0.005,"",IF(Start!$D$10="Avalanche",INDEX(Calc!AC$75:AC$89,Calc!$F$19),INDEX(Calc!AC$50:AC$64,Calc!$D$19)))) | AI15: =IF(AJ15="","",N(AJ14)*(1+Start!$E$28/12)-AJ15) | AJ15: =IF(OR(OR(Calc!$B$4=0,$B15>IF(Start!$D$10="Avalanche",Calc!$B$3,Calc!$B$2)),Calc!$B$20=0),"",IF(N(AJ14)<=0.005,"",IF(Start!$D$10="Avalanche",INDEX(Calc!AC$75:AC$89,Calc!$F$20),INDEX(Calc!AC$50:AC$64,Calc!$D$20))))
B16: 10 | C16: =IF(Calc!$B$4=0,"",EDATE(Start!$D$11,9)) | D16: =IF(OR(Calc!$B$4=0,$B16>IF(Start!$D$10="Avalanche",Calc!$B$3,Calc!$B$2)),"",SUM(G16,I16,K16,M16,O16,Q16,S16,U16,W16,Y16,AA16,AC16,AE16,AG16,AI16)) | E16: =IF(OR(Calc!$B$4=0,$B16>IF(Start!$D$10="Avalanche",Calc!$B$3,Calc!$B$2)),"",IF(Start!$D$10="Avalanche",Calc!AD$72,Calc!AD$47)) | F16: =IF(Calc!$B$4=0,"",IF($B16>IF(Start!$D$10="Avalanche",Calc!$B$3,Calc!$B$2),NA(),SUM(H16,J16,L16,N16,P16,R16,T16,V16,X16,Z16,AB16,AD16,AF16,AH16,AJ16))) | G16: =IF(H16="","",N(H15)*(1+Start!$E$14/12)-H16) | H16: =IF(OR(OR(Calc!$B$4=0,$B16>IF(Start!$D$10="Avalanche",Calc!$B$3,Calc!$B$2)),Calc!$B$6=0),"",IF(N(H15)<=0.005,"",IF(Start!$D$10="Avalanche",INDEX(Calc!AF$75:AF$89,Calc!$F$6),INDEX(Calc!AF$50:AF$64,Calc!$D$6)))) | I16: =IF(J16="","",N(J15)*(1+Start!$E$15/12)-J16) | J16: =IF(OR(OR(Calc!$B$4=0,$B16>IF(Start!$D$10="Avalanche",Calc!$B$3,Calc!$B$2)),Calc!$B$7=0),"",IF(N(J15)<=0.005,"",IF(Start!$D$10="Avalanche",INDEX(Calc!AF$75:AF$89,Calc!$F$7),INDEX(Calc!AF$50:AF$64,Calc!$D$7)))) | K16: =IF(L16="","",N(L15)*(1+Start!$E$16/12)-L16) | L16: =IF(OR(OR(Calc!$B$4=0,$B16>IF(Start!$D$10="Avalanche",Calc!$B$3,Calc!$B$2)),Calc!$B$8=0),"",IF(N(L15)<=0.005,"",IF(Start!$D$10="Avalanche",INDEX(Calc!AF$75:AF$89,Calc!$F$8),INDEX(Calc!AF$50:AF$64,Calc!$D$8)))) | M16: =IF(N16="","",N(N15)*(1+Start!$E$17/12)-N16) | N16: =IF(OR(OR(Calc!$B$4=0,$B16>IF(Start!$D$10="Avalanche",Calc!$B$3,Calc!$B$2)),Calc!$B$9=0),"",IF(N(N15)<=0.005,"",IF(Start!$D$10="Avalanche",INDEX(Calc!AF$75:AF$89,Calc!$F$9),INDEX(Calc!AF$50:AF$64,Calc!$D$9)))) | O16: =IF(P16="","",N(P15)*(1+Start!$E$18/12)-P16) | P16: =IF(OR(OR(Calc!$B$4=0,$B16>IF(Start!$D$10="Avalanche",Calc!$B$3,Calc!$B$2)),Calc!$B$10=0),"",IF(N(P15)<=0.005,"",IF(Start!$D$10="Avalanche",INDEX(Calc!AF$75:AF$89,Calc!$F$10),INDEX(Calc!AF$50:AF$64,Calc!$D$10)))) | Q16: =IF(R16="","",N(R15)*(1+Start!$E$19/12)-R16) | R16: =IF(OR(OR(Calc!$B$4=0,$B16>IF(Start!$D$10="Avalanche",Calc!$B$3,Calc!$B$2)),Calc!$B$11=0),"",IF(N(R15)<=0.005,"",IF(Start!$D$10="Avalanche",INDEX(Calc!AF$75:AF$89,Calc!$F$11),INDEX(Calc!AF$50:AF$64,Calc!$D$11)))) | S16: =IF(T16="","",N(T15)*(1+Start!$E$20/12)-T16) | T16: =IF(OR(OR(Calc!$B$4=0,$B16>IF(Start!$D$10="Avalanche",Calc!$B$3,Calc!$B$2)),Calc!$B$12=0),"",IF(N(T15)<=0.005,"",IF(Start!$D$10="Avalanche",INDEX(Calc!AF$75:AF$89,Calc!$F$12),INDEX(Calc!AF$50:AF$64,Calc!$D$12)))) | U16: =IF(V16="","",N(V15)*(1+Start!$E$21/12)-V16) | V16: =IF(OR(OR(Calc!$B$4=0,$B16>IF(Start!$D$10="Avalanche",Calc!$B$3,Calc!$B$2)),Calc!$B$13=0),"",IF(N(V15)<=0.005,"",IF(Start!$D$10="Avalanche",INDEX(Calc!AF$75:AF$89,Calc!$F$13),INDEX(Calc!AF$50:AF$64,Calc!$D$13)))) | W16: =IF(X16="","",N(X15)*(1+Start!$E$22/12)-X16) | X16: =IF(OR(OR(Calc!$B$4=0,$B16>IF(Start!$D$10="Avalanche",Calc!$B$3,Calc!$B$2)),Calc!$B$14=0),"",IF(N(X15)<=0.005,"",IF(Start!$D$10="Avalanche",INDEX(Calc!AF$75:AF$89,Calc!$F$14),INDEX(Calc!AF$50:AF$64,Calc!$D$14)))) | Y16: =IF(Z16="","",N(Z15)*(1+Start!$E$23/12)-Z16) | Z16: =IF(OR(OR(Calc!$B$4=0,$B16>IF(Start!$D$10="Avalanche",Calc!$B$3,Calc!$B$2)),Calc!$B$15=0),"",IF(N(Z15)<=0.005,"",IF(Start!$D$10="Avalanche",INDEX(Calc!AF$75:AF$89,Calc!$F$15),INDEX(Calc!AF$50:AF$64,Calc!$D$15)))) | AA16: =IF(AB16="","",N(AB15)*(1+Start!$E$24/12)-AB16) | AB16: =IF(OR(OR(Calc!$B$4=0,$B16>IF(Start!$D$10="Avalanche",Calc!$B$3,Calc!$B$2)),Calc!$B$16=0),"",IF(N(AB15)<=0.005,"",IF(Start!$D$10="Avalanche",INDEX(Calc!AF$75:AF$89,Calc!$F$16),INDEX(Calc!AF$50:AF$64,Calc!$D$16)))) | AC16: =IF(AD16="","",N(AD15)*(1+Start!$E$25/12)-AD16) | AD16: =IF(OR(OR(Calc!$B$4=0,$B16>IF(Start!$D$10="Avalanche",Calc!$B$3,Calc!$B$2)),Calc!$B$17=0),"",IF(N(AD15)<=0.005,"",IF(Start!$D$10="Avalanche",INDEX(Calc!AF$75:AF$89,Calc!$F$17),INDEX(Calc!AF$50:AF$64,Calc!$D$17)))) | AE16: =IF(AF16="","",N(AF15)*(1+Start!$E$26/12)-AF16) | AF16: =IF(OR(OR(Calc!$B$4=0,$B16>IF(Start!$D$10="Avalanche",Calc!$B$3,Calc!$B$2)),Calc!$B$18=0),"",IF(N(AF15)<=0.005,"",IF(Start!$D$10="Avalanche",INDEX(Calc!AF$75:AF$89,Calc!$F$18),INDEX(Calc!AF$50:AF$64,Calc!$D$18)))) | AG16: =IF(AH16="","",N(AH15)*(1+Start!$E$27/12)-AH16) | AH16: =IF(OR(OR(Calc!$B$4=0,$B16>IF(Start!$D$10="Avalanche",Calc!$B$3,Calc!$B$2)),Calc!$B$19=0),"",IF(N(AH15)<=0.005,"",IF(Start!$D$10="Avalanche",INDEX(Calc!AF$75:AF$89,Calc!$F$19),INDEX(Calc!AF$50:AF$64,Calc!$D$19)))) | AI16: =IF(AJ16="","",N(AJ15)*(1+Start!$E$28/12)-AJ16) | AJ16: =IF(OR(OR(Calc!$B$4=0,$B16>IF(Start!$D$10="Avalanche",Calc!$B$3,Calc!$B$2)),Calc!$B$20=0),"",IF(N(AJ15)<=0.005,"",IF(Start!$D$10="Avalanche",INDEX(Calc!AF$75:AF$89,Calc!$F$20),INDEX(Calc!AF$50:AF$64,Calc!$D$20))))
B17: 11 | C17: =IF(Calc!$B$4=0,"",EDATE(Start!$D$11,10)) | D17: =IF(OR(Calc!$B$4=0,$B17>IF(Start!$D$10="Avalanche",Calc!$B$3,Calc!$B$2)),"",SUM(G17,I17,K17,M17,O17,Q17,S17,U17,W17,Y17,AA17,AC17,AE17,AG17,AI17)) | E17: =IF(OR(Calc!$B$4=0,$B17>IF(Start!$D$10="Avalanche",Calc!$B$3,Calc!$B$2)),"",IF(Start!$D$10="Avalanche",Calc!AG$72,Calc!AG$47)) | F17: =IF(Calc!$B$4=0,"",IF($B17>IF(Start!$D$10="Avalanche",Calc!$B$3,Calc!$B$2),NA(),SUM(H17,J17,L17,N17,P17,R17,T17,V17,X17,Z17,AB17,AD17,AF17,AH17,AJ17))) | G17: =IF(H17="","",N(H16)*(1+Start!$E$14/12)-H17) | H17: =IF(OR(OR(Calc!$B$4=0,$B17>IF(Start!$D$10="Avalanche",Calc!$B$3,Calc!$B$2)),Calc!$B$6=0),"",IF(N(H16)<=0.005,"",IF(Start!$D$10="Avalanche",INDEX(Calc!AI$75:AI$89,Calc!$F$6),INDEX(Calc!AI$50:AI$64,Calc!$D$6)))) | I17: =IF(J17="","",N(J16)*(1+Start!$E$15/12)-J17) | J17: =IF(OR(OR(Calc!$B$4=0,$B17>IF(Start!$D$10="Avalanche",Calc!$B$3,Calc!$B$2)),Calc!$B$7=0),"",IF(N(J16)<=0.005,"",IF(Start!$D$10="Avalanche",INDEX(Calc!AI$75:AI$89,Calc!$F$7),INDEX(Calc!AI$50:AI$64,Calc!$D$7)))) | K17: =IF(L17="","",N(L16)*(1+Start!$E$16/12)-L17) | L17: =IF(OR(OR(Calc!$B$4=0,$B17>IF(Start!$D$10="Avalanche",Calc!$B$3,Calc!$B$2)),Calc!$B$8=0),"",IF(N(L16)<=0.005,"",IF(Start!$D$10="Avalanche",INDEX(Calc!AI$75:AI$89,Calc!$F$8),INDEX(Calc!AI$50:AI$64,Calc!$D$8)))) | M17: =IF(N17="","",N(N16)*(1+Start!$E$17/12)-N17) | N17: =IF(OR(OR(Calc!$B$4=0,$B17>IF(Start!$D$10="Avalanche",Calc!$B$3,Calc!$B$2)),Calc!$B$9=0),"",IF(N(N16)<=0.005,"",IF(Start!$D$10="Avalanche",INDEX(Calc!AI$75:AI$89,Calc!$F$9),INDEX(Calc!AI$50:AI$64,Calc!$D$9)))) | O17: =IF(P17="","",N(P16)*(1+Start!$E$18/12)-P17) | P17: =IF(OR(OR(Calc!$B$4=0,$B17>IF(Start!$D$10="Avalanche",Calc!$B$3,Calc!$B$2)),Calc!$B$10=0),"",IF(N(P16)<=0.005,"",IF(Start!$D$10="Avalanche",INDEX(Calc!AI$75:AI$89,Calc!$F$10),INDEX(Calc!AI$50:AI$64,Calc!$D$10)))) | Q17: =IF(R17="","",N(R16)*(1+Start!$E$19/12)-R17) | R17: =IF(OR(OR(Calc!$B$4=0,$B17>IF(Start!$D$10="Avalanche",Calc!$B$3,Calc!$B$2)),Calc!$B$11=0),"",IF(N(R16)<=0.005,"",IF(Start!$D$10="Avalanche",INDEX(Calc!AI$75:AI$89,Calc!$F$11),INDEX(Calc!AI$50:AI$64,Calc!$D$11)))) | S17: =IF(T17="","",N(T16)*(1+Start!$E$20/12)-T17) | T17: =IF(OR(OR(Calc!$B$4=0,$B17>IF(Start!$D$10="Avalanche",Calc!$B$3,Calc!$B$2)),Calc!$B$12=0),"",IF(N(T16)<=0.005,"",IF(Start!$D$10="Avalanche",INDEX(Calc!AI$75:AI$89,Calc!$F$12),INDEX(Calc!AI$50:AI$64,Calc!$D$12)))) | U17: =IF(V17="","",N(V16)*(1+Start!$E$21/12)-V17) | V17: =IF(OR(OR(Calc!$B$4=0,$B17>IF(Start!$D$10="Avalanche",Calc!$B$3,Calc!$B$2)),Calc!$B$13=0),"",IF(N(V16)<=0.005,"",IF(Start!$D$10="Avalanche",INDEX(Calc!AI$75:AI$89,Calc!$F$13),INDEX(Calc!AI$50:AI$64,Calc!$D$13)))) | W17: =IF(X17="","",N(X16)*(1+Start!$E$22/12)-X17) | X17: =IF(OR(OR(Calc!$B$4=0,$B17>IF(Start!$D$10="Avalanche",Calc!$B$3,Calc!$B$2)),Calc!$B$14=0),"",IF(N(X16)<=0.005,"",IF(Start!$D$10="Avalanche",INDEX(Calc!AI$75:AI$89,Calc!$F$14),INDEX(Calc!AI$50:AI$64,Calc!$D$14)))) | Y17: =IF(Z17="","",N(Z16)*(1+Start!$E$23/12)-Z17) | Z17: =IF(OR(OR(Calc!$B$4=0,$B17>IF(Start!$D$10="Avalanche",Calc!$B$3,Calc!$B$2)),Calc!$B$15=0),"",IF(N(Z16)<=0.005,"",IF(Start!$D$10="Avalanche",INDEX(Calc!AI$75:AI$89,Calc!$F$15),INDEX(Calc!AI$50:AI$64,Calc!$D$15)))) | AA17: =IF(AB17="","",N(AB16)*(1+Start!$E$24/12)-AB17) | AB17: =IF(OR(OR(Calc!$B$4=0,$B17>IF(Start!$D$10="Avalanche",Calc!$B$3,Calc!$B$2)),Calc!$B$16=0),"",IF(N(AB16)<=0.005,"",IF(Start!$D$10="Avalanche",INDEX(Calc!AI$75:AI$89,Calc!$F$16),INDEX(Calc!AI$50:AI$64,Calc!$D$16)))) | AC17: =IF(AD17="","",N(AD16)*(1+Start!$E$25/12)-AD17) | AD17: =IF(OR(OR(Calc!$B$4=0,$B17>IF(Start!$D$10="Avalanche",Calc!$B$3,Calc!$B$2)),Calc!$B$17=0),"",IF(N(AD16)<=0.005,"",IF(Start!$D$10="Avalanche",INDEX(Calc!AI$75:AI$89,Calc!$F$17),INDEX(Calc!AI$50:AI$64,Calc!$D$17)))) | AE17: =IF(AF17="","",N(AF16)*(1+Start!$E$26/12)-AF17) | AF17: =IF(OR(OR(Calc!$B$4=0,$B17>IF(Start!$D$10="Avalanche",Calc!$B$3,Calc!$B$2)),Calc!$B$18=0),"",IF(N(AF16)<=0.005,"",IF(Start!$D$10="Avalanche",INDEX(Calc!AI$75:AI$89,Calc!$F$18),INDEX(Calc!AI$50:AI$64,Calc!$D$18)))) | AG17: =IF(AH17="","",N(AH16)*(1+Start!$E$27/12)-AH17) | AH17: =IF(OR(OR(Calc!$B$4=0,$B17>IF(Start!$D$10="Avalanche",Calc!$B$3,Calc!$B$2)),Calc!$B$19=0),"",IF(N(AH16)<=0.005,"",IF(Start!$D$10="Avalanche",INDEX(Calc!AI$75:AI$89,Calc!$F$19),INDEX(Calc!AI$50:AI$64,Calc!$D$19)))) | AI17: =IF(AJ17="","",N(AJ16)*(1+Start!$E$28/12)-AJ17) | AJ17: =IF(OR(OR(Calc!$B$4=0,$B17>IF(Start!$D$10="Avalanche",Calc!$B$3,Calc!$B$2)),Calc!$B$20=0),"",IF(N(AJ16)<=0.005,"",IF(Start!$D$10="Avalanche",INDEX(Calc!AI$75:AI$89,Calc!$F$20),INDEX(Calc!AI$50:AI$64,Calc!$D$20))))
B18: 12 | C18: =IF(Calc!$B$4=0,"",EDATE(Start!$D$11,11)) | D18: =IF(OR(Calc!$B$4=0,$B18>IF(Start!$D$10="Avalanche",Calc!$B$3,Calc!$B$2)),"",SUM(G18,I18,K18,M18,O18,Q18,S18,U18,W18,Y18,AA18,AC18,AE18,AG18,AI18)) | E18: =IF(OR(Calc!$B$4=0,$B18>IF(Start!$D$10="Avalanche",Calc!$B$3,Calc!$B$2)),"",IF(Start!$D$10="Avalanche",Calc!AJ$72,Calc!AJ$47)) | F18: =IF(Calc!$B$4=0,"",IF($B18>IF(Start!$D$10="Avalanche",Calc!$B$3,Calc!$B$2),NA(),SUM(H18,J18,L18,N18,P18,R18,T18,V18,X18,Z18,AB18,AD18,AF18,AH18,AJ18))) | G18: =IF(H18="","",N(H17)*(1+Start!$E$14/12)-H18) | H18: =IF(OR(OR(Calc!$B$4=0,$B18>IF(Start!$D$10="Avalanche",Calc!$B$3,Calc!$B$2)),Calc!$B$6=0),"",IF(N(H17)<=0.005,"",IF(Start!$D$10="Avalanche",INDEX(Calc!AL$75:AL$89,Calc!$F$6),INDEX(Calc!AL$50:AL$64,Calc!$D$6)))) | I18: =IF(J18="","",N(J17)*(1+Start!$E$15/12)-J18) | J18: =IF(OR(OR(Calc!$B$4=0,$B18>IF(Start!$D$10="Avalanche",Calc!$B$3,Calc!$B$2)),Calc!$B$7=0),"",IF(N(J17)<=0.005,"",IF(Start!$D$10="Avalanche",INDEX(Calc!AL$75:AL$89,Calc!$F$7),INDEX(Calc!AL$50:AL$64,Calc!$D$7)))) | K18: =IF(L18="","",N(L17)*(1+Start!$E$16/12)-L18) | L18: =IF(OR(OR(Calc!$B$4=0,$B18>IF(Start!$D$10="Avalanche",Calc!$B$3,Calc!$B$2)),Calc!$B$8=0),"",IF(N(L17)<=0.005,"",IF(Start!$D$10="Avalanche",INDEX(Calc!AL$75:AL$89,Calc!$F$8),INDEX(Calc!AL$50:AL$64,Calc!$D$8)))) | M18: =IF(N18="","",N(N17)*(1+Start!$E$17/12)-N18) | N18: =IF(OR(OR(Calc!$B$4=0,$B18>IF(Start!$D$10="Avalanche",Calc!$B$3,Calc!$B$2)),Calc!$B$9=0),"",IF(N(N17)<=0.005,"",IF(Start!$D$10="Avalanche",INDEX(Calc!AL$75:AL$89,Calc!$F$9),INDEX(Calc!AL$50:AL$64,Calc!$D$9)))) | O18: =IF(P18="","",N(P17)*(1+Start!$E$18/12)-P18) | P18: =IF(OR(OR(Calc!$B$4=0,$B18>IF(Start!$D$10="Avalanche",Calc!$B$3,Calc!$B$2)),Calc!$B$10=0),"",IF(N(P17)<=0.005,"",IF(Start!$D$10="Avalanche",INDEX(Calc!AL$75:AL$89,Calc!$F$10),INDEX(Calc!AL$50:AL$64,Calc!$D$10)))) | Q18: =IF(R18="","",N(R17)*(1+Start!$E$19/12)-R18) | R18: =IF(OR(OR(Calc!$B$4=0,$B18>IF(Start!$D$10="Avalanche",Calc!$B$3,Calc!$B$2)),Calc!$B$11=0),"",IF(N(R17)<=0.005,"",IF(Start!$D$10="Avalanche",INDEX(Calc!AL$75:AL$89,Calc!$F$11),INDEX(Calc!AL$50:AL$64,Calc!$D$11)))) | S18: =IF(T18="","",N(T17)*(1+Start!$E$20/12)-T18) | T18: =IF(OR(OR(Calc!$B$4=0,$B18>IF(Start!$D$10="Avalanche",Calc!$B$3,Calc!$B$2)),Calc!$B$12=0),"",IF(N(T17)<=0.005,"",IF(Start!$D$10="Avalanche",INDEX(Calc!AL$75:AL$89,Calc!$F$12),INDEX(Calc!AL$50:AL$64,Calc!$D$12)))) | U18: =IF(V18="","",N(V17)*(1+Start!$E$21/12)-V18) | V18: =IF(OR(OR(Calc!$B$4=0,$B18>IF(Start!$D$10="Avalanche",Calc!$B$3,Calc!$B$2)),Calc!$B$13=0),"",IF(N(V17)<=0.005,"",IF(Start!$D$10="Avalanche",INDEX(Calc!AL$75:AL$89,Calc!$F$13),INDEX(Calc!AL$50:AL$64,Calc!$D$13)))) | W18: =IF(X18="","",N(X17)*(1+Start!$E$22/12)-X18) | X18: =IF(OR(OR(Calc!$B$4=0,$B18>IF(Start!$D$10="Avalanche",Calc!$B$3,Calc!$B$2)),Calc!$B$14=0),"",IF(N(X17)<=0.005,"",IF(Start!$D$10="Avalanche",INDEX(Calc!AL$75:AL$89,Calc!$F$14),INDEX(Calc!AL$50:AL$64,Calc!$D$14)))) | Y18: =IF(Z18="","",N(Z17)*(1+Start!$E$23/12)-Z18) | Z18: =IF(OR(OR(Calc!$B$4=0,$B18>IF(Start!$D$10="Avalanche",Calc!$B$3,Calc!$B$2)),Calc!$B$15=0),"",IF(N(Z17)<=0.005,"",IF(Start!$D$10="Avalanche",INDEX(Calc!AL$75:AL$89,Calc!$F$15),INDEX(Calc!AL$50:AL$64,Calc!$D$15)))) | AA18: =IF(AB18="","",N(AB17)*(1+Start!$E$24/12)-AB18) | AB18: =IF(OR(OR(Calc!$B$4=0,$B18>IF(Start!$D$10="Avalanche",Calc!$B$3,Calc!$B$2)),Calc!$B$16=0),"",IF(N(AB17)<=0.005,"",IF(Start!$D$10="Avalanche",INDEX(Calc!AL$75:AL$89,Calc!$F$16),INDEX(Calc!AL$50:AL$64,Calc!$D$16)))) | AC18: =IF(AD18="","",N(AD17)*(1+Start!$E$25/12)-AD18) | AD18: =IF(OR(OR(Calc!$B$4=0,$B18>IF(Start!$D$10="Avalanche",Calc!$B$3,Calc!$B$2)),Calc!$B$17=0),"",IF(N(AD17)<=0.005,"",IF(Start!$D$10="Avalanche",INDEX(Calc!AL$75:AL$89,Calc!$F$17),INDEX(Calc!AL$50:AL$64,Calc!$D$17)))) | AE18: =IF(AF18="","",N(AF17)*(1+Start!$E$26/12)-AF18) | AF18: =IF(OR(OR(Calc!$B$4=0,$B18>IF(Start!$D$10="Avalanche",Calc!$B$3,Calc!$B$2)),Calc!$B$18=0),"",IF(N(AF17)<=0.005,"",IF(Start!$D$10="Avalanche",INDEX(Calc!AL$75:AL$89,Calc!$F$18),INDEX(Calc!AL$50:AL$64,Calc!$D$18)))) | AG18: =IF(AH18="","",N(AH17)*(1+Start!$E$27/12)-AH18) | AH18: =IF(OR(OR(Calc!$B$4=0,$B18>IF(Start!$D$10="Avalanche",Calc!$B$3,Calc!$B$2)),Calc!$B$19=0),"",IF(N(AH17)<=0.005,"",IF(Start!$D$10="Avalanche",INDEX(Calc!AL$75:AL$89,Calc!$F$19),INDEX(Calc!AL$50:AL$64,Calc!$D$19)))) | AI18: =IF(AJ18="","",N(AJ17)*(1+Start!$E$28/12)-AJ18) | AJ18: =IF(OR(OR(Calc!$B$4=0,$B18>IF(Start!$D$10="Avalanche",Calc!$B$3,Calc!$B$2)),Calc!$B$20=0),"",IF(N(AJ17)<=0.005,"",IF(Start!$D$10="Avalanche",INDEX(Calc!AL$75:AL$89,Calc!$F$20),INDEX(Calc!AL$50:AL$64,Calc!$D$20))))
B19: 13 | C19: =IF(Calc!$B$4=0,"",EDATE(Start!$D$11,12)) | D19: =IF(OR(Calc!$B$4=0,$B19>IF(Start!$D$10="Avalanche",Calc!$B$3,Calc!$B$2)),"",SUM(G19,I19,K19,M19,O19,Q19,S19,U19,W19,Y19,AA19,AC19,AE19,AG19,AI19)) | E19: =IF(OR(Calc!$B$4=0,$B19>IF(Start!$D$10="Avalanche",Calc!$B$3,Calc!$B$2)),"",IF(Start!$D$10="Avalanche",Calc!AM$72,Calc!AM$47)) | F19: =IF(Calc!$B$4=0,"",IF($B19>IF(Start!$D$10="Avalanche",Calc!$B$3,Calc!$B$2),NA(),SUM(H19,J19,L19,N19,P19,R19,T19,V19,X19,Z19,AB19,AD19,AF19,AH19,AJ19))) | G19: =IF(H19="","",N(H18)*(1+Start!$E$14/12)-H19) | H19: =IF(OR(OR(Calc!$B$4=0,$B19>IF(Start!$D$10="Avalanche",Calc!$B$3,Calc!$B$2)),Calc!$B$6=0),"",IF(N(H18)<=0.005,"",IF(Start!$D$10="Avalanche",INDEX(Calc!AO$75:AO$89,Calc!$F$6),INDEX(Calc!AO$50:AO$64,Calc!$D$6)))) | I19: =IF(J19="","",N(J18)*(1+Start!$E$15/12)-J19) | J19: =IF(OR(OR(Calc!$B$4=0,$B19>IF(Start!$D$10="Avalanche",Calc!$B$3,Calc!$B$2)),Calc!$B$7=0),"",IF(N(J18)<=0.005,"",IF(Start!$D$10="Avalanche",INDEX(Calc!AO$75:AO$89,Calc!$F$7),INDEX(Calc!AO$50:AO$64,Calc!$D$7)))) | K19: =IF(L19="","",N(L18)*(1+Start!$E$16/12)-L19) | L19: =IF(OR(OR(Calc!$B$4=0,$B19>IF(Start!$D$10="Avalanche",Calc!$B$3,Calc!$B$2)),Calc!$B$8=0),"",IF(N(L18)<=0.005,"",IF(Start!$D$10="Avalanche",INDEX(Calc!AO$75:AO$89,Calc!$F$8),INDEX(Calc!AO$50:AO$64,Calc!$D$8)))) | M19: =IF(N19="","",N(N18)*(1+Start!$E$17/12)-N19) | N19: =IF(OR(OR(Calc!$B$4=0,$B19>IF(Start!$D$10="Avalanche",Calc!$B$3,Calc!$B$2)),Calc!$B$9=0),"",IF(N(N18)<=0.005,"",IF(Start!$D$10="Avalanche",INDEX(Calc!AO$75:AO$89,Calc!$F$9),INDEX(Calc!AO$50:AO$64,Calc!$D$9)))) | O19: =IF(P19="","",N(P18)*(1+Start!$E$18/12)-P19) | P19: =IF(OR(OR(Calc!$B$4=0,$B19>IF(Start!$D$10="Avalanche",Calc!$B$3,Calc!$B$2)),Calc!$B$10=0),"",IF(N(P18)<=0.005,"",IF(Start!$D$10="Avalanche",INDEX(Calc!AO$75:AO$89,Calc!$F$10),INDEX(Calc!AO$50:AO$64,Calc!$D$10)))) | Q19: =IF(R19="","",N(R18)*(1+Start!$E$19/12)-R19) | R19: =IF(OR(OR(Calc!$B$4=0,$B19>IF(Start!$D$10="Avalanche",Calc!$B$3,Calc!$B$2)),Calc!$B$11=0),"",IF(N(R18)<=0.005,"",IF(Start!$D$10="Avalanche",INDEX(Calc!AO$75:AO$89,Calc!$F$11),INDEX(Calc!AO$50:AO$64,Calc!$D$11)))) | S19: =IF(T19="","",N(T18)*(1+Start!$E$20/12)-T19) | T19: =IF(OR(OR(Calc!$B$4=0,$B19>IF(Start!$D$10="Avalanche",Calc!$B$3,Calc!$B$2)),Calc!$B$12=0),"",IF(N(T18)<=0.005,"",IF(Start!$D$10="Avalanche",INDEX(Calc!AO$75:AO$89,Calc!$F$12),INDEX(Calc!AO$50:AO$64,Calc!$D$12)))) | U19: =IF(V19="","",N(V18)*(1+Start!$E$21/12)-V19) | V19: =IF(OR(OR(Calc!$B$4=0,$B19>IF(Start!$D$10="Avalanche",Calc!$B$3,Calc!$B$2)),Calc!$B$13=0),"",IF(N(V18)<=0.005,"",IF(Start!$D$10="Avalanche",INDEX(Calc!AO$75:AO$89,Calc!$F$13),INDEX(Calc!AO$50:AO$64,Calc!$D$13)))) | W19: =IF(X19="","",N(X18)*(1+Start!$E$22/12)-X19) | X19: =IF(OR(OR(Calc!$B$4=0,$B19>IF(Start!$D$10="Avalanche",Calc!$B$3,Calc!$B$2)),Calc!$B$14=0),"",IF(N(X18)<=0.005,"",IF(Start!$D$10="Avalanche",INDEX(Calc!AO$75:AO$89,Calc!$F$14),INDEX(Calc!AO$50:AO$64,Calc!$D$14)))) | Y19: =IF(Z19="","",N(Z18)*(1+Start!$E$23/12)-Z19) | Z19: =IF(OR(OR(Calc!$B$4=0,$B19>IF(Start!$D$10="Avalanche",Calc!$B$3,Calc!$B$2)),Calc!$B$15=0),"",IF(N(Z18)<=0.005,"",IF(Start!$D$10="Avalanche",INDEX(Calc!AO$75:AO$89,Calc!$F$15),INDEX(Calc!AO$50:AO$64,Calc!$D$15)))) | AA19: =IF(AB19="","",N(AB18)*(1+Start!$E$24/12)-AB19) | AB19: =IF(OR(OR(Calc!$B$4=0,$B19>IF(Start!$D$10="Avalanche",Calc!$B$3,Calc!$B$2)),Calc!$B$16=0),"",IF(N(AB18)<=0.005,"",IF(Start!$D$10="Avalanche",INDEX(Calc!AO$75:AO$89,Calc!$F$16),INDEX(Calc!AO$50:AO$64,Calc!$D$16)))) | AC19: =IF(AD19="","",N(AD18)*(1+Start!$E$25/12)-AD19) | AD19: =IF(OR(OR(Calc!$B$4=0,$B19>IF(Start!$D$10="Avalanche",Calc!$B$3,Calc!$B$2)),Calc!$B$17=0),"",IF(N(AD18)<=0.005,"",IF(Start!$D$10="Avalanche",INDEX(Calc!AO$75:AO$89,Calc!$F$17),INDEX(Calc!AO$50:AO$64,Calc!$D$17)))) | AE19: =IF(AF19="","",N(AF18)*(1+Start!$E$26/12)-AF19) | AF19: =IF(OR(OR(Calc!$B$4=0,$B19>IF(Start!$D$10="Avalanche",Calc!$B$3,Calc!$B$2)),Calc!$B$18=0),"",IF(N(AF18)<=0.005,"",IF(Start!$D$10="Avalanche",INDEX(Calc!AO$75:AO$89,Calc!$F$18),INDEX(Calc!AO$50:AO$64,Calc!$D$18)))) | AG19: =IF(AH19="","",N(AH18)*(1+Start!$E$27/12)-AH19) | AH19: =IF(OR(OR(Calc!$B$4=0,$B19>IF(Start!$D$10="Avalanche",Calc!$B$3,Calc!$B$2)),Calc!$B$19=0),"",IF(N(AH18)<=0.005,"",IF(Start!$D$10="Avalanche",INDEX(Calc!AO$75:AO$89,Calc!$F$19),INDEX(Calc!AO$50:AO$64,Calc!$D$19)))) | AI19: =IF(AJ19="","",N(AJ18)*(1+Start!$E$28/12)-AJ19) | AJ19: =IF(OR(OR(Calc!$B$4=0,$B19>IF(Start!$D$10="Avalanche",Calc!$B$3,Calc!$B$2)),Calc!$B$20=0),"",IF(N(AJ18)<=0.005,"",IF(Start!$D$10="Avalanche",INDEX(Calc!AO$75:AO$89,Calc!$F$20),INDEX(Calc!AO$50:AO$64,Calc!$D$20))))
B20: 14 | C20: =IF(Calc!$B$4=0,"",EDATE(Start!$D$11,13)) | D20: =IF(OR(Calc!$B$4=0,$B20>IF(Start!$D$10="Avalanche",Calc!$B$3,Calc!$B$2)),"",SUM(G20,I20,K20,M20,O20,Q20,S20,U20,W20,Y20,AA20,AC20,AE20,AG20,AI20)) | E20: =IF(OR(Calc!$B$4=0,$B20>IF(Start!$D$10="Avalanche",Calc!$B$3,Calc!$B$2)),"",IF(Start!$D$10="Avalanche",Calc!AP$72,Calc!AP$47)) | F20: =IF(Calc!$B$4=0,"",IF($B20>IF(Start!$D$10="Avalanche",Calc!$B$3,Calc!$B$2),NA(),SUM(H20,J20,L20,N20,P20,R20,T20,V20,X20,Z20,AB20,AD20,AF20,AH20,AJ20))) | G20: =IF(H20="","",N(H19)*(1+Start!$E$14/12)-H20) | H20: =IF(OR(OR(Calc!$B$4=0,$B20>IF(Start!$D$10="Avalanche",Calc!$B$3,Calc!$B$2)),Calc!$B$6=0),"",IF(N(H19)<=0.005,"",IF(Start!$D$10="Avalanche",INDEX(Calc!AR$75:AR$89,Calc!$F$6),INDEX(Calc!AR$50:AR$64,Calc!$D$6)))) | I20: =IF(J20="","",N(J19)*(1+Start!$E$15/12)-J20) | J20: =IF(OR(OR(Calc!$B$4=0,$B20>IF(Start!$D$10="Avalanche",Calc!$B$3,Calc!$B$2)),Calc!$B$7=0),"",IF(N(J19)<=0.005,"",IF(Start!$D$10="Avalanche",INDEX(Calc!AR$75:AR$89,Calc!$F$7),INDEX(Calc!AR$50:AR$64,Calc!$D$7)))) | K20: =IF(L20="","",N(L19)*(1+Start!$E$16/12)-L20) | L20: =IF(OR(OR(Calc!$B$4=0,$B20>IF(Start!$D$10="Avalanche",Calc!$B$3,Calc!$B$2)),Calc!$B$8=0),"",IF(N(L19)<=0.005,"",IF(Start!$D$10="Avalanche",INDEX(Calc!AR$75:AR$89,Calc!$F$8),INDEX(Calc!AR$50:AR$64,Calc!$D$8)))) | M20: =IF(N20="","",N(N19)*(1+Start!$E$17/12)-N20) | N20: =IF(OR(OR(Calc!$B$4=0,$B20>IF(Start!$D$10="Avalanche",Calc!$B$3,Calc!$B$2)),Calc!$B$9=0),"",IF(N(N19)<=0.005,"",IF(Start!$D$10="Avalanche",INDEX(Calc!AR$75:AR$89,Calc!$F$9),INDEX(Calc!AR$50:AR$64,Calc!$D$9)))) | O20: =IF(P20="","",N(P19)*(1+Start!$E$18/12)-P20) | P20: =IF(OR(OR(Calc!$B$4=0,$B20>IF(Start!$D$10="Avalanche",Calc!$B$3,Calc!$B$2)),Calc!$B$10=0),"",IF(N(P19)<=0.005,"",IF(Start!$D$10="Avalanche",INDEX(Calc!AR$75:AR$89,Calc!$F$10),INDEX(Calc!AR$50:AR$64,Calc!$D$10)))) | Q20: =IF(R20="","",N(R19)*(1+Start!$E$19/12)-R20) | R20: =IF(OR(OR(Calc!$B$4=0,$B20>IF(Start!$D$10="Avalanche",Calc!$B$3,Calc!$B$2)),Calc!$B$11=0),"",IF(N(R19)<=0.005,"",IF(Start!$D$10="Avalanche",INDEX(Calc!AR$75:AR$89,Calc!$F$11),INDEX(Calc!AR$50:AR$64,Calc!$D$11)))) | S20: =IF(T20="","",N(T19)*(1+Start!$E$20/12)-T20) | T20: =IF(OR(OR(Calc!$B$4=0,$B20>IF(Start!$D$10="Avalanche",Calc!$B$3,Calc!$B$2)),Calc!$B$12=0),"",IF(N(T19)<=0.005,"",IF(Start!$D$10="Avalanche",INDEX(Calc!AR$75:AR$89,Calc!$F$12),INDEX(Calc!AR$50:AR$64,Calc!$D$12)))) | U20: =IF(V20="","",N(V19)*(1+Start!$E$21/12)-V20) | V20: =IF(OR(OR(Calc!$B$4=0,$B20>IF(Start!$D$10="Avalanche",Calc!$B$3,Calc!$B$2)),Calc!$B$13=0),"",IF(N(V19)<=0.005,"",IF(Start!$D$10="Avalanche",INDEX(Calc!AR$75:AR$89,Calc!$F$13),INDEX(Calc!AR$50:AR$64,Calc!$D$13)))) | W20: =IF(X20="","",N(X19)*(1+Start!$E$22/12)-X20) | X20: =IF(OR(OR(Calc!$B$4=0,$B20>IF(Start!$D$10="Avalanche",Calc!$B$3,Calc!$B$2)),Calc!$B$14=0),"",IF(N(X19)<=0.005,"",IF(Start!$D$10="Avalanche",INDEX(Calc!AR$75:AR$89,Calc!$F$14),INDEX(Calc!AR$50:AR$64,Calc!$D$14)))) | Y20: =IF(Z20="","",N(Z19)*(1+Start!$E$23/12)-Z20) | Z20: =IF(OR(OR(Calc!$B$4=0,$B20>IF(Start!$D$10="Avalanche",Calc!$B$3,Calc!$B$2)),Calc!$B$15=0),"",IF(N(Z19)<=0.005,"",IF(Start!$D$10="Avalanche",INDEX(Calc!AR$75:AR$89,Calc!$F$15),INDEX(Calc!AR$50:AR$64,Calc!$D$15)))) | AA20: =IF(AB20="","",N(AB19)*(1+Start!$E$24/12)-AB20) | AB20: =IF(OR(OR(Calc!$B$4=0,$B20>IF(Start!$D$10="Avalanche",Calc!$B$3,Calc!$B$2)),Calc!$B$16=0),"",IF(N(AB19)<=0.005,"",IF(Start!$D$10="Avalanche",INDEX(Calc!AR$75:AR$89,Calc!$F$16),INDEX(Calc!AR$50:AR$64,Calc!$D$16)))) | AC20: =IF(AD20="","",N(AD19)*(1+Start!$E$25/12)-AD20) | AD20: =IF(OR(OR(Calc!$B$4=0,$B20>IF(Start!$D$10="Avalanche",Calc!$B$3,Calc!$B$2)),Calc!$B$17=0),"",IF(N(AD19)<=0.005,"",IF(Start!$D$10="Avalanche",INDEX(Calc!AR$75:AR$89,Calc!$F$17),INDEX(Calc!AR$50:AR$64,Calc!$D$17)))) | AE20: =IF(AF20="","",N(AF19)*(1+Start!$E$26/12)-AF20) | AF20: =IF(OR(OR(Calc!$B$4=0,$B20>IF(Start!$D$10="Avalanche",Calc!$B$3,Calc!$B$2)),Calc!$B$18=0),"",IF(N(AF19)<=0.005,"",IF(Start!$D$10="Avalanche",INDEX(Calc!AR$75:AR$89,Calc!$F$18),INDEX(Calc!AR$50:AR$64,Calc!$D$18)))) | AG20: =IF(AH20="","",N(AH19)*(1+Start!$E$27/12)-AH20) | AH20: =IF(OR(OR(Calc!$B$4=0,$B20>IF(Start!$D$10="Avalanche",Calc!$B$3,Calc!$B$2)),Calc!$B$19=0),"",IF(N(AH19)<=0.005,"",IF(Start!$D$10="Avalanche",INDEX(Calc!AR$75:AR$89,Calc!$F$19),INDEX(Calc!AR$50:AR$64,Calc!$D$19)))) | AI20: =IF(AJ20="","",N(AJ19)*(1+Start!$E$28/12)-AJ20) | AJ20: =IF(OR(OR(Calc!$B$4=0,$B20>IF(Start!$D$10="Avalanche",Calc!$B$3,Calc!$B$2)),Calc!$B$20=0),"",IF(N(AJ19)<=0.005,"",IF(Start!$D$10="Avalanche",INDEX(Calc!AR$75:AR$89,Calc!$F$20),INDEX(Calc!AR$50:AR$64,Calc!$D$20))))
B21: 15 | C21: =IF(Calc!$B$4=0,"",EDATE(Start!$D$11,14)) | D21: =IF(OR(Calc!$B$4=0,$B21>IF(Start!$D$10="Avalanche",Calc!$B$3,Calc!$B$2)),"",SUM(G21,I21,K21,M21,O21,Q21,S21,U21,W21,Y21,AA21,AC21,AE21,AG21,AI21)) | E21: =IF(OR(Calc!$B$4=0,$B21>IF(Start!$D$10="Avalanche",Calc!$B$3,Calc!$B$2)),"",IF(Start!$D$10="Avalanche",Calc!AS$72,Calc!AS$47)) | F21: =IF(Calc!$B$4=0,"",IF($B21>IF(Start!$D$10="Avalanche",Calc!$B$3,Calc!$B$2),NA(),SUM(H21,J21,L21,N21,P21,R21,T21,V21,X21,Z21,AB21,AD21,AF21,AH21,AJ21))) | G21: =IF(H21="","",N(H20)*(1+Start!$E$14/12)-H21) | H21: =IF(OR(OR(Calc!$B$4=0,$B21>IF(Start!$D$10="Avalanche",Calc!$B$3,Calc!$B$2)),Calc!$B$6=0),"",IF(N(H20)<=0.005,"",IF(Start!$D$10="Avalanche",INDEX(Calc!AU$75:AU$89,Calc!$F$6),INDEX(Calc!AU$50:AU$64,Calc!$D$6)))) | I21: =IF(J21="","",N(J20)*(1+Start!$E$15/12)-J21) | J21: =IF(OR(OR(Calc!$B$4=0,$B21>IF(Start!$D$10="Avalanche",Calc!$B$3,Calc!$B$2)),Calc!$B$7=0),"",IF(N(J20)<=0.005,"",IF(Start!$D$10="Avalanche",INDEX(Calc!AU$75:AU$89,Calc!$F$7),INDEX(Calc!AU$50:AU$64,Calc!$D$7)))) | K21: =IF(L21="","",N(L20)*(1+Start!$E$16/12)-L21) | L21: =IF(OR(OR(Calc!$B$4=0,$B21>IF(Start!$D$10="Avalanche",Calc!$B$3,Calc!$B$2)),Calc!$B$8=0),"",IF(N(L20)<=0.005,"",IF(Start!$D$10="Avalanche",INDEX(Calc!AU$75:AU$89,Calc!$F$8),INDEX(Calc!AU$50:AU$64,Calc!$D$8)))) | M21: =IF(N21="","",N(N20)*(1+Start!$E$17/12)-N21) | N21: =IF(OR(OR(Calc!$B$4=0,$B21>IF(Start!$D$10="Avalanche",Calc!$B$3,Calc!$B$2)),Calc!$B$9=0),"",IF(N(N20)<=0.005,"",IF(Start!$D$10="Avalanche",INDEX(Calc!AU$75:AU$89,Calc!$F$9),INDEX(Calc!AU$50:AU$64,Calc!$D$9)))) | O21: =IF(P21="","",N(P20)*(1+Start!$E$18/12)-P21) | P21: =IF(OR(OR(Calc!$B$4=0,$B21>IF(Start!$D$10="Avalanche",Calc!$B$3,Calc!$B$2)),Calc!$B$10=0),"",IF(N(P20)<=0.005,"",IF(Start!$D$10="Avalanche",INDEX(Calc!AU$75:AU$89,Calc!$F$10),INDEX(Calc!AU$50:AU$64,Calc!$D$10)))) | Q21: =IF(R21="","",N(R20)*(1+Start!$E$19/12)-R21) | R21: =IF(OR(OR(Calc!$B$4=0,$B21>IF(Start!$D$10="Avalanche",Calc!$B$3,Calc!$B$2)),Calc!$B$11=0),"",IF(N(R20)<=0.005,"",IF(Start!$D$10="Avalanche",INDEX(Calc!AU$75:AU$89,Calc!$F$11),INDEX(Calc!AU$50:AU$64,Calc!$D$11)))) | S21: =IF(T21="","",N(T20)*(1+Start!$E$20/12)-T21) | T21: =IF(OR(OR(Calc!$B$4=0,$B21>IF(Start!$D$10="Avalanche",Calc!$B$3,Calc!$B$2)),Calc!$B$12=0),"",IF(N(T20)<=0.005,"",IF(Start!$D$10="Avalanche",INDEX(Calc!AU$75:AU$89,Calc!$F$12),INDEX(Calc!AU$50:AU$64,Calc!$D$12)))) | U21: =IF(V21="","",N(V20)*(1+Start!$E$21/12)-V21) | V21: =IF(OR(OR(Calc!$B$4=0,$B21>IF(Start!$D$10="Avalanche",Calc!$B$3,Calc!$B$2)),Calc!$B$13=0),"",IF(N(V20)<=0.005,"",IF(Start!$D$10="Avalanche",INDEX(Calc!AU$75:AU$89,Calc!$F$13),INDEX(Calc!AU$50:AU$64,Calc!$D$13)))) | W21: =IF(X21="","",N(X20)*(1+Start!$E$22/12)-X21) | X21: =IF(OR(OR(Calc!$B$4=0,$B21>IF(Start!$D$10="Avalanche",Calc!$B$3,Calc!$B$2)),Calc!$B$14=0),"",IF(N(X20)<=0.005,"",IF(Start!$D$10="Avalanche",INDEX(Calc!AU$75:AU$89,Calc!$F$14),INDEX(Calc!AU$50:AU$64,Calc!$D$14)))) | Y21: =IF(Z21="","",N(Z20)*(1+Start!$E$23/12)-Z21) | Z21: =IF(OR(OR(Calc!$B$4=0,$B21>IF(Start!$D$10="Avalanche",Calc!$B$3,Calc!$B$2)),Calc!$B$15=0),"",IF(N(Z20)<=0.005,"",IF(Start!$D$10="Avalanche",INDEX(Calc!AU$75:AU$89,Calc!$F$15),INDEX(Calc!AU$50:AU$64,Calc!$D$15)))) | AA21: =IF(AB21="","",N(AB20)*(1+Start!$E$24/12)-AB21) | AB21: =IF(OR(OR(Calc!$B$4=0,$B21>IF(Start!$D$10="Avalanche",Calc!$B$3,Calc!$B$2)),Calc!$B$16=0),"",IF(N(AB20)<=0.005,"",IF(Start!$D$10="Avalanche",INDEX(Calc!AU$75:AU$89,Calc!$F$16),INDEX(Calc!AU$50:AU$64,Calc!$D$16)))) | AC21: =IF(AD21="","",N(AD20)*(1+Start!$E$25/12)-AD21) | AD21: =IF(OR(OR(Calc!$B$4=0,$B21>IF(Start!$D$10="Avalanche",Calc!$B$3,Calc!$B$2)),Calc!$B$17=0),"",IF(N(AD20)<=0.005,"",IF(Start!$D$10="Avalanche",INDEX(Calc!AU$75:AU$89,Calc!$F$17),INDEX(Calc!AU$50:AU$64,Calc!$D$17)))) | AE21: =IF(AF21="","",N(AF20)*(1+Start!$E$26/12)-AF21) | AF21: =IF(OR(OR(Calc!$B$4=0,$B21>IF(Start!$D$10="Avalanche",Calc!$B$3,Calc!$B$2)),Calc!$B$18=0),"",IF(N(AF20)<=0.005,"",IF(Start!$D$10="Avalanche",INDEX(Calc!AU$75:AU$89,Calc!$F$18),INDEX(Calc!AU$50:AU$64,Calc!$D$18)))) | AG21: =IF(AH21="","",N(AH20)*(1+Start!$E$27/12)-AH21) | AH21: =IF(OR(OR(Calc!$B$4=0,$B21>IF(Start!$D$10="Avalanche",Calc!$B$3,Calc!$B$2)),Calc!$B$19=0),"",IF(N(AH20)<=0.005,"",IF(Start!$D$10="Avalanche",INDEX(Calc!AU$75:AU$89,Calc!$F$19),INDEX(Calc!AU$50:AU$64,Calc!$D$19)))) | AI21: =IF(AJ21="","",N(AJ20)*(1+Start!$E$28/12)-AJ21) | AJ21: =IF(OR(OR(Calc!$B$4=0,$B21>IF(Start!$D$10="Avalanche",Calc!$B$3,Calc!$B$2)),Calc!$B$20=0),"",IF(N(AJ20)<=0.005,"",IF(Start!$D$10="Avalanche",INDEX(Calc!AU$75:AU$89,Calc!$F$20),INDEX(Calc!AU$50:AU$64,Calc!$D$20))))
B22: 16 | C22: =IF(Calc!$B$4=0,"",EDATE(Start!$D$11,15)) | D22: =IF(OR(Calc!$B$4=0,$B22>IF(Start!$D$10="Avalanche",Calc!$B$3,Calc!$B$2)),"",SUM(G22,I22,K22,M22,O22,Q22,S22,U22,W22,Y22,AA22,AC22,AE22,AG22,AI22)) | E22: =IF(OR(Calc!$B$4=0,$B22>IF(Start!$D$10="Avalanche",Calc!$B$3,Calc!$B$2)),"",IF(Start!$D$10="Avalanche",Calc!AV$72,Calc!AV$47)) | F22: =IF(Calc!$B$4=0,"",IF($B22>IF(Start!$D$10="Avalanche",Calc!$B$3,Calc!$B$2),NA(),SUM(H22,J22,L22,N22,P22,R22,T22,V22,X22,Z22,AB22,AD22,AF22,AH22,AJ22))) | G22: =IF(H22="","",N(H21)*(1+Start!$E$14/12)-H22) | H22: =IF(OR(OR(Calc!$B$4=0,$B22>IF(Start!$D$10="Avalanche",Calc!$B$3,Calc!$B$2)),Calc!$B$6=0),"",IF(N(H21)<=0.005,"",IF(Start!$D$10="Avalanche",INDEX(Calc!AX$75:AX$89,Calc!$F$6),INDEX(Calc!AX$50:AX$64,Calc!$D$6)))) | I22: =IF(J22="","",N(J21)*(1+Start!$E$15/12)-J22) | J22: =IF(OR(OR(Calc!$B$4=0,$B22>IF(Start!$D$10="Avalanche",Calc!$B$3,Calc!$B$2)),Calc!$B$7=0),"",IF(N(J21)<=0.005,"",IF(Start!$D$10="Avalanche",INDEX(Calc!AX$75:AX$89,Calc!$F$7),INDEX(Calc!AX$50:AX$64,Calc!$D$7)))) | K22: =IF(L22="","",N(L21)*(1+Start!$E$16/12)-L22) | L22: =IF(OR(OR(Calc!$B$4=0,$B22>IF(Start!$D$10="Avalanche",Calc!$B$3,Calc!$B$2)),Calc!$B$8=0),"",IF(N(L21)<=0.005,"",IF(Start!$D$10="Avalanche",INDEX(Calc!AX$75:AX$89,Calc!$F$8),INDEX(Calc!AX$50:AX$64,Calc!$D$8)))) | M22: =IF(N22="","",N(N21)*(1+Start!$E$17/12)-N22) | N22: =IF(OR(OR(Calc!$B$4=0,$B22>IF(Start!$D$10="Avalanche",Calc!$B$3,Calc!$B$2)),Calc!$B$9=0),"",IF(N(N21)<=0.005,"",IF(Start!$D$10="Avalanche",INDEX(Calc!AX$75:AX$89,Calc!$F$9),INDEX(Calc!AX$50:AX$64,Calc!$D$9)))) | O22: =IF(P22="","",N(P21)*(1+Start!$E$18/12)-P22) | P22: =IF(OR(OR(Calc!$B$4=0,$B22>IF(Start!$D$10="Avalanche",Calc!$B$3,Calc!$B$2)),Calc!$B$10=0),"",IF(N(P21)<=0.005,"",IF(Start!$D$10="Avalanche",INDEX(Calc!AX$75:AX$89,Calc!$F$10),INDEX(Calc!AX$50:AX$64,Calc!$D$10)))) | Q22: =IF(R22="","",N(R21)*(1+Start!$E$19/12)-R22) | R22: =IF(OR(OR(Calc!$B$4=0,$B22>IF(Start!$D$10="Avalanche",Calc!$B$3,Calc!$B$2)),Calc!$B$11=0),"",IF(N(R21)<=0.005,"",IF(Start!$D$10="Avalanche",INDEX(Calc!AX$75:AX$89,Calc!$F$11),INDEX(Calc!AX$50:AX$64,Calc!$D$11)))) | S22: =IF(T22="","",N(T21)*(1+Start!$E$20/12)-T22) | T22: =IF(OR(OR(Calc!$B$4=0,$B22>IF(Start!$D$10="Avalanche",Calc!$B$3,Calc!$B$2)),Calc!$B$12=0),"",IF(N(T21)<=0.005,"",IF(Start!$D$10="Avalanche",INDEX(Calc!AX$75:AX$89,Calc!$F$12),INDEX(Calc!AX$50:AX$64,Calc!$D$12)))) | U22: =IF(V22="","",N(V21)*(1+Start!$E$21/12)-V22) | V22: =IF(OR(OR(Calc!$B$4=0,$B22>IF(Start!$D$10="Avalanche",Calc!$B$3,Calc!$B$2)),Calc!$B$13=0),"",IF(N(V21)<=0.005,"",IF(Start!$D$10="Avalanche",INDEX(Calc!AX$75:AX$89,Calc!$F$13),INDEX(Calc!AX$50:AX$64,Calc!$D$13)))) | W22: =IF(X22="","",N(X21)*(1+Start!$E$22/12)-X22) | X22: =IF(OR(OR(Calc!$B$4=0,$B22>IF(Start!$D$10="Avalanche",Calc!$B$3,Calc!$B$2)),Calc!$B$14=0),"",IF(N(X21)<=0.005,"",IF(Start!$D$10="Avalanche",INDEX(Calc!AX$75:AX$89,Calc!$F$14),INDEX(Calc!AX$50:AX$64,Calc!$D$14)))) | Y22: =IF(Z22="","",N(Z21)*(1+Start!$E$23/12)-Z22) | Z22: =IF(OR(OR(Calc!$B$4=0,$B22>IF(Start!$D$10="Avalanche",Calc!$B$3,Calc!$B$2)),Calc!$B$15=0),"",IF(N(Z21)<=0.005,"",IF(Start!$D$10="Avalanche",INDEX(Calc!AX$75:AX$89,Calc!$F$15),INDEX(Calc!AX$50:AX$64,Calc!$D$15)))) | AA22: =IF(AB22="","",N(AB21)*(1+Start!$E$24/12)-AB22) | AB22: =IF(OR(OR(Calc!$B$4=0,$B22>IF(Start!$D$10="Avalanche",Calc!$B$3,Calc!$B$2)),Calc!$B$16=0),"",IF(N(AB21)<=0.005,"",IF(Start!$D$10="Avalanche",INDEX(Calc!AX$75:AX$89,Calc!$F$16),INDEX(Calc!AX$50:AX$64,Calc!$D$16)))) | AC22: =IF(AD22="","",N(AD21)*(1+Start!$E$25/12)-AD22) | AD22: =IF(OR(OR(Calc!$B$4=0,$B22>IF(Start!$D$10="Avalanche",Calc!$B$3,Calc!$B$2)),Calc!$B$17=0),"",IF(N(AD21)<=0.005,"",IF(Start!$D$10="Avalanche",INDEX(Calc!AX$75:AX$89,Calc!$F$17),INDEX(Calc!AX$50:AX$64,Calc!$D$17)))) | AE22: =IF(AF22="","",N(AF21)*(1+Start!$E$26/12)-AF22) | AF22: =IF(OR(OR(Calc!$B$4=0,$B22>IF(Start!$D$10="Avalanche",Calc!$B$3,Calc!$B$2)),Calc!$B$18=0),"",IF(N(AF21)<=0.005,"",IF(Start!$D$10="Avalanche",INDEX(Calc!AX$75:AX$89,Calc!$F$18),INDEX(Calc!AX$50:AX$64,Calc!$D$18)))) | AG22: =IF(AH22="","",N(AH21)*(1+Start!$E$27/12)-AH22) | AH22: =IF(OR(OR(Calc!$B$4=0,$B22>IF(Start!$D$10="Avalanche",Calc!$B$3,Calc!$B$2)),Calc!$B$19=0),"",IF(N(AH21)<=0.005,"",IF(Start!$D$10="Avalanche",INDEX(Calc!AX$75:AX$89,Calc!$F$19),INDEX(Calc!AX$50:AX$64,Calc!$D$19)))) | AI22: =IF(AJ22="","",N(AJ21)*(1+Start!$E$28/12)-AJ22) | AJ22: =IF(OR(OR(Calc!$B$4=0,$B22>IF(Start!$D$10="Avalanche",Calc!$B$3,Calc!$B$2)),Calc!$B$20=0),"",IF(N(AJ21)<=0.005,"",IF(Start!$D$10="Avalanche",INDEX(Calc!AX$75:AX$89,Calc!$F$20),INDEX(Calc!AX$50:AX$64,Calc!$D$20))))
B23: 17 | C23: =IF(Calc!$B$4=0,"",EDATE(Start!$D$11,16)) | D23: =IF(OR(Calc!$B$4=0,$B23>IF(Start!$D$10="Avalanche",Calc!$B$3,Calc!$B$2)),"",SUM(G23,I23,K23,M23,O23,Q23,S23,U23,W23,Y23,AA23,AC23,AE23,AG23,AI23)) | E23: =IF(OR(Calc!$B$4=0,$B23>IF(Start!$D$10="Avalanche",Calc!$B$3,Calc!$B$2)),"",IF(Start!$D$10="Avalanche",Calc!AY$72,Calc!AY$47)) | F23: =IF(Calc!$B$4=0,"",IF($B23>IF(Start!$D$10="Avalanche",Calc!$B$3,Calc!$B$2),NA(),SUM(H23,J23,L23,N23,P23,R23,T23,V23,X23,Z23,AB23,AD23,AF23,AH23,AJ23))) | G23: =IF(H23="","",N(H22)*(1+Start!$E$14/12)-H23) | H23: =IF(OR(OR(Calc!$B$4=0,$B23>IF(Start!$D$10="Avalanche",Calc!$B$3,Calc!$B$2)),Calc!$B$6=0),"",IF(N(H22)<=0.005,"",IF(Start!$D$10="Avalanche",INDEX(Calc!BA$75:BA$89,Calc!$F$6),INDEX(Calc!BA$50:BA$64,Calc!$D$6)))) | I23: =IF(J23="","",N(J22)*(1+Start!$E$15/12)-J23) | J23: =IF(OR(OR(Calc!$B$4=0,$B23>IF(Start!$D$10="Avalanche",Calc!$B$3,Calc!$B$2)),Calc!$B$7=0),"",IF(N(J22)<=0.005,"",IF(Start!$D$10="Avalanche",INDEX(Calc!BA$75:BA$89,Calc!$F$7),INDEX(Calc!BA$50:BA$64,Calc!$D$7)))) | K23: =IF(L23="","",N(L22)*(1+Start!$E$16/12)-L23) | L23: =IF(OR(OR(Calc!$B$4=0,$B23>IF(Start!$D$10="Avalanche",Calc!$B$3,Calc!$B$2)),Calc!$B$8=0),"",IF(N(L22)<=0.005,"",IF(Start!$D$10="Avalanche",INDEX(Calc!BA$75:BA$89,Calc!$F$8),INDEX(Calc!BA$50:BA$64,Calc!$D$8)))) | M23: =IF(N23="","",N(N22)*(1+Start!$E$17/12)-N23) | N23: =IF(OR(OR(Calc!$B$4=0,$B23>IF(Start!$D$10="Avalanche",Calc!$B$3,Calc!$B$2)),Calc!$B$9=0),"",IF(N(N22)<=0.005,"",IF(Start!$D$10="Avalanche",INDEX(Calc!BA$75:BA$89,Calc!$F$9),INDEX(Calc!BA$50:BA$64,Calc!$D$9)))) | O23: =IF(P23="","",N(P22)*(1+Start!$E$18/12)-P23) | P23: =IF(OR(OR(Calc!$B$4=0,$B23>IF(Start!$D$10="Avalanche",Calc!$B$3,Calc!$B$2)),Calc!$B$10=0),"",IF(N(P22)<=0.005,"",IF(Start!$D$10="Avalanche",INDEX(Calc!BA$75:BA$89,Calc!$F$10),INDEX(Calc!BA$50:BA$64,Calc!$D$10)))) | Q23: =IF(R23="","",N(R22)*(1+Start!$E$19/12)-R23) | R23: =IF(OR(OR(Calc!$B$4=0,$B23>IF(Start!$D$10="Avalanche",Calc!$B$3,Calc!$B$2)),Calc!$B$11=0),"",IF(N(R22)<=0.005,"",IF(Start!$D$10="Avalanche",INDEX(Calc!BA$75:BA$89,Calc!$F$11),INDEX(Calc!BA$50:BA$64,Calc!$D$11)))) | S23: =IF(T23="","",N(T22)*(1+Start!$E$20/12)-T23) | T23: =IF(OR(OR(Calc!$B$4=0,$B23>IF(Start!$D$10="Avalanche",Calc!$B$3,Calc!$B$2)),Calc!$B$12=0),"",IF(N(T22)<=0.005,"",IF(Start!$D$10="Avalanche",INDEX(Calc!BA$75:BA$89,Calc!$F$12),INDEX(Calc!BA$50:BA$64,Calc!$D$12)))) | U23: =IF(V23="","",N(V22)*(1+Start!$E$21/12)-V23) | V23: =IF(OR(OR(Calc!$B$4=0,$B23>IF(Start!$D$10="Avalanche",Calc!$B$3,Calc!$B$2)),Calc!$B$13=0),"",IF(N(V22)<=0.005,"",IF(Start!$D$10="Avalanche",INDEX(Calc!BA$75:BA$89,Calc!$F$13),INDEX(Calc!BA$50:BA$64,Calc!$D$13)))) | W23: =IF(X23="","",N(X22)*(1+Start!$E$22/12)-X23) | X23: =IF(OR(OR(Calc!$B$4=0,$B23>IF(Start!$D$10="Avalanche",Calc!$B$3,Calc!$B$2)),Calc!$B$14=0),"",IF(N(X22)<=0.005,"",IF(Start!$D$10="Avalanche",INDEX(Calc!BA$75:BA$89,Calc!$F$14),INDEX(Calc!BA$50:BA$64,Calc!$D$14)))) | Y23: =IF(Z23="","",N(Z22)*(1+Start!$E$23/12)-Z23) | Z23: =IF(OR(OR(Calc!$B$4=0,$B23>IF(Start!$D$10="Avalanche",Calc!$B$3,Calc!$B$2)),Calc!$B$15=0),"",IF(N(Z22)<=0.005,"",IF(Start!$D$10="Avalanche",INDEX(Calc!BA$75:BA$89,Calc!$F$15),INDEX(Calc!BA$50:BA$64,Calc!$D$15)))) | AA23: =IF(AB23="","",N(AB22)*(1+Start!$E$24/12)-AB23) | AB23: =IF(OR(OR(Calc!$B$4=0,$B23>IF(Start!$D$10="Avalanche",Calc!$B$3,Calc!$B$2)),Calc!$B$16=0),"",IF(N(AB22)<=0.005,"",IF(Start!$D$10="Avalanche",INDEX(Calc!BA$75:BA$89,Calc!$F$16),INDEX(Calc!BA$50:BA$64,Calc!$D$16)))) | AC23: =IF(AD23="","",N(AD22)*(1+Start!$E$25/12)-AD23) | AD23: =IF(OR(OR(Calc!$B$4=0,$B23>IF(Start!$D$10="Avalanche",Calc!$B$3,Calc!$B$2)),Calc!$B$17=0),"",IF(N(AD22)<=0.005,"",IF(Start!$D$10="Avalanche",INDEX(Calc!BA$75:BA$89,Calc!$F$17),INDEX(Calc!BA$50:BA$64,Calc!$D$17)))) | AE23: =IF(AF23="","",N(AF22)*(1+Start!$E$26/12)-AF23) | AF23: =IF(OR(OR(Calc!$B$4=0,$B23>IF(Start!$D$10="Avalanche",Calc!$B$3,Calc!$B$2)),Calc!$B$18=0),"",IF(N(AF22)<=0.005,"",IF(Start!$D$10="Avalanche",INDEX(Calc!BA$75:BA$89,Calc!$F$18),INDEX(Calc!BA$50:BA$64,Calc!$D$18)))) | AG23: =IF(AH23="","",N(AH22)*(1+Start!$E$27/12)-AH23) | AH23: =IF(OR(OR(Calc!$B$4=0,$B23>IF(Start!$D$10="Avalanche",Calc!$B$3,Calc!$B$2)),Calc!$B$19=0),"",IF(N(AH22)<=0.005,"",IF(Start!$D$10="Avalanche",INDEX(Calc!BA$75:BA$89,Calc!$F$19),INDEX(Calc!BA$50:BA$64,Calc!$D$19)))) | AI23: =IF(AJ23="","",N(AJ22)*(1+Start!$E$28/12)-AJ23) | AJ23: =IF(OR(OR(Calc!$B$4=0,$B23>IF(Start!$D$10="Avalanche",Calc!$B$3,Calc!$B$2)),Calc!$B$20=0),"",IF(N(AJ22)<=0.005,"",IF(Start!$D$10="Avalanche",INDEX(Calc!BA$75:BA$89,Calc!$F$20),INDEX(Calc!BA$50:BA$64,Calc!$D$20))))
B24: 18 | C24: =IF(Calc!$B$4=0,"",EDATE(Start!$D$11,17)) | D24: =IF(OR(Calc!$B$4=0,$B24>IF(Start!$D$10="Avalanche",Calc!$B$3,Calc!$B$2)),"",SUM(G24,I24,K24,M24,O24,Q24,S24,U24,W24,Y24,AA24,AC24,AE24,AG24,AI24)) | E24: =IF(OR(Calc!$B$4=0,$B24>IF(Start!$D$10="Avalanche",Calc!$B$3,Calc!$B$2)),"",IF(Start!$D$10="Avalanche",Calc!BB$72,Calc!BB$47)) | F24: =IF(Calc!$B$4=0,"",IF($B24>IF(Start!$D$10="Avalanche",Calc!$B$3,Calc!$B$2),NA(),SUM(H24,J24,L24,N24,P24,R24,T24,V24,X24,Z24,AB24,AD24,AF24,AH24,AJ24))) | G24: =IF(H24="","",N(H23)*(1+Start!$E$14/12)-H24) | H24: =IF(OR(OR(Calc!$B$4=0,$B24>IF(Start!$D$10="Avalanche",Calc!$B$3,Calc!$B$2)),Calc!$B$6=0),"",IF(N(H23)<=0.005,"",IF(Start!$D$10="Avalanche",INDEX(Calc!BD$75:BD$89,Calc!$F$6),INDEX(Calc!BD$50:BD$64,Calc!$D$6)))) | I24: =IF(J24="","",N(J23)*(1+Start!$E$15/12)-J24) | J24: =IF(OR(OR(Calc!$B$4=0,$B24>IF(Start!$D$10="Avalanche",Calc!$B$3,Calc!$B$2)),Calc!$B$7=0),"",IF(N(J23)<=0.005,"",IF(Start!$D$10="Avalanche",INDEX(Calc!BD$75:BD$89,Calc!$F$7),INDEX(Calc!BD$50:BD$64,Calc!$D$7)))) | K24: =IF(L24="","",N(L23)*(1+Start!$E$16/12)-L24) | L24: =IF(OR(OR(Calc!$B$4=0,$B24>IF(Start!$D$10="Avalanche",Calc!$B$3,Calc!$B$2)),Calc!$B$8=0),"",IF(N(L23)<=0.005,"",IF(Start!$D$10="Avalanche",INDEX(Calc!BD$75:BD$89,Calc!$F$8),INDEX(Calc!BD$50:BD$64,Calc!$D$8)))) | M24: =IF(N24="","",N(N23)*(1+Start!$E$17/12)-N24) | N24: =IF(OR(OR(Calc!$B$4=0,$B24>IF(Start!$D$10="Avalanche",Calc!$B$3,Calc!$B$2)),Calc!$B$9=0),"",IF(N(N23)<=0.005,"",IF(Start!$D$10="Avalanche",INDEX(Calc!BD$75:BD$89,Calc!$F$9),INDEX(Calc!BD$50:BD$64,Calc!$D$9)))) | O24: =IF(P24="","",N(P23)*(1+Start!$E$18/12)-P24) | P24: =IF(OR(OR(Calc!$B$4=0,$B24>IF(Start!$D$10="Avalanche",Calc!$B$3,Calc!$B$2)),Calc!$B$10=0),"",IF(N(P23)<=0.005,"",IF(Start!$D$10="Avalanche",INDEX(Calc!BD$75:BD$89,Calc!$F$10),INDEX(Calc!BD$50:BD$64,Calc!$D$10)))) | Q24: =IF(R24="","",N(R23)*(1+Start!$E$19/12)-R24) | R24: =IF(OR(OR(Calc!$B$4=0,$B24>IF(Start!$D$10="Avalanche",Calc!$B$3,Calc!$B$2)),Calc!$B$11=0),"",IF(N(R23)<=0.005,"",IF(Start!$D$10="Avalanche",INDEX(Calc!BD$75:BD$89,Calc!$F$11),INDEX(Calc!BD$50:BD$64,Calc!$D$11)))) | S24: =IF(T24="","",N(T23)*(1+Start!$E$20/12)-T24) | T24: =IF(OR(OR(Calc!$B$4=0,$B24>IF(Start!$D$10="Avalanche",Calc!$B$3,Calc!$B$2)),Calc!$B$12=0),"",IF(N(T23)<=0.005,"",IF(Start!$D$10="Avalanche",INDEX(Calc!BD$75:BD$89,Calc!$F$12),INDEX(Calc!BD$50:BD$64,Calc!$D$12)))) | U24: =IF(V24="","",N(V23)*(1+Start!$E$21/12)-V24) | V24: =IF(OR(OR(Calc!$B$4=0,$B24>IF(Start!$D$10="Avalanche",Calc!$B$3,Calc!$B$2)),Calc!$B$13=0),"",IF(N(V23)<=0.005,"",IF(Start!$D$10="Avalanche",INDEX(Calc!BD$75:BD$89,Calc!$F$13),INDEX(Calc!BD$50:BD$64,Calc!$D$13)))) | W24: =IF(X24="","",N(X23)*(1+Start!$E$22/12)-X24) | X24: =IF(OR(OR(Calc!$B$4=0,$B24>IF(Start!$D$10="Avalanche",Calc!$B$3,Calc!$B$2)),Calc!$B$14=0),"",IF(N(X23)<=0.005,"",IF(Start!$D$10="Avalanche",INDEX(Calc!BD$75:BD$89,Calc!$F$14),INDEX(Calc!BD$50:BD$64,Calc!$D$14)))) | Y24: =IF(Z24="","",N(Z23)*(1+Start!$E$23/12)-Z24) | Z24: =IF(OR(OR(Calc!$B$4=0,$B24>IF(Start!$D$10="Avalanche",Calc!$B$3,Calc!$B$2)),Calc!$B$15=0),"",IF(N(Z23)<=0.005,"",IF(Start!$D$10="Avalanche",INDEX(Calc!BD$75:BD$89,Calc!$F$15),INDEX(Calc!BD$50:BD$64,Calc!$D$15)))) | AA24: =IF(AB24="","",N(AB23)*(1+Start!$E$24/12)-AB24) | AB24: =IF(OR(OR(Calc!$B$4=0,$B24>IF(Start!$D$10="Avalanche",Calc!$B$3,Calc!$B$2)),Calc!$B$16=0),"",IF(N(AB23)<=0.005,"",IF(Start!$D$10="Avalanche",INDEX(Calc!BD$75:BD$89,Calc!$F$16),INDEX(Calc!BD$50:BD$64,Calc!$D$16)))) | AC24: =IF(AD24="","",N(AD23)*(1+Start!$E$25/12)-AD24) | AD24: =IF(OR(OR(Calc!$B$4=0,$B24>IF(Start!$D$10="Avalanche",Calc!$B$3,Calc!$B$2)),Calc!$B$17=0),"",IF(N(AD23)<=0.005,"",IF(Start!$D$10="Avalanche",INDEX(Calc!BD$75:BD$89,Calc!$F$17),INDEX(Calc!BD$50:BD$64,Calc!$D$17)))) | AE24: =IF(AF24="","",N(AF23)*(1+Start!$E$26/12)-AF24) | AF24: =IF(OR(OR(Calc!$B$4=0,$B24>IF(Start!$D$10="Avalanche",Calc!$B$3,Calc!$B$2)),Calc!$B$18=0),"",IF(N(AF23)<=0.005,"",IF(Start!$D$10="Avalanche",INDEX(Calc!BD$75:BD$89,Calc!$F$18),INDEX(Calc!BD$50:BD$64,Calc!$D$18)))) | AG24: =IF(AH24="","",N(AH23)*(1+Start!$E$27/12)-AH24) | AH24: =IF(OR(OR(Calc!$B$4=0,$B24>IF(Start!$D$10="Avalanche",Calc!$B$3,Calc!$B$2)),Calc!$B$19=0),"",IF(N(AH23)<=0.005,"",IF(Start!$D$10="Avalanche",INDEX(Calc!BD$75:BD$89,Calc!$F$19),INDEX(Calc!BD$50:BD$64,Calc!$D$19)))) | AI24: =IF(AJ24="","",N(AJ23)*(1+Start!$E$28/12)-AJ24) | AJ24: =IF(OR(OR(Calc!$B$4=0,$B24>IF(Start!$D$10="Avalanche",Calc!$B$3,Calc!$B$2)),Calc!$B$20=0),"",IF(N(AJ23)<=0.005,"",IF(Start!$D$10="Avalanche",INDEX(Calc!BD$75:BD$89,Calc!$F$20),INDEX(Calc!BD$50:BD$64,Calc!$D$20))))
B25: 19 | C25: =IF(Calc!$B$4=0,"",EDATE(Start!$D$11,18)) | D25: =IF(OR(Calc!$B$4=0,$B25>IF(Start!$D$10="Avalanche",Calc!$B$3,Calc!$B$2)),"",SUM(G25,I25,K25,M25,O25,Q25,S25,U25,W25,Y25,AA25,AC25,AE25,AG25,AI25)) | E25: =IF(OR(Calc!$B$4=0,$B25>IF(Start!$D$10="Avalanche",Calc!$B$3,Calc!$B$2)),"",IF(Start!$D$10="Avalanche",Calc!BE$72,Calc!BE$47)) | F25: =IF(Calc!$B$4=0,"",IF($B25>IF(Start!$D$10="Avalanche",Calc!$B$3,Calc!$B$2),NA(),SUM(H25,J25,L25,N25,P25,R25,T25,V25,X25,Z25,AB25,AD25,AF25,AH25,AJ25))) | G25: =IF(H25="","",N(H24)*(1+Start!$E$14/12)-H25) | H25: =IF(OR(OR(Calc!$B$4=0,$B25>IF(Start!$D$10="Avalanche",Calc!$B$3,Calc!$B$2)),Calc!$B$6=0),"",IF(N(H24)<=0.005,"",IF(Start!$D$10="Avalanche",INDEX(Calc!BG$75:BG$89,Calc!$F$6),INDEX(Calc!BG$50:BG$64,Calc!$D$6)))) | I25: =IF(J25="","",N(J24)*(1+Start!$E$15/12)-J25) | J25: =IF(OR(OR(Calc!$B$4=0,$B25>IF(Start!$D$10="Avalanche",Calc!$B$3,Calc!$B$2)),Calc!$B$7=0),"",IF(N(J24)<=0.005,"",IF(Start!$D$10="Avalanche",INDEX(Calc!BG$75:BG$89,Calc!$F$7),INDEX(Calc!BG$50:BG$64,Calc!$D$7)))) | K25: =IF(L25="","",N(L24)*(1+Start!$E$16/12)-L25) | L25: =IF(OR(OR(Calc!$B$4=0,$B25>IF(Start!$D$10="Avalanche",Calc!$B$3,Calc!$B$2)),Calc!$B$8=0),"",IF(N(L24)<=0.005,"",IF(Start!$D$10="Avalanche",INDEX(Calc!BG$75:BG$89,Calc!$F$8),INDEX(Calc!BG$50:BG$64,Calc!$D$8)))) | M25: =IF(N25="","",N(N24)*(1+Start!$E$17/12)-N25) | N25: =IF(OR(OR(Calc!$B$4=0,$B25>IF(Start!$D$10="Avalanche",Calc!$B$3,Calc!$B$2)),Calc!$B$9=0),"",IF(N(N24)<=0.005,"",IF(Start!$D$10="Avalanche",INDEX(Calc!BG$75:BG$89,Calc!$F$9),INDEX(Calc!BG$50:BG$64,Calc!$D$9)))) | O25: =IF(P25="","",N(P24)*(1+Start!$E$18/12)-P25) | P25: =IF(OR(OR(Calc!$B$4=0,$B25>IF(Start!$D$10="Avalanche",Calc!$B$3,Calc!$B$2)),Calc!$B$10=0),"",IF(N(P24)<=0.005,"",IF(Start!$D$10="Avalanche",INDEX(Calc!BG$75:BG$89,Calc!$F$10),INDEX(Calc!BG$50:BG$64,Calc!$D$10)))) | Q25: =IF(R25="","",N(R24)*(1+Start!$E$19/12)-R25) | R25: =IF(OR(OR(Calc!$B$4=0,$B25>IF(Start!$D$10="Avalanche",Calc!$B$3,Calc!$B$2)),Calc!$B$11=0),"",IF(N(R24)<=0.005,"",IF(Start!$D$10="Avalanche",INDEX(Calc!BG$75:BG$89,Calc!$F$11),INDEX(Calc!BG$50:BG$64,Calc!$D$11)))) | S25: =IF(T25="","",N(T24)*(1+Start!$E$20/12)-T25) | T25: =IF(OR(OR(Calc!$B$4=0,$B25>IF(Start!$D$10="Avalanche",Calc!$B$3,Calc!$B$2)),Calc!$B$12=0),"",IF(N(T24)<=0.005,"",IF(Start!$D$10="Avalanche",INDEX(Calc!BG$75:BG$89,Calc!$F$12),INDEX(Calc!BG$50:BG$64,Calc!$D$12)))) | U25: =IF(V25="","",N(V24)*(1+Start!$E$21/12)-V25) | V25: =IF(OR(OR(Calc!$B$4=0,$B25>IF(Start!$D$10="Avalanche",Calc!$B$3,Calc!$B$2)),Calc!$B$13=0),"",IF(N(V24)<=0.005,"",IF(Start!$D$10="Avalanche",INDEX(Calc!BG$75:BG$89,Calc!$F$13),INDEX(Calc!BG$50:BG$64,Calc!$D$13)))) | W25: =IF(X25="","",N(X24)*(1+Start!$E$22/12)-X25) | X25: =IF(OR(OR(Calc!$B$4=0,$B25>IF(Start!$D$10="Avalanche",Calc!$B$3,Calc!$B$2)),Calc!$B$14=0),"",IF(N(X24)<=0.005,"",IF(Start!$D$10="Avalanche",INDEX(Calc!BG$75:BG$89,Calc!$F$14),INDEX(Calc!BG$50:BG$64,Calc!$D$14)))) | Y25: =IF(Z25="","",N(Z24)*(1+Start!$E$23/12)-Z25) | Z25: =IF(OR(OR(Calc!$B$4=0,$B25>IF(Start!$D$10="Avalanche",Calc!$B$3,Calc!$B$2)),Calc!$B$15=0),"",IF(N(Z24)<=0.005,"",IF(Start!$D$10="Avalanche",INDEX(Calc!BG$75:BG$89,Calc!$F$15),INDEX(Calc!BG$50:BG$64,Calc!$D$15)))) | AA25: =IF(AB25="","",N(AB24)*(1+Start!$E$24/12)-AB25) | AB25: =IF(OR(OR(Calc!$B$4=0,$B25>IF(Start!$D$10="Avalanche",Calc!$B$3,Calc!$B$2)),Calc!$B$16=0),"",IF(N(AB24)<=0.005,"",IF(Start!$D$10="Avalanche",INDEX(Calc!BG$75:BG$89,Calc!$F$16),INDEX(Calc!BG$50:BG$64,Calc!$D$16)))) | AC25: =IF(AD25="","",N(AD24)*(1+Start!$E$25/12)-AD25) | AD25: =IF(OR(OR(Calc!$B$4=0,$B25>IF(Start!$D$10="Avalanche",Calc!$B$3,Calc!$B$2)),Calc!$B$17=0),"",IF(N(AD24)<=0.005,"",IF(Start!$D$10="Avalanche",INDEX(Calc!BG$75:BG$89,Calc!$F$17),INDEX(Calc!BG$50:BG$64,Calc!$D$17)))) | AE25: =IF(AF25="","",N(AF24)*(1+Start!$E$26/12)-AF25) | AF25: =IF(OR(OR(Calc!$B$4=0,$B25>IF(Start!$D$10="Avalanche",Calc!$B$3,Calc!$B$2)),Calc!$B$18=0),"",IF(N(AF24)<=0.005,"",IF(Start!$D$10="Avalanche",INDEX(Calc!BG$75:BG$89,Calc!$F$18),INDEX(Calc!BG$50:BG$64,Calc!$D$18)))) | AG25: =IF(AH25="","",N(AH24)*(1+Start!$E$27/12)-AH25) | AH25: =IF(OR(OR(Calc!$B$4=0,$B25>IF(Start!$D$10="Avalanche",Calc!$B$3,Calc!$B$2)),Calc!$B$19=0),"",IF(N(AH24)<=0.005,"",IF(Start!$D$10="Avalanche",INDEX(Calc!BG$75:BG$89,Calc!$F$19),INDEX(Calc!BG$50:BG$64,Calc!$D$19)))) | AI25: =IF(AJ25="","",N(AJ24)*(1+Start!$E$28/12)-AJ25) | AJ25: =IF(OR(OR(Calc!$B$4=0,$B25>IF(Start!$D$10="Avalanche",Calc!$B$3,Calc!$B$2)),Calc!$B$20=0),"",IF(N(AJ24)<=0.005,"",IF(Start!$D$10="Avalanche",INDEX(Calc!BG$75:BG$89,Calc!$F$20),INDEX(Calc!BG$50:BG$64,Calc!$D$20))))
B26: 20 | C26: =IF(Calc!$B$4=0,"",EDATE(Start!$D$11,19)) | D26: =IF(OR(Calc!$B$4=0,$B26>IF(Start!$D$10="Avalanche",Calc!$B$3,Calc!$B$2)),"",SUM(G26,I26,K26,M26,O26,Q26,S26,U26,W26,Y26,AA26,AC26,AE26,AG26,AI26)) | E26: =IF(OR(Calc!$B$4=0,$B26>IF(Start!$D$10="Avalanche",Calc!$B$3,Calc!$B$2)),"",IF(Start!$D$10="Avalanche",Calc!BH$72,Calc!BH$47)) | F26: =IF(Calc!$B$4=0,"",IF($B26>IF(Start!$D$10="Avalanche",Calc!$B$3,Calc!$B$2),NA(),SUM(H26,J26,L26,N26,P26,R26,T26,V26,X26,Z26,AB26,AD26,AF26,AH26,AJ26))) | G26: =IF(H26="","",N(H25)*(1+Start!$E$14/12)-H26) | H26: =IF(OR(OR(Calc!$B$4=0,$B26>IF(Start!$D$10="Avalanche",Calc!$B$3,Calc!$B$2)),Calc!$B$6=0),"",IF(N(H25)<=0.005,"",IF(Start!$D$10="Avalanche",INDEX(Calc!BJ$75:BJ$89,Calc!$F$6),INDEX(Calc!BJ$50:BJ$64,Calc!$D$6)))) | I26: =IF(J26="","",N(J25)*(1+Start!$E$15/12)-J26) | J26: =IF(OR(OR(Calc!$B$4=0,$B26>IF(Start!$D$10="Avalanche",Calc!$B$3,Calc!$B$2)),Calc!$B$7=0),"",IF(N(J25)<=0.005,"",IF(Start!$D$10="Avalanche",INDEX(Calc!BJ$75:BJ$89,Calc!$F$7),INDEX(Calc!BJ$50:BJ$64,Calc!$D$7)))) | K26: =IF(L26="","",N(L25)*(1+Start!$E$16/12)-L26) | L26: =IF(OR(OR(Calc!$B$4=0,$B26>IF(Start!$D$10="Avalanche",Calc!$B$3,Calc!$B$2)),Calc!$B$8=0),"",IF(N(L25)<=0.005,"",IF(Start!$D$10="Avalanche",INDEX(Calc!BJ$75:BJ$89,Calc!$F$8),INDEX(Calc!BJ$50:BJ$64,Calc!$D$8)))) | M26: =IF(N26="","",N(N25)*(1+Start!$E$17/12)-N26) | N26: =IF(OR(OR(Calc!$B$4=0,$B26>IF(Start!$D$10="Avalanche",Calc!$B$3,Calc!$B$2)),Calc!$B$9=0),"",IF(N(N25)<=0.005,"",IF(Start!$D$10="Avalanche",INDEX(Calc!BJ$75:BJ$89,Calc!$F$9),INDEX(Calc!BJ$50:BJ$64,Calc!$D$9)))) | O26: =IF(P26="","",N(P25)*(1+Start!$E$18/12)-P26) | P26: =IF(OR(OR(Calc!$B$4=0,$B26>IF(Start!$D$10="Avalanche",Calc!$B$3,Calc!$B$2)),Calc!$B$10=0),"",IF(N(P25)<=0.005,"",IF(Start!$D$10="Avalanche",INDEX(Calc!BJ$75:BJ$89,Calc!$F$10),INDEX(Calc!BJ$50:BJ$64,Calc!$D$10)))) | Q26: =IF(R26="","",N(R25)*(1+Start!$E$19/12)-R26) | R26: =IF(OR(OR(Calc!$B$4=0,$B26>IF(Start!$D$10="Avalanche",Calc!$B$3,Calc!$B$2)),Calc!$B$11=0),"",IF(N(R25)<=0.005,"",IF(Start!$D$10="Avalanche",INDEX(Calc!BJ$75:BJ$89,Calc!$F$11),INDEX(Calc!BJ$50:BJ$64,Calc!$D$11)))) | S26: =IF(T26="","",N(T25)*(1+Start!$E$20/12)-T26) | T26: =IF(OR(OR(Calc!$B$4=0,$B26>IF(Start!$D$10="Avalanche",Calc!$B$3,Calc!$B$2)),Calc!$B$12=0),"",IF(N(T25)<=0.005,"",IF(Start!$D$10="Avalanche",INDEX(Calc!BJ$75:BJ$89,Calc!$F$12),INDEX(Calc!BJ$50:BJ$64,Calc!$D$12)))) | U26: =IF(V26="","",N(V25)*(1+Start!$E$21/12)-V26) | V26: =IF(OR(OR(Calc!$B$4=0,$B26>IF(Start!$D$10="Avalanche",Calc!$B$3,Calc!$B$2)),Calc!$B$13=0),"",IF(N(V25)<=0.005,"",IF(Start!$D$10="Avalanche",INDEX(Calc!BJ$75:BJ$89,Calc!$F$13),INDEX(Calc!BJ$50:BJ$64,Calc!$D$13)))) | W26: =IF(X26="","",N(X25)*(1+Start!$E$22/12)-X26) | X26: =IF(OR(OR(Calc!$B$4=0,$B26>IF(Start!$D$10="Avalanche",Calc!$B$3,Calc!$B$2)),Calc!$B$14=0),"",IF(N(X25)<=0.005,"",IF(Start!$D$10="Avalanche",INDEX(Calc!BJ$75:BJ$89,Calc!$F$14),INDEX(Calc!BJ$50:BJ$64,Calc!$D$14)))) | Y26: =IF(Z26="","",N(Z25)*(1+Start!$E$23/12)-Z26) | Z26: =IF(OR(OR(Calc!$B$4=0,$B26>IF(Start!$D$10="Avalanche",Calc!$B$3,Calc!$B$2)),Calc!$B$15=0),"",IF(N(Z25)<=0.005,"",IF(Start!$D$10="Avalanche",INDEX(Calc!BJ$75:BJ$89,Calc!$F$15),INDEX(Calc!BJ$50:BJ$64,Calc!$D$15)))) | AA26: =IF(AB26="","",N(AB25)*(1+Start!$E$24/12)-AB26) | AB26: =IF(OR(OR(Calc!$B$4=0,$B26>IF(Start!$D$10="Avalanche",Calc!$B$3,Calc!$B$2)),Calc!$B$16=0),"",IF(N(AB25)<=0.005,"",IF(Start!$D$10="Avalanche",INDEX(Calc!BJ$75:BJ$89,Calc!$F$16),INDEX(Calc!BJ$50:BJ$64,Calc!$D$16)))) | AC26: =IF(AD26="","",N(AD25)*(1+Start!$E$25/12)-AD26) | AD26: =IF(OR(OR(Calc!$B$4=0,$B26>IF(Start!$D$10="Avalanche",Calc!$B$3,Calc!$B$2)),Calc!$B$17=0),"",IF(N(AD25)<=0.005,"",IF(Start!$D$10="Avalanche",INDEX(Calc!BJ$75:BJ$89,Calc!$F$17),INDEX(Calc!BJ$50:BJ$64,Calc!$D$17)))) | AE26: =IF(AF26="","",N(AF25)*(1+Start!$E$26/12)-AF26) | AF26: =IF(OR(OR(Calc!$B$4=0,$B26>IF(Start!$D$10="Avalanche",Calc!$B$3,Calc!$B$2)),Calc!$B$18=0),"",IF(N(AF25)<=0.005,"",IF(Start!$D$10="Avalanche",INDEX(Calc!BJ$75:BJ$89,Calc!$F$18),INDEX(Calc!BJ$50:BJ$64,Calc!$D$18)))) | AG26: =IF(AH26="","",N(AH25)*(1+Start!$E$27/12)-AH26) | AH26: =IF(OR(OR(Calc!$B$4=0,$B26>IF(Start!$D$10="Avalanche",Calc!$B$3,Calc!$B$2)),Calc!$B$19=0),"",IF(N(AH25)<=0.005,"",IF(Start!$D$10="Avalanche",INDEX(Calc!BJ$75:BJ$89,Calc!$F$19),INDEX(Calc!BJ$50:BJ$64,Calc!$D$19)))) | AI26: =IF(AJ26="","",N(AJ25)*(1+Start!$E$28/12)-AJ26) | AJ26: =IF(OR(OR(Calc!$B$4=0,$B26>IF(Start!$D$10="Avalanche",Calc!$B$3,Calc!$B$2)),Calc!$B$20=0),"",IF(N(AJ25)<=0.005,"",IF(Start!$D$10="Avalanche",INDEX(Calc!BJ$75:BJ$89,Calc!$F$20),INDEX(Calc!BJ$50:BJ$64,Calc!$D$20))))
B27: 21 | C27: =IF(Calc!$B$4=0,"",EDATE(Start!$D$11,20)) | D27: =IF(OR(Calc!$B$4=0,$B27>IF(Start!$D$10="Avalanche",Calc!$B$3,Calc!$B$2)),"",SUM(G27,I27,K27,M27,O27,Q27,S27,U27,W27,Y27,AA27,AC27,AE27,AG27,AI27)) | E27: =IF(OR(Calc!$B$4=0,$B27>IF(Start!$D$10="Avalanche",Calc!$B$3,Calc!$B$2)),"",IF(Start!$D$10="Avalanche",Calc!BK$72,Calc!BK$47)) | F27: =IF(Calc!$B$4=0,"",IF($B27>IF(Start!$D$10="Avalanche",Calc!$B$3,Calc!$B$2),NA(),SUM(H27,J27,L27,N27,P27,R27,T27,V27,X27,Z27,AB27,AD27,AF27,AH27,AJ27))) | G27: =IF(H27="","",N(H26)*(1+Start!$E$14/12)-H27) | H27: =IF(OR(OR(Calc!$B$4=0,$B27>IF(Start!$D$10="Avalanche",Calc!$B$3,Calc!$B$2)),Calc!$B$6=0),"",IF(N(H26)<=0.005,"",IF(Start!$D$10="Avalanche",INDEX(Calc!BM$75:BM$89,Calc!$F$6),INDEX(Calc!BM$50:BM$64,Calc!$D$6)))) | I27: =IF(J27="","",N(J26)*(1+Start!$E$15/12)-J27) | J27: =IF(OR(OR(Calc!$B$4=0,$B27>IF(Start!$D$10="Avalanche",Calc!$B$3,Calc!$B$2)),Calc!$B$7=0),"",IF(N(J26)<=0.005,"",IF(Start!$D$10="Avalanche",INDEX(Calc!BM$75:BM$89,Calc!$F$7),INDEX(Calc!BM$50:BM$64,Calc!$D$7)))) | K27: =IF(L27="","",N(L26)*(1+Start!$E$16/12)-L27) | L27: =IF(OR(OR(Calc!$B$4=0,$B27>IF(Start!$D$10="Avalanche",Calc!$B$3,Calc!$B$2)),Calc!$B$8=0),"",IF(N(L26)<=0.005,"",IF(Start!$D$10="Avalanche",INDEX(Calc!BM$75:BM$89,Calc!$F$8),INDEX(Calc!BM$50:BM$64,Calc!$D$8)))) | M27: =IF(N27="","",N(N26)*(1+Start!$E$17/12)-N27) | N27: =IF(OR(OR(Calc!$B$4=0,$B27>IF(Start!$D$10="Avalanche",Calc!$B$3,Calc!$B$2)),Calc!$B$9=0),"",IF(N(N26)<=0.005,"",IF(Start!$D$10="Avalanche",INDEX(Calc!BM$75:BM$89,Calc!$F$9),INDEX(Calc!BM$50:BM$64,Calc!$D$9)))) | O27: =IF(P27="","",N(P26)*(1+Start!$E$18/12)-P27) | P27: =IF(OR(OR(Calc!$B$4=0,$B27>IF(Start!$D$10="Avalanche",Calc!$B$3,Calc!$B$2)),Calc!$B$10=0),"",IF(N(P26)<=0.005,"",IF(Start!$D$10="Avalanche",INDEX(Calc!BM$75:BM$89,Calc!$F$10),INDEX(Calc!BM$50:BM$64,Calc!$D$10)))) | Q27: =IF(R27="","",N(R26)*(1+Start!$E$19/12)-R27) | R27: =IF(OR(OR(Calc!$B$4=0,$B27>IF(Start!$D$10="Avalanche",Calc!$B$3,Calc!$B$2)),Calc!$B$11=0),"",IF(N(R26)<=0.005,"",IF(Start!$D$10="Avalanche",INDEX(Calc!BM$75:BM$89,Calc!$F$11),INDEX(Calc!BM$50:BM$64,Calc!$D$11)))) | S27: =IF(T27="","",N(T26)*(1+Start!$E$20/12)-T27) | T27: =IF(OR(OR(Calc!$B$4=0,$B27>IF(Start!$D$10="Avalanche",Calc!$B$3,Calc!$B$2)),Calc!$B$12=0),"",IF(N(T26)<=0.005,"",IF(Start!$D$10="Avalanche",INDEX(Calc!BM$75:BM$89,Calc!$F$12),INDEX(Calc!BM$50:BM$64,Calc!$D$12)))) | U27: =IF(V27="","",N(V26)*(1+Start!$E$21/12)-V27) | V27: =IF(OR(OR(Calc!$B$4=0,$B27>IF(Start!$D$10="Avalanche",Calc!$B$3,Calc!$B$2)),Calc!$B$13=0),"",IF(N(V26)<=0.005,"",IF(Start!$D$10="Avalanche",INDEX(Calc!BM$75:BM$89,Calc!$F$13),INDEX(Calc!BM$50:BM$64,Calc!$D$13)))) | W27: =IF(X27="","",N(X26)*(1+Start!$E$22/12)-X27) | X27: =IF(OR(OR(Calc!$B$4=0,$B27>IF(Start!$D$10="Avalanche",Calc!$B$3,Calc!$B$2)),Calc!$B$14=0),"",IF(N(X26)<=0.005,"",IF(Start!$D$10="Avalanche",INDEX(Calc!BM$75:BM$89,Calc!$F$14),INDEX(Calc!BM$50:BM$64,Calc!$D$14)))) | Y27: =IF(Z27="","",N(Z26)*(1+Start!$E$23/12)-Z27) | Z27: =IF(OR(OR(Calc!$B$4=0,$B27>IF(Start!$D$10="Avalanche",Calc!$B$3,Calc!$B$2)),Calc!$B$15=0),"",IF(N(Z26)<=0.005,"",IF(Start!$D$10="Avalanche",INDEX(Calc!BM$75:BM$89,Calc!$F$15),INDEX(Calc!BM$50:BM$64,Calc!$D$15)))) | AA27: =IF(AB27="","",N(AB26)*(1+Start!$E$24/12)-AB27) | AB27: =IF(OR(OR(Calc!$B$4=0,$B27>IF(Start!$D$10="Avalanche",Calc!$B$3,Calc!$B$2)),Calc!$B$16=0),"",IF(N(AB26)<=0.005,"",IF(Start!$D$10="Avalanche",INDEX(Calc!BM$75:BM$89,Calc!$F$16),INDEX(Calc!BM$50:BM$64,Calc!$D$16)))) | AC27: =IF(AD27="","",N(AD26)*(1+Start!$E$25/12)-AD27) | AD27: =IF(OR(OR(Calc!$B$4=0,$B27>IF(Start!$D$10="Avalanche",Calc!$B$3,Calc!$B$2)),Calc!$B$17=0),"",IF(N(AD26)<=0.005,"",IF(Start!$D$10="Avalanche",INDEX(Calc!BM$75:BM$89,Calc!$F$17),INDEX(Calc!BM$50:BM$64,Calc!$D$17)))) | AE27: =IF(AF27="","",N(AF26)*(1+Start!$E$26/12)-AF27) | AF27: =IF(OR(OR(Calc!$B$4=0,$B27>IF(Start!$D$10="Avalanche",Calc!$B$3,Calc!$B$2)),Calc!$B$18=0),"",IF(N(AF26)<=0.005,"",IF(Start!$D$10="Avalanche",INDEX(Calc!BM$75:BM$89,Calc!$F$18),INDEX(Calc!BM$50:BM$64,Calc!$D$18)))) | AG27: =IF(AH27="","",N(AH26)*(1+Start!$E$27/12)-AH27) | AH27: =IF(OR(OR(Calc!$B$4=0,$B27>IF(Start!$D$10="Avalanche",Calc!$B$3,Calc!$B$2)),Calc!$B$19=0),"",IF(N(AH26)<=0.005,"",IF(Start!$D$10="Avalanche",INDEX(Calc!BM$75:BM$89,Calc!$F$19),INDEX(Calc!BM$50:BM$64,Calc!$D$19)))) | AI27: =IF(AJ27="","",N(AJ26)*(1+Start!$E$28/12)-AJ27) | AJ27: =IF(OR(OR(Calc!$B$4=0,$B27>IF(Start!$D$10="Avalanche",Calc!$B$3,Calc!$B$2)),Calc!$B$20=0),"",IF(N(AJ26)<=0.005,"",IF(Start!$D$10="Avalanche",INDEX(Calc!BM$75:BM$89,Calc!$F$20),INDEX(Calc!BM$50:BM$64,Calc!$D$20))))
B28: 22 | C28: =IF(Calc!$B$4=0,"",EDATE(Start!$D$11,21)) | D28: =IF(OR(Calc!$B$4=0,$B28>IF(Start!$D$10="Avalanche",Calc!$B$3,Calc!$B$2)),"",SUM(G28,I28,K28,M28,O28,Q28,S28,U28,W28,Y28,AA28,AC28,AE28,AG28,AI28)) | E28: =IF(OR(Calc!$B$4=0,$B28>IF(Start!$D$10="Avalanche",Calc!$B$3,Calc!$B$2)),"",IF(Start!$D$10="Avalanche",Calc!BN$72,Calc!BN$47)) | F28: =IF(Calc!$B$4=0,"",IF($B28>IF(Start!$D$10="Avalanche",Calc!$B$3,Calc!$B$2),NA(),SUM(H28,J28,L28,N28,P28,R28,T28,V28,X28,Z28,AB28,AD28,AF28,AH28,AJ28))) | G28: =IF(H28="","",N(H27)*(1+Start!$E$14/12)-H28) | H28: =IF(OR(OR(Calc!$B$4=0,$B28>IF(Start!$D$10="Avalanche",Calc!$B$3,Calc!$B$2)),Calc!$B$6=0),"",IF(N(H27)<=0.005,"",IF(Start!$D$10="Avalanche",INDEX(Calc!BP$75:BP$89,Calc!$F$6),INDEX(Calc!BP$50:BP$64,Calc!$D$6)))) | I28: =IF(J28="","",N(J27)*(1+Start!$E$15/12)-J28) | J28: =IF(OR(OR(Calc!$B$4=0,$B28>IF(Start!$D$10="Avalanche",Calc!$B$3,Calc!$B$2)),Calc!$B$7=0),"",IF(N(J27)<=0.005,"",IF(Start!$D$10="Avalanche",INDEX(Calc!BP$75:BP$89,Calc!$F$7),INDEX(Calc!BP$50:BP$64,Calc!$D$7)))) | K28: =IF(L28="","",N(L27)*(1+Start!$E$16/12)-L28) | L28: =IF(OR(OR(Calc!$B$4=0,$B28>IF(Start!$D$10="Avalanche",Calc!$B$3,Calc!$B$2)),Calc!$B$8=0),"",IF(N(L27)<=0.005,"",IF(Start!$D$10="Avalanche",INDEX(Calc!BP$75:BP$89,Calc!$F$8),INDEX(Calc!BP$50:BP$64,Calc!$D$8)))) | M28: =IF(N28="","",N(N27)*(1+Start!$E$17/12)-N28) | N28: =IF(OR(OR(Calc!$B$4=0,$B28>IF(Start!$D$10="Avalanche",Calc!$B$3,Calc!$B$2)),Calc!$B$9=0),"",IF(N(N27)<=0.005,"",IF(Start!$D$10="Avalanche",INDEX(Calc!BP$75:BP$89,Calc!$F$9),INDEX(Calc!BP$50:BP$64,Calc!$D$9)))) | O28: =IF(P28="","",N(P27)*(1+Start!$E$18/12)-P28) | P28: =IF(OR(OR(Calc!$B$4=0,$B28>IF(Start!$D$10="Avalanche",Calc!$B$3,Calc!$B$2)),Calc!$B$10=0),"",IF(N(P27)<=0.005,"",IF(Start!$D$10="Avalanche",INDEX(Calc!BP$75:BP$89,Calc!$F$10),INDEX(Calc!BP$50:BP$64,Calc!$D$10)))) | Q28: =IF(R28="","",N(R27)*(1+Start!$E$19/12)-R28) | R28: =IF(OR(OR(Calc!$B$4=0,$B28>IF(Start!$D$10="Avalanche",Calc!$B$3,Calc!$B$2)),Calc!$B$11=0),"",IF(N(R27)<=0.005,"",IF(Start!$D$10="Avalanche",INDEX(Calc!BP$75:BP$89,Calc!$F$11),INDEX(Calc!BP$50:BP$64,Calc!$D$11)))) | S28: =IF(T28="","",N(T27)*(1+Start!$E$20/12)-T28) | T28: =IF(OR(OR(Calc!$B$4=0,$B28>IF(Start!$D$10="Avalanche",Calc!$B$3,Calc!$B$2)),Calc!$B$12=0),"",IF(N(T27)<=0.005,"",IF(Start!$D$10="Avalanche",INDEX(Calc!BP$75:BP$89,Calc!$F$12),INDEX(Calc!BP$50:BP$64,Calc!$D$12)))) | U28: =IF(V28="","",N(V27)*(1+Start!$E$21/12)-V28) | V28: =IF(OR(OR(Calc!$B$4=0,$B28>IF(Start!$D$10="Avalanche",Calc!$B$3,Calc!$B$2)),Calc!$B$13=0),"",IF(N(V27)<=0.005,"",IF(Start!$D$10="Avalanche",INDEX(Calc!BP$75:BP$89,Calc!$F$13),INDEX(Calc!BP$50:BP$64,Calc!$D$13)))) | W28: =IF(X28="","",N(X27)*(1+Start!$E$22/12)-X28) | X28: =IF(OR(OR(Calc!$B$4=0,$B28>IF(Start!$D$10="Avalanche",Calc!$B$3,Calc!$B$2)),Calc!$B$14=0),"",IF(N(X27)<=0.005,"",IF(Start!$D$10="Avalanche",INDEX(Calc!BP$75:BP$89,Calc!$F$14),INDEX(Calc!BP$50:BP$64,Calc!$D$14)))) | Y28: =IF(Z28="","",N(Z27)*(1+Start!$E$23/12)-Z28) | Z28: =IF(OR(OR(Calc!$B$4=0,$B28>IF(Start!$D$10="Avalanche",Calc!$B$3,Calc!$B$2)),Calc!$B$15=0),"",IF(N(Z27)<=0.005,"",IF(Start!$D$10="Avalanche",INDEX(Calc!BP$75:BP$89,Calc!$F$15),INDEX(Calc!BP$50:BP$64,Calc!$D$15)))) | AA28: =IF(AB28="","",N(AB27)*(1+Start!$E$24/12)-AB28) | AB28: =IF(OR(OR(Calc!$B$4=0,$B28>IF(Start!$D$10="Avalanche",Calc!$B$3,Calc!$B$2)),Calc!$B$16=0),"",IF(N(AB27)<=0.005,"",IF(Start!$D$10="Avalanche",INDEX(Calc!BP$75:BP$89,Calc!$F$16),INDEX(Calc!BP$50:BP$64,Calc!$D$16)))) | AC28: =IF(AD28="","",N(AD27)*(1+Start!$E$25/12)-AD28) | AD28: =IF(OR(OR(Calc!$B$4=0,$B28>IF(Start!$D$10="Avalanche",Calc!$B$3,Calc!$B$2)),Calc!$B$17=0),"",IF(N(AD27)<=0.005,"",IF(Start!$D$10="Avalanche",INDEX(Calc!BP$75:BP$89,Calc!$F$17),INDEX(Calc!BP$50:BP$64,Calc!$D$17)))) | AE28: =IF(AF28="","",N(AF27)*(1+Start!$E$26/12)-AF28) | AF28: =IF(OR(OR(Calc!$B$4=0,$B28>IF(Start!$D$10="Avalanche",Calc!$B$3,Calc!$B$2)),Calc!$B$18=0),"",IF(N(AF27)<=0.005,"",IF(Start!$D$10="Avalanche",INDEX(Calc!BP$75:BP$89,Calc!$F$18),INDEX(Calc!BP$50:BP$64,Calc!$D$18)))) | AG28: =IF(AH28="","",N(AH27)*(1+Start!$E$27/12)-AH28) | AH28: =IF(OR(OR(Calc!$B$4=0,$B28>IF(Start!$D$10="Avalanche",Calc!$B$3,Calc!$B$2)),Calc!$B$19=0),"",IF(N(AH27)<=0.005,"",IF(Start!$D$10="Avalanche",INDEX(Calc!BP$75:BP$89,Calc!$F$19),INDEX(Calc!BP$50:BP$64,Calc!$D$19)))) | AI28: =IF(AJ28="","",N(AJ27)*(1+Start!$E$28/12)-AJ28) | AJ28: =IF(OR(OR(Calc!$B$4=0,$B28>IF(Start!$D$10="Avalanche",Calc!$B$3,Calc!$B$2)),Calc!$B$20=0),"",IF(N(AJ27)<=0.005,"",IF(Start!$D$10="Avalanche",INDEX(Calc!BP$75:BP$89,Calc!$F$20),INDEX(Calc!BP$50:BP$64,Calc!$D$20))))
B29: 23 | C29: =IF(Calc!$B$4=0,"",EDATE(Start!$D$11,22)) | D29: =IF(OR(Calc!$B$4=0,$B29>IF(Start!$D$10="Avalanche",Calc!$B$3,Calc!$B$2)),"",SUM(G29,I29,K29,M29,O29,Q29,S29,U29,W29,Y29,AA29,AC29,AE29,AG29,AI29)) | E29: =IF(OR(Calc!$B$4=0,$B29>IF(Start!$D$10="Avalanche",Calc!$B$3,Calc!$B$2)),"",IF(Start!$D$10="Avalanche",Calc!BQ$72,Calc!BQ$47)) | F29: =IF(Calc!$B$4=0,"",IF($B29>IF(Start!$D$10="Avalanche",Calc!$B$3,Calc!$B$2),NA(),SUM(H29,J29,L29,N29,P29,R29,T29,V29,X29,Z29,AB29,AD29,AF29,AH29,AJ29))) | G29: =IF(H29="","",N(H28)*(1+Start!$E$14/12)-H29) | H29: =IF(OR(OR(Calc!$B$4=0,$B29>IF(Start!$D$10="Avalanche",Calc!$B$3,Calc!$B$2)),Calc!$B$6=0),"",IF(N(H28)<=0.005,"",IF(Start!$D$10="Avalanche",INDEX(Calc!BS$75:BS$89,Calc!$F$6),INDEX(Calc!BS$50:BS$64,Calc!$D$6)))) | I29: =IF(J29="","",N(J28)*(1+Start!$E$15/12)-J29) | J29: =IF(OR(OR(Calc!$B$4=0,$B29>IF(Start!$D$10="Avalanche",Calc!$B$3,Calc!$B$2)),Calc!$B$7=0),"",IF(N(J28)<=0.005,"",IF(Start!$D$10="Avalanche",INDEX(Calc!BS$75:BS$89,Calc!$F$7),INDEX(Calc!BS$50:BS$64,Calc!$D$7)))) | K29: =IF(L29="","",N(L28)*(1+Start!$E$16/12)-L29) | L29: =IF(OR(OR(Calc!$B$4=0,$B29>IF(Start!$D$10="Avalanche",Calc!$B$3,Calc!$B$2)),Calc!$B$8=0),"",IF(N(L28)<=0.005,"",IF(Start!$D$10="Avalanche",INDEX(Calc!BS$75:BS$89,Calc!$F$8),INDEX(Calc!BS$50:BS$64,Calc!$D$8)))) | M29: =IF(N29="","",N(N28)*(1+Start!$E$17/12)-N29) | N29: =IF(OR(OR(Calc!$B$4=0,$B29>IF(Start!$D$10="Avalanche",Calc!$B$3,Calc!$B$2)),Calc!$B$9=0),"",IF(N(N28)<=0.005,"",IF(Start!$D$10="Avalanche",INDEX(Calc!BS$75:BS$89,Calc!$F$9),INDEX(Calc!BS$50:BS$64,Calc!$D$9)))) | O29: =IF(P29="","",N(P28)*(1+Start!$E$18/12)-P29) | P29: =IF(OR(OR(Calc!$B$4=0,$B29>IF(Start!$D$10="Avalanche",Calc!$B$3,Calc!$B$2)),Calc!$B$10=0),"",IF(N(P28)<=0.005,"",IF(Start!$D$10="Avalanche",INDEX(Calc!BS$75:BS$89,Calc!$F$10),INDEX(Calc!BS$50:BS$64,Calc!$D$10)))) | Q29: =IF(R29="","",N(R28)*(1+Start!$E$19/12)-R29) | R29: =IF(OR(OR(Calc!$B$4=0,$B29>IF(Start!$D$10="Avalanche",Calc!$B$3,Calc!$B$2)),Calc!$B$11=0),"",IF(N(R28)<=0.005,"",IF(Start!$D$10="Avalanche",INDEX(Calc!BS$75:BS$89,Calc!$F$11),INDEX(Calc!BS$50:BS$64,Calc!$D$11)))) | S29: =IF(T29="","",N(T28)*(1+Start!$E$20/12)-T29) | T29: =IF(OR(OR(Calc!$B$4=0,$B29>IF(Start!$D$10="Avalanche",Calc!$B$3,Calc!$B$2)),Calc!$B$12=0),"",IF(N(T28)<=0.005,"",IF(Start!$D$10="Avalanche",INDEX(Calc!BS$75:BS$89,Calc!$F$12),INDEX(Calc!BS$50:BS$64,Calc!$D$12)))) | U29: =IF(V29="","",N(V28)*(1+Start!$E$21/12)-V29) | V29: =IF(OR(OR(Calc!$B$4=0,$B29>IF(Start!$D$10="Avalanche",Calc!$B$3,Calc!$B$2)),Calc!$B$13=0),"",IF(N(V28)<=0.005,"",IF(Start!$D$10="Avalanche",INDEX(Calc!BS$75:BS$89,Calc!$F$13),INDEX(Calc!BS$50:BS$64,Calc!$D$13)))) | W29: =IF(X29="","",N(X28)*(1+Start!$E$22/12)-X29) | X29: =IF(OR(OR(Calc!$B$4=0,$B29>IF(Start!$D$10="Avalanche",Calc!$B$3,Calc!$B$2)),Calc!$B$14=0),"",IF(N(X28)<=0.005,"",IF(Start!$D$10="Avalanche",INDEX(Calc!BS$75:BS$89,Calc!$F$14),INDEX(Calc!BS$50:BS$64,Calc!$D$14)))) | Y29: =IF(Z29="","",N(Z28)*(1+Start!$E$23/12)-Z29) | Z29: =IF(OR(OR(Calc!$B$4=0,$B29>IF(Start!$D$10="Avalanche",Calc!$B$3,Calc!$B$2)),Calc!$B$15=0),"",IF(N(Z28)<=0.005,"",IF(Start!$D$10="Avalanche",INDEX(Calc!BS$75:BS$89,Calc!$F$15),INDEX(Calc!BS$50:BS$64,Calc!$D$15)))) | AA29: =IF(AB29="","",N(AB28)*(1+Start!$E$24/12)-AB29) | AB29: =IF(OR(OR(Calc!$B$4=0,$B29>IF(Start!$D$10="Avalanche",Calc!$B$3,Calc!$B$2)),Calc!$B$16=0),"",IF(N(AB28)<=0.005,"",IF(Start!$D$10="Avalanche",INDEX(Calc!BS$75:BS$89,Calc!$F$16),INDEX(Calc!BS$50:BS$64,Calc!$D$16)))) | AC29: =IF(AD29="","",N(AD28)*(1+Start!$E$25/12)-AD29) | AD29: =IF(OR(OR(Calc!$B$4=0,$B29>IF(Start!$D$10="Avalanche",Calc!$B$3,Calc!$B$2)),Calc!$B$17=0),"",IF(N(AD28)<=0.005,"",IF(Start!$D$10="Avalanche",INDEX(Calc!BS$75:BS$89,Calc!$F$17),INDEX(Calc!BS$50:BS$64,Calc!$D$17)))) | AE29: =IF(AF29="","",N(AF28)*(1+Start!$E$26/12)-AF29) | AF29: =IF(OR(OR(Calc!$B$4=0,$B29>IF(Start!$D$10="Avalanche",Calc!$B$3,Calc!$B$2)),Calc!$B$18=0),"",IF(N(AF28)<=0.005,"",IF(Start!$D$10="Avalanche",INDEX(Calc!BS$75:BS$89,Calc!$F$18),INDEX(Calc!BS$50:BS$64,Calc!$D$18)))) | AG29: =IF(AH29="","",N(AH28)*(1+Start!$E$27/12)-AH29) | AH29: =IF(OR(OR(Calc!$B$4=0,$B29>IF(Start!$D$10="Avalanche",Calc!$B$3,Calc!$B$2)),Calc!$B$19=0),"",IF(N(AH28)<=0.005,"",IF(Start!$D$10="Avalanche",INDEX(Calc!BS$75:BS$89,Calc!$F$19),INDEX(Calc!BS$50:BS$64,Calc!$D$19)))) | AI29: =IF(AJ29="","",N(AJ28)*(1+Start!$E$28/12)-AJ29) | AJ29: =IF(OR(OR(Calc!$B$4=0,$B29>IF(Start!$D$10="Avalanche",Calc!$B$3,Calc!$B$2)),Calc!$B$20=0),"",IF(N(AJ28)<=0.005,"",IF(Start!$D$10="Avalanche",INDEX(Calc!BS$75:BS$89,Calc!$F$20),INDEX(Calc!BS$50:BS$64,Calc!$D$20))))
B30: 24 | C30: =IF(Calc!$B$4=0,"",EDATE(Start!$D$11,23)) | D30: =IF(OR(Calc!$B$4=0,$B30>IF(Start!$D$10="Avalanche",Calc!$B$3,Calc!$B$2)),"",SUM(G30,I30,K30,M30,O30,Q30,S30,U30,W30,Y30,AA30,AC30,AE30,AG30,AI30)) | E30: =IF(OR(Calc!$B$4=0,$B30>IF(Start!$D$10="Avalanche",Calc!$B$3,Calc!$B$2)),"",IF(Start!$D$10="Avalanche",Calc!BT$72,Calc!BT$47)) | F30: =IF(Calc!$B$4=0,"",IF($B30>IF(Start!$D$10="Avalanche",Calc!$B$3,Calc!$B$2),NA(),SUM(H30,J30,L30,N30,P30,R30,T30,V30,X30,Z30,AB30,AD30,AF30,AH30,AJ30))) | G30: =IF(H30="","",N(H29)*(1+Start!$E$14/12)-H30) | H30: =IF(OR(OR(Calc!$B$4=0,$B30>IF(Start!$D$10="Avalanche",Calc!$B$3,Calc!$B$2)),Calc!$B$6=0),"",IF(N(H29)<=0.005,"",IF(Start!$D$10="Avalanche",INDEX(Calc!BV$75:BV$89,Calc!$F$6),INDEX(Calc!BV$50:BV$64,Calc!$D$6)))) | I30: =IF(J30="","",N(J29)*(1+Start!$E$15/12)-J30) | J30: =IF(OR(OR(Calc!$B$4=0,$B30>IF(Start!$D$10="Avalanche",Calc!$B$3,Calc!$B$2)),Calc!$B$7=0),"",IF(N(J29)<=0.005,"",IF(Start!$D$10="Avalanche",INDEX(Calc!BV$75:BV$89,Calc!$F$7),INDEX(Calc!BV$50:BV$64,Calc!$D$7)))) | K30: =IF(L30="","",N(L29)*(1+Start!$E$16/12)-L30) | L30: =IF(OR(OR(Calc!$B$4=0,$B30>IF(Start!$D$10="Avalanche",Calc!$B$3,Calc!$B$2)),Calc!$B$8=0),"",IF(N(L29)<=0.005,"",IF(Start!$D$10="Avalanche",INDEX(Calc!BV$75:BV$89,Calc!$F$8),INDEX(Calc!BV$50:BV$64,Calc!$D$8)))) | M30: =IF(N30="","",N(N29)*(1+Start!$E$17/12)-N30) | N30: =IF(OR(OR(Calc!$B$4=0,$B30>IF(Start!$D$10="Avalanche",Calc!$B$3,Calc!$B$2)),Calc!$B$9=0),"",IF(N(N29)<=0.005,"",IF(Start!$D$10="Avalanche",INDEX(Calc!BV$75:BV$89,Calc!$F$9),INDEX(Calc!BV$50:BV$64,Calc!$D$9)))) | O30: =IF(P30="","",N(P29)*(1+Start!$E$18/12)-P30) | P30: =IF(OR(OR(Calc!$B$4=0,$B30>IF(Start!$D$10="Avalanche",Calc!$B$3,Calc!$B$2)),Calc!$B$10=0),"",IF(N(P29)<=0.005,"",IF(Start!$D$10="Avalanche",INDEX(Calc!BV$75:BV$89,Calc!$F$10),INDEX(Calc!BV$50:BV$64,Calc!$D$10)))) | Q30: =IF(R30="","",N(R29)*(1+Start!$E$19/12)-R30) | R30: =IF(OR(OR(Calc!$B$4=0,$B30>IF(Start!$D$10="Avalanche",Calc!$B$3,Calc!$B$2)),Calc!$B$11=0),"",IF(N(R29)<=0.005,"",IF(Start!$D$10="Avalanche",INDEX(Calc!BV$75:BV$89,Calc!$F$11),INDEX(Calc!BV$50:BV$64,Calc!$D$11)))) | S30: =IF(T30="","",N(T29)*(1+Start!$E$20/12)-T30) | T30: =IF(OR(OR(Calc!$B$4=0,$B30>IF(Start!$D$10="Avalanche",Calc!$B$3,Calc!$B$2)),Calc!$B$12=0),"",IF(N(T29)<=0.005,"",IF(Start!$D$10="Avalanche",INDEX(Calc!BV$75:BV$89,Calc!$F$12),INDEX(Calc!BV$50:BV$64,Calc!$D$12)))) | U30: =IF(V30="","",N(V29)*(1+Start!$E$21/12)-V30) | V30: =IF(OR(OR(Calc!$B$4=0,$B30>IF(Start!$D$10="Avalanche",Calc!$B$3,Calc!$B$2)),Calc!$B$13=0),"",IF(N(V29)<=0.005,"",IF(Start!$D$10="Avalanche",INDEX(Calc!BV$75:BV$89,Calc!$F$13),INDEX(Calc!BV$50:BV$64,Calc!$D$13)))) | W30: =IF(X30="","",N(X29)*(1+Start!$E$22/12)-X30) | X30: =IF(OR(OR(Calc!$B$4=0,$B30>IF(Start!$D$10="Avalanche",Calc!$B$3,Calc!$B$2)),Calc!$B$14=0),"",IF(N(X29)<=0.005,"",IF(Start!$D$10="Avalanche",INDEX(Calc!BV$75:BV$89,Calc!$F$14),INDEX(Calc!BV$50:BV$64,Calc!$D$14)))) | Y30: =IF(Z30="","",N(Z29)*(1+Start!$E$23/12)-Z30) | Z30: =IF(OR(OR(Calc!$B$4=0,$B30>IF(Start!$D$10="Avalanche",Calc!$B$3,Calc!$B$2)),Calc!$B$15=0),"",IF(N(Z29)<=0.005,"",IF(Start!$D$10="Avalanche",INDEX(Calc!BV$75:BV$89,Calc!$F$15),INDEX(Calc!BV$50:BV$64,Calc!$D$15)))) | AA30: =IF(AB30="","",N(AB29)*(1+Start!$E$24/12)-AB30) | AB30: =IF(OR(OR(Calc!$B$4=0,$B30>IF(Start!$D$10="Avalanche",Calc!$B$3,Calc!$B$2)),Calc!$B$16=0),"",IF(N(AB29)<=0.005,"",IF(Start!$D$10="Avalanche",INDEX(Calc!BV$75:BV$89,Calc!$F$16),INDEX(Calc!BV$50:BV$64,Calc!$D$16)))) | AC30: =IF(AD30="","",N(AD29)*(1+Start!$E$25/12)-AD30) | AD30: =IF(OR(OR(Calc!$B$4=0,$B30>IF(Start!$D$10="Avalanche",Calc!$B$3,Calc!$B$2)),Calc!$B$17=0),"",IF(N(AD29)<=0.005,"",IF(Start!$D$10="Avalanche",INDEX(Calc!BV$75:BV$89,Calc!$F$17),INDEX(Calc!BV$50:BV$64,Calc!$D$17)))) | AE30: =IF(AF30="","",N(AF29)*(1+Start!$E$26/12)-AF30) | AF30: =IF(OR(OR(Calc!$B$4=0,$B30>IF(Start!$D$10="Avalanche",Calc!$B$3,Calc!$B$2)),Calc!$B$18=0),"",IF(N(AF29)<=0.005,"",IF(Start!$D$10="Avalanche",INDEX(Calc!BV$75:BV$89,Calc!$F$18),INDEX(Calc!BV$50:BV$64,Calc!$D$18)))) | AG30: =IF(AH30="","",N(AH29)*(1+Start!$E$27/12)-AH30) | AH30: =IF(OR(OR(Calc!$B$4=0,$B30>IF(Start!$D$10="Avalanche",Calc!$B$3,Calc!$B$2)),Calc!$B$19=0),"",IF(N(AH29)<=0.005,"",IF(Start!$D$10="Avalanche",INDEX(Calc!BV$75:BV$89,Calc!$F$19),INDEX(Calc!BV$50:BV$64,Calc!$D$19)))) | AI30: =IF(AJ30="","",N(AJ29)*(1+Start!$E$28/12)-AJ30) | AJ30: =IF(OR(OR(Calc!$B$4=0,$B30>IF(Start!$D$10="Avalanche",Calc!$B$3,Calc!$B$2)),Calc!$B$20=0),"",IF(N(AJ29)<=0.005,"",IF(Start!$D$10="Avalanche",INDEX(Calc!BV$75:BV$89,Calc!$F$20),INDEX(Calc!BV$50:BV$64,Calc!$D$20))))
B31: 25 | C31: =IF(Calc!$B$4=0,"",EDATE(Start!$D$11,24)) | D31: =IF(OR(Calc!$B$4=0,$B31>IF(Start!$D$10="Avalanche",Calc!$B$3,Calc!$B$2)),"",SUM(G31,I31,K31,M31,O31,Q31,S31,U31,W31,Y31,AA31,AC31,AE31,AG31,AI31)) | E31: =IF(OR(Calc!$B$4=0,$B31>IF(Start!$D$10="Avalanche",Calc!$B$3,Calc!$B$2)),"",IF(Start!$D$10="Avalanche",Calc!BW$72,Calc!BW$47)) | F31: =IF(Calc!$B$4=0,"",IF($B31>IF(Start!$D$10="Avalanche",Calc!$B$3,Calc!$B$2),NA(),SUM(H31,J31,L31,N31,P31,R31,T31,V31,X31,Z31,AB31,AD31,AF31,AH31,AJ31))) | G31: =IF(H31="","",N(H30)*(1+Start!$E$14/12)-H31) | H31: =IF(OR(OR(Calc!$B$4=0,$B31>IF(Start!$D$10="Avalanche",Calc!$B$3,Calc!$B$2)),Calc!$B$6=0),"",IF(N(H30)<=0.005,"",IF(Start!$D$10="Avalanche",INDEX(Calc!BY$75:BY$89,Calc!$F$6),INDEX(Calc!BY$50:BY$64,Calc!$D$6)))) | I31: =IF(J31="","",N(J30)*(1+Start!$E$15/12)-J31) | J31: =IF(OR(OR(Calc!$B$4=0,$B31>IF(Start!$D$10="Avalanche",Calc!$B$3,Calc!$B$2)),Calc!$B$7=0),"",IF(N(J30)<=0.005,"",IF(Start!$D$10="Avalanche",INDEX(Calc!BY$75:BY$89,Calc!$F$7),INDEX(Calc!BY$50:BY$64,Calc!$D$7)))) | K31: =IF(L31="","",N(L30)*(1+Start!$E$16/12)-L31) | L31: =IF(OR(OR(Calc!$B$4=0,$B31>IF(Start!$D$10="Avalanche",Calc!$B$3,Calc!$B$2)),Calc!$B$8=0),"",IF(N(L30)<=0.005,"",IF(Start!$D$10="Avalanche",INDEX(Calc!BY$75:BY$89,Calc!$F$8),INDEX(Calc!BY$50:BY$64,Calc!$D$8)))) | M31: =IF(N31="","",N(N30)*(1+Start!$E$17/12)-N31) | N31: =IF(OR(OR(Calc!$B$4=0,$B31>IF(Start!$D$10="Avalanche",Calc!$B$3,Calc!$B$2)),Calc!$B$9=0),"",IF(N(N30)<=0.005,"",IF(Start!$D$10="Avalanche",INDEX(Calc!BY$75:BY$89,Calc!$F$9),INDEX(Calc!BY$50:BY$64,Calc!$D$9)))) | O31: =IF(P31="","",N(P30)*(1+Start!$E$18/12)-P31) | P31: =IF(OR(OR(Calc!$B$4=0,$B31>IF(Start!$D$10="Avalanche",Calc!$B$3,Calc!$B$2)),Calc!$B$10=0),"",IF(N(P30)<=0.005,"",IF(Start!$D$10="Avalanche",INDEX(Calc!BY$75:BY$89,Calc!$F$10),INDEX(Calc!BY$50:BY$64,Calc!$D$10)))) | Q31: =IF(R31="","",N(R30)*(1+Start!$E$19/12)-R31) | R31: =IF(OR(OR(Calc!$B$4=0,$B31>IF(Start!$D$10="Avalanche",Calc!$B$3,Calc!$B$2)),Calc!$B$11=0),"",IF(N(R30)<=0.005,"",IF(Start!$D$10="Avalanche",INDEX(Calc!BY$75:BY$89,Calc!$F$11),INDEX(Calc!BY$50:BY$64,Calc!$D$11)))) | S31: =IF(T31="","",N(T30)*(1+Start!$E$20/12)-T31) | T31: =IF(OR(OR(Calc!$B$4=0,$B31>IF(Start!$D$10="Avalanche",Calc!$B$3,Calc!$B$2)),Calc!$B$12=0),"",IF(N(T30)<=0.005,"",IF(Start!$D$10="Avalanche",INDEX(Calc!BY$75:BY$89,Calc!$F$12),INDEX(Calc!BY$50:BY$64,Calc!$D$12)))) | U31: =IF(V31="","",N(V30)*(1+Start!$E$21/12)-V31) | V31: =IF(OR(OR(Calc!$B$4=0,$B31>IF(Start!$D$10="Avalanche",Calc!$B$3,Calc!$B$2)),Calc!$B$13=0),"",IF(N(V30)<=0.005,"",IF(Start!$D$10="Avalanche",INDEX(Calc!BY$75:BY$89,Calc!$F$13),INDEX(Calc!BY$50:BY$64,Calc!$D$13)))) | W31: =IF(X31="","",N(X30)*(1+Start!$E$22/12)-X31) | X31: =IF(OR(OR(Calc!$B$4=0,$B31>IF(Start!$D$10="Avalanche",Calc!$B$3,Calc!$B$2)),Calc!$B$14=0),"",IF(N(X30)<=0.005,"",IF(Start!$D$10="Avalanche",INDEX(Calc!BY$75:BY$89,Calc!$F$14),INDEX(Calc!BY$50:BY$64,Calc!$D$14)))) | Y31: =IF(Z31="","",N(Z30)*(1+Start!$E$23/12)-Z31) | Z31: =IF(OR(OR(Calc!$B$4=0,$B31>IF(Start!$D$10="Avalanche",Calc!$B$3,Calc!$B$2)),Calc!$B$15=0),"",IF(N(Z30)<=0.005,"",IF(Start!$D$10="Avalanche",INDEX(Calc!BY$75:BY$89,Calc!$F$15),INDEX(Calc!BY$50:BY$64,Calc!$D$15)))) | AA31: =IF(AB31="","",N(AB30)*(1+Start!$E$24/12)-AB31) | AB31: =IF(OR(OR(Calc!$B$4=0,$B31>IF(Start!$D$10="Avalanche",Calc!$B$3,Calc!$B$2)),Calc!$B$16=0),"",IF(N(AB30)<=0.005,"",IF(Start!$D$10="Avalanche",INDEX(Calc!BY$75:BY$89,Calc!$F$16),INDEX(Calc!BY$50:BY$64,Calc!$D$16)))) | AC31: =IF(AD31="","",N(AD30)*(1+Start!$E$25/12)-AD31) | AD31: =IF(OR(OR(Calc!$B$4=0,$B31>IF(Start!$D$10="Avalanche",Calc!$B$3,Calc!$B$2)),Calc!$B$17=0),"",IF(N(AD30)<=0.005,"",IF(Start!$D$10="Avalanche",INDEX(Calc!BY$75:BY$89,Calc!$F$17),INDEX(Calc!BY$50:BY$64,Calc!$D$17)))) | AE31: =IF(AF31="","",N(AF30)*(1+Start!$E$26/12)-AF31) | AF31: =IF(OR(OR(Calc!$B$4=0,$B31>IF(Start!$D$10="Avalanche",Calc!$B$3,Calc!$B$2)),Calc!$B$18=0),"",IF(N(AF30)<=0.005,"",IF(Start!$D$10="Avalanche",INDEX(Calc!BY$75:BY$89,Calc!$F$18),INDEX(Calc!BY$50:BY$64,Calc!$D$18)))) | AG31: =IF(AH31="","",N(AH30)*(1+Start!$E$27/12)-AH31) | AH31: =IF(OR(OR(Calc!$B$4=0,$B31>IF(Start!$D$10="Avalanche",Calc!$B$3,Calc!$B$2)),Calc!$B$19=0),"",IF(N(AH30)<=0.005,"",IF(Start!$D$10="Avalanche",INDEX(Calc!BY$75:BY$89,Calc!$F$19),INDEX(Calc!BY$50:BY$64,Calc!$D$19)))) | AI31: =IF(AJ31="","",N(AJ30)*(1+Start!$E$28/12)-AJ31) | AJ31: =IF(OR(OR(Calc!$B$4=0,$B31>IF(Start!$D$10="Avalanche",Calc!$B$3,Calc!$B$2)),Calc!$B$20=0),"",IF(N(AJ30)<=0.005,"",IF(Start!$D$10="Avalanche",INDEX(Calc!BY$75:BY$89,Calc!$F$20),INDEX(Calc!BY$50:BY$64,Calc!$D$20))))
B32: 26 | C32: =IF(Calc!$B$4=0,"",EDATE(Start!$D$11,25)) | D32: =IF(OR(Calc!$B$4=0,$B32>IF(Start!$D$10="Avalanche",Calc!$B$3,Calc!$B$2)),"",SUM(G32,I32,K32,M32,O32,Q32,S32,U32,W32,Y32,AA32,AC32,AE32,AG32,AI32)) | E32: =IF(OR(Calc!$B$4=0,$B32>IF(Start!$D$10="Avalanche",Calc!$B$3,Calc!$B$2)),"",IF(Start!$D$10="Avalanche",Calc!BZ$72,Calc!BZ$47)) | F32: =IF(Calc!$B$4=0,"",IF($B32>IF(Start!$D$10="Avalanche",Calc!$B$3,Calc!$B$2),NA(),SUM(H32,J32,L32,N32,P32,R32,T32,V32,X32,Z32,AB32,AD32,AF32,AH32,AJ32))) | G32: =IF(H32="","",N(H31)*(1+Start!$E$14/12)-H32) | H32: =IF(OR(OR(Calc!$B$4=0,$B32>IF(Start!$D$10="Avalanche",Calc!$B$3,Calc!$B$2)),Calc!$B$6=0),"",IF(N(H31)<=0.005,"",IF(Start!$D$10="Avalanche",INDEX(Calc!CB$75:CB$89,Calc!$F$6),INDEX(Calc!CB$50:CB$64,Calc!$D$6)))) | I32: =IF(J32="","",N(J31)*(1+Start!$E$15/12)-J32) | J32: =IF(OR(OR(Calc!$B$4=0,$B32>IF(Start!$D$10="Avalanche",Calc!$B$3,Calc!$B$2)),Calc!$B$7=0),"",IF(N(J31)<=0.005,"",IF(Start!$D$10="Avalanche",INDEX(Calc!CB$75:CB$89,Calc!$F$7),INDEX(Calc!CB$50:CB$64,Calc!$D$7)))) | K32: =IF(L32="","",N(L31)*(1+Start!$E$16/12)-L32) | L32: =IF(OR(OR(Calc!$B$4=0,$B32>IF(Start!$D$10="Avalanche",Calc!$B$3,Calc!$B$2)),Calc!$B$8=0),"",IF(N(L31)<=0.005,"",IF(Start!$D$10="Avalanche",INDEX(Calc!CB$75:CB$89,Calc!$F$8),INDEX(Calc!CB$50:CB$64,Calc!$D$8)))) | M32: =IF(N32="","",N(N31)*(1+Start!$E$17/12)-N32) | N32: =IF(OR(OR(Calc!$B$4=0,$B32>IF(Start!$D$10="Avalanche",Calc!$B$3,Calc!$B$2)),Calc!$B$9=0),"",IF(N(N31)<=0.005,"",IF(Start!$D$10="Avalanche",INDEX(Calc!CB$75:CB$89,Calc!$F$9),INDEX(Calc!CB$50:CB$64,Calc!$D$9)))) | O32: =IF(P32="","",N(P31)*(1+Start!$E$18/12)-P32) | P32: =IF(OR(OR(Calc!$B$4=0,$B32>IF(Start!$D$10="Avalanche",Calc!$B$3,Calc!$B$2)),Calc!$B$10=0),"",IF(N(P31)<=0.005,"",IF(Start!$D$10="Avalanche",INDEX(Calc!CB$75:CB$89,Calc!$F$10),INDEX(Calc!CB$50:CB$64,Calc!$D$10)))) | Q32: =IF(R32="","",N(R31)*(1+Start!$E$19/12)-R32) | R32: =IF(OR(OR(Calc!$B$4=0,$B32>IF(Start!$D$10="Avalanche",Calc!$B$3,Calc!$B$2)),Calc!$B$11=0),"",IF(N(R31)<=0.005,"",IF(Start!$D$10="Avalanche",INDEX(Calc!CB$75:CB$89,Calc!$F$11),INDEX(Calc!CB$50:CB$64,Calc!$D$11)))) | S32: =IF(T32="","",N(T31)*(1+Start!$E$20/12)-T32) | T32: =IF(OR(OR(Calc!$B$4=0,$B32>IF(Start!$D$10="Avalanche",Calc!$B$3,Calc!$B$2)),Calc!$B$12=0),"",IF(N(T31)<=0.005,"",IF(Start!$D$10="Avalanche",INDEX(Calc!CB$75:CB$89,Calc!$F$12),INDEX(Calc!CB$50:CB$64,Calc!$D$12)))) | U32: =IF(V32="","",N(V31)*(1+Start!$E$21/12)-V32) | V32: =IF(OR(OR(Calc!$B$4=0,$B32>IF(Start!$D$10="Avalanche",Calc!$B$3,Calc!$B$2)),Calc!$B$13=0),"",IF(N(V31)<=0.005,"",IF(Start!$D$10="Avalanche",INDEX(Calc!CB$75:CB$89,Calc!$F$13),INDEX(Calc!CB$50:CB$64,Calc!$D$13)))) | W32: =IF(X32="","",N(X31)*(1+Start!$E$22/12)-X32) | X32: =IF(OR(OR(Calc!$B$4=0,$B32>IF(Start!$D$10="Avalanche",Calc!$B$3,Calc!$B$2)),Calc!$B$14=0),"",IF(N(X31)<=0.005,"",IF(Start!$D$10="Avalanche",INDEX(Calc!CB$75:CB$89,Calc!$F$14),INDEX(Calc!CB$50:CB$64,Calc!$D$14)))) | Y32: =IF(Z32="","",N(Z31)*(1+Start!$E$23/12)-Z32) | Z32: =IF(OR(OR(Calc!$B$4=0,$B32>IF(Start!$D$10="Avalanche",Calc!$B$3,Calc!$B$2)),Calc!$B$15=0),"",IF(N(Z31)<=0.005,"",IF(Start!$D$10="Avalanche",INDEX(Calc!CB$75:CB$89,Calc!$F$15),INDEX(Calc!CB$50:CB$64,Calc!$D$15)))) | AA32: =IF(AB32="","",N(AB31)*(1+Start!$E$24/12)-AB32) | AB32: =IF(OR(OR(Calc!$B$4=0,$B32>IF(Start!$D$10="Avalanche",Calc!$B$3,Calc!$B$2)),Calc!$B$16=0),"",IF(N(AB31)<=0.005,"",IF(Start!$D$10="Avalanche",INDEX(Calc!CB$75:CB$89,Calc!$F$16),INDEX(Calc!CB$50:CB$64,Calc!$D$16)))) | AC32: =IF(AD32="","",N(AD31)*(1+Start!$E$25/12)-AD32) | AD32: =IF(OR(OR(Calc!$B$4=0,$B32>IF(Start!$D$10="Avalanche",Calc!$B$3,Calc!$B$2)),Calc!$B$17=0),"",IF(N(AD31)<=0.005,"",IF(Start!$D$10="Avalanche",INDEX(Calc!CB$75:CB$89,Calc!$F$17),INDEX(Calc!CB$50:CB$64,Calc!$D$17)))) | AE32: =IF(AF32="","",N(AF31)*(1+Start!$E$26/12)-AF32) | AF32: =IF(OR(OR(Calc!$B$4=0,$B32>IF(Start!$D$10="Avalanche",Calc!$B$3,Calc!$B$2)),Calc!$B$18=0),"",IF(N(AF31)<=0.005,"",IF(Start!$D$10="Avalanche",INDEX(Calc!CB$75:CB$89,Calc!$F$18),INDEX(Calc!CB$50:CB$64,Calc!$D$18)))) | AG32: =IF(AH32="","",N(AH31)*(1+Start!$E$27/12)-AH32) | AH32: =IF(OR(OR(Calc!$B$4=0,$B32>IF(Start!$D$10="Avalanche",Calc!$B$3,Calc!$B$2)),Calc!$B$19=0),"",IF(N(AH31)<=0.005,"",IF(Start!$D$10="Avalanche",INDEX(Calc!CB$75:CB$89,Calc!$F$19),INDEX(Calc!CB$50:CB$64,Calc!$D$19)))) | AI32: =IF(AJ32="","",N(AJ31)*(1+Start!$E$28/12)-AJ32) | AJ32: =IF(OR(OR(Calc!$B$4=0,$B32>IF(Start!$D$10="Avalanche",Calc!$B$3,Calc!$B$2)),Calc!$B$20=0),"",IF(N(AJ31)<=0.005,"",IF(Start!$D$10="Avalanche",INDEX(Calc!CB$75:CB$89,Calc!$F$20),INDEX(Calc!CB$50:CB$64,Calc!$D$20))))
B33: 27 | C33: =IF(Calc!$B$4=0,"",EDATE(Start!$D$11,26)) | D33: =IF(OR(Calc!$B$4=0,$B33>IF(Start!$D$10="Avalanche",Calc!$B$3,Calc!$B$2)),"",SUM(G33,I33,K33,M33,O33,Q33,S33,U33,W33,Y33,AA33,AC33,AE33,AG33,AI33)) | E33: =IF(OR(Calc!$B$4=0,$B33>IF(Start!$D$10="Avalanche",Calc!$B$3,Calc!$B$2)),"",IF(Start!$D$10="Avalanche",Calc!CC$72,Calc!CC$47)) | F33: =IF(Calc!$B$4=0,"",IF($B33>IF(Start!$D$10="Avalanche",Calc!$B$3,Calc!$B$2),NA(),SUM(H33,J33,L33,N33,P33,R33,T33,V33,X33,Z33,AB33,AD33,AF33,AH33,AJ33))) | G33: =IF(H33="","",N(H32)*(1+Start!$E$14/12)-H33) | H33: =IF(OR(OR(Calc!$B$4=0,$B33>IF(Start!$D$10="Avalanche",Calc!$B$3,Calc!$B$2)),Calc!$B$6=0),"",IF(N(H32)<=0.005,"",IF(Start!$D$10="Avalanche",INDEX(Calc!CE$75:CE$89,Calc!$F$6),INDEX(Calc!CE$50:CE$64,Calc!$D$6)))) | I33: =IF(J33="","",N(J32)*(1+Start!$E$15/12)-J33) | J33: =IF(OR(OR(Calc!$B$4=0,$B33>IF(Start!$D$10="Avalanche",Calc!$B$3,Calc!$B$2)),Calc!$B$7=0),"",IF(N(J32)<=0.005,"",IF(Start!$D$10="Avalanche",INDEX(Calc!CE$75:CE$89,Calc!$F$7),INDEX(Calc!CE$50:CE$64,Calc!$D$7)))) | K33: =IF(L33="","",N(L32)*(1+Start!$E$16/12)-L33) | L33: =IF(OR(OR(Calc!$B$4=0,$B33>IF(Start!$D$10="Avalanche",Calc!$B$3,Calc!$B$2)),Calc!$B$8=0),"",IF(N(L32)<=0.005,"",IF(Start!$D$10="Avalanche",INDEX(Calc!CE$75:CE$89,Calc!$F$8),INDEX(Calc!CE$50:CE$64,Calc!$D$8)))) | M33: =IF(N33="","",N(N32)*(1+Start!$E$17/12)-N33) | N33: =IF(OR(OR(Calc!$B$4=0,$B33>IF(Start!$D$10="Avalanche",Calc!$B$3,Calc!$B$2)),Calc!$B$9=0),"",IF(N(N32)<=0.005,"",IF(Start!$D$10="Avalanche",INDEX(Calc!CE$75:CE$89,Calc!$F$9),INDEX(Calc!CE$50:CE$64,Calc!$D$9)))) | O33: =IF(P33="","",N(P32)*(1+Start!$E$18/12)-P33) | P33: =IF(OR(OR(Calc!$B$4=0,$B33>IF(Start!$D$10="Avalanche",Calc!$B$3,Calc!$B$2)),Calc!$B$10=0),"",IF(N(P32)<=0.005,"",IF(Start!$D$10="Avalanche",INDEX(Calc!CE$75:CE$89,Calc!$F$10),INDEX(Calc!CE$50:CE$64,Calc!$D$10)))) | Q33: =IF(R33="","",N(R32)*(1+Start!$E$19/12)-R33) | R33: =IF(OR(OR(Calc!$B$4=0,$B33>IF(Start!$D$10="Avalanche",Calc!$B$3,Calc!$B$2)),Calc!$B$11=0),"",IF(N(R32)<=0.005,"",IF(Start!$D$10="Avalanche",INDEX(Calc!CE$75:CE$89,Calc!$F$11),INDEX(Calc!CE$50:CE$64,Calc!$D$11)))) | S33: =IF(T33="","",N(T32)*(1+Start!$E$20/12)-T33) | T33: =IF(OR(OR(Calc!$B$4=0,$B33>IF(Start!$D$10="Avalanche",Calc!$B$3,Calc!$B$2)),Calc!$B$12=0),"",IF(N(T32)<=0.005,"",IF(Start!$D$10="Avalanche",INDEX(Calc!CE$75:CE$89,Calc!$F$12),INDEX(Calc!CE$50:CE$64,Calc!$D$12)))) | U33: =IF(V33="","",N(V32)*(1+Start!$E$21/12)-V33) | V33: =IF(OR(OR(Calc!$B$4=0,$B33>IF(Start!$D$10="Avalanche",Calc!$B$3,Calc!$B$2)),Calc!$B$13=0),"",IF(N(V32)<=0.005,"",IF(Start!$D$10="Avalanche",INDEX(Calc!CE$75:CE$89,Calc!$F$13),INDEX(Calc!CE$50:CE$64,Calc!$D$13)))) | W33: =IF(X33="","",N(X32)*(1+Start!$E$22/12)-X33) | X33: =IF(OR(OR(Calc!$B$4=0,$B33>IF(Start!$D$10="Avalanche",Calc!$B$3,Calc!$B$2)),Calc!$B$14=0),"",IF(N(X32)<=0.005,"",IF(Start!$D$10="Avalanche",INDEX(Calc!CE$75:CE$89,Calc!$F$14),INDEX(Calc!CE$50:CE$64,Calc!$D$14)))) | Y33: =IF(Z33="","",N(Z32)*(1+Start!$E$23/12)-Z33) | Z33: =IF(OR(OR(Calc!$B$4=0,$B33>IF(Start!$D$10="Avalanche",Calc!$B$3,Calc!$B$2)),Calc!$B$15=0),"",IF(N(Z32)<=0.005,"",IF(Start!$D$10="Avalanche",INDEX(Calc!CE$75:CE$89,Calc!$F$15),INDEX(Calc!CE$50:CE$64,Calc!$D$15)))) | AA33: =IF(AB33="","",N(AB32)*(1+Start!$E$24/12)-AB33) | AB33: =IF(OR(OR(Calc!$B$4=0,$B33>IF(Start!$D$10="Avalanche",Calc!$B$3,Calc!$B$2)),Calc!$B$16=0),"",IF(N(AB32)<=0.005,"",IF(Start!$D$10="Avalanche",INDEX(Calc!CE$75:CE$89,Calc!$F$16),INDEX(Calc!CE$50:CE$64,Calc!$D$16)))) | AC33: =IF(AD33="","",N(AD32)*(1+Start!$E$25/12)-AD33) | AD33: =IF(OR(OR(Calc!$B$4=0,$B33>IF(Start!$D$10="Avalanche",Calc!$B$3,Calc!$B$2)),Calc!$B$17=0),"",IF(N(AD32)<=0.005,"",IF(Start!$D$10="Avalanche",INDEX(Calc!CE$75:CE$89,Calc!$F$17),INDEX(Calc!CE$50:CE$64,Calc!$D$17)))) | AE33: =IF(AF33="","",N(AF32)*(1+Start!$E$26/12)-AF33) | AF33: =IF(OR(OR(Calc!$B$4=0,$B33>IF(Start!$D$10="Avalanche",Calc!$B$3,Calc!$B$2)),Calc!$B$18=0),"",IF(N(AF32)<=0.005,"",IF(Start!$D$10="Avalanche",INDEX(Calc!CE$75:CE$89,Calc!$F$18),INDEX(Calc!CE$50:CE$64,Calc!$D$18)))) | AG33: =IF(AH33="","",N(AH32)*(1+Start!$E$27/12)-AH33) | AH33: =IF(OR(OR(Calc!$B$4=0,$B33>IF(Start!$D$10="Avalanche",Calc!$B$3,Calc!$B$2)),Calc!$B$19=0),"",IF(N(AH32)<=0.005,"",IF(Start!$D$10="Avalanche",INDEX(Calc!CE$75:CE$89,Calc!$F$19),INDEX(Calc!CE$50:CE$64,Calc!$D$19)))) | AI33: =IF(AJ33="","",N(AJ32)*(1+Start!$E$28/12)-AJ33) | AJ33: =IF(OR(OR(Calc!$B$4=0,$B33>IF(Start!$D$10="Avalanche",Calc!$B$3,Calc!$B$2)),Calc!$B$20=0),"",IF(N(AJ32)<=0.005,"",IF(Start!$D$10="Avalanche",INDEX(Calc!CE$75:CE$89,Calc!$F$20),INDEX(Calc!CE$50:CE$64,Calc!$D$20))))
B34: 28 | C34: =IF(Calc!$B$4=0,"",EDATE(Start!$D$11,27)) | D34: =IF(OR(Calc!$B$4=0,$B34>IF(Start!$D$10="Avalanche",Calc!$B$3,Calc!$B$2)),"",SUM(G34,I34,K34,M34,O34,Q34,S34,U34,W34,Y34,AA34,AC34,AE34,AG34,AI34)) | E34: =IF(OR(Calc!$B$4=0,$B34>IF(Start!$D$10="Avalanche",Calc!$B$3,Calc!$B$2)),"",IF(Start!$D$10="Avalanche",Calc!CF$72,Calc!CF$47)) | F34: =IF(Calc!$B$4=0,"",IF($B34>IF(Start!$D$10="Avalanche",Calc!$B$3,Calc!$B$2),NA(),SUM(H34,J34,L34,N34,P34,R34,T34,V34,X34,Z34,AB34,AD34,AF34,AH34,AJ34))) | G34: =IF(H34="","",N(H33)*(1+Start!$E$14/12)-H34) | H34: =IF(OR(OR(Calc!$B$4=0,$B34>IF(Start!$D$10="Avalanche",Calc!$B$3,Calc!$B$2)),Calc!$B$6=0),"",IF(N(H33)<=0.005,"",IF(Start!$D$10="Avalanche",INDEX(Calc!CH$75:CH$89,Calc!$F$6),INDEX(Calc!CH$50:CH$64,Calc!$D$6)))) | I34: =IF(J34="","",N(J33)*(1+Start!$E$15/12)-J34) | J34: =IF(OR(OR(Calc!$B$4=0,$B34>IF(Start!$D$10="Avalanche",Calc!$B$3,Calc!$B$2)),Calc!$B$7=0),"",IF(N(J33)<=0.005,"",IF(Start!$D$10="Avalanche",INDEX(Calc!CH$75:CH$89,Calc!$F$7),INDEX(Calc!CH$50:CH$64,Calc!$D$7)))) | K34: =IF(L34="","",N(L33)*(1+Start!$E$16/12)-L34) | L34: =IF(OR(OR(Calc!$B$4=0,$B34>IF(Start!$D$10="Avalanche",Calc!$B$3,Calc!$B$2)),Calc!$B$8=0),"",IF(N(L33)<=0.005,"",IF(Start!$D$10="Avalanche",INDEX(Calc!CH$75:CH$89,Calc!$F$8),INDEX(Calc!CH$50:CH$64,Calc!$D$8)))) | M34: =IF(N34="","",N(N33)*(1+Start!$E$17/12)-N34) | N34: =IF(OR(OR(Calc!$B$4=0,$B34>IF(Start!$D$10="Avalanche",Calc!$B$3,Calc!$B$2)),Calc!$B$9=0),"",IF(N(N33)<=0.005,"",IF(Start!$D$10="Avalanche",INDEX(Calc!CH$75:CH$89,Calc!$F$9),INDEX(Calc!CH$50:CH$64,Calc!$D$9)))) | O34: =IF(P34="","",N(P33)*(1+Start!$E$18/12)-P34) | P34: =IF(OR(OR(Calc!$B$4=0,$B34>IF(Start!$D$10="Avalanche",Calc!$B$3,Calc!$B$2)),Calc!$B$10=0),"",IF(N(P33)<=0.005,"",IF(Start!$D$10="Avalanche",INDEX(Calc!CH$75:CH$89,Calc!$F$10),INDEX(Calc!CH$50:CH$64,Calc!$D$10)))) | Q34: =IF(R34="","",N(R33)*(1+Start!$E$19/12)-R34) | R34: =IF(OR(OR(Calc!$B$4=0,$B34>IF(Start!$D$10="Avalanche",Calc!$B$3,Calc!$B$2)),Calc!$B$11=0),"",IF(N(R33)<=0.005,"",IF(Start!$D$10="Avalanche",INDEX(Calc!CH$75:CH$89,Calc!$F$11),INDEX(Calc!CH$50:CH$64,Calc!$D$11)))) | S34: =IF(T34="","",N(T33)*(1+Start!$E$20/12)-T34) | T34: =IF(OR(OR(Calc!$B$4=0,$B34>IF(Start!$D$10="Avalanche",Calc!$B$3,Calc!$B$2)),Calc!$B$12=0),"",IF(N(T33)<=0.005,"",IF(Start!$D$10="Avalanche",INDEX(Calc!CH$75:CH$89,Calc!$F$12),INDEX(Calc!CH$50:CH$64,Calc!$D$12)))) | U34: =IF(V34="","",N(V33)*(1+Start!$E$21/12)-V34) | V34: =IF(OR(OR(Calc!$B$4=0,$B34>IF(Start!$D$10="Avalanche",Calc!$B$3,Calc!$B$2)),Calc!$B$13=0),"",IF(N(V33)<=0.005,"",IF(Start!$D$10="Avalanche",INDEX(Calc!CH$75:CH$89,Calc!$F$13),INDEX(Calc!CH$50:CH$64,Calc!$D$13)))) | W34: =IF(X34="","",N(X33)*(1+Start!$E$22/12)-X34) | X34: =IF(OR(OR(Calc!$B$4=0,$B34>IF(Start!$D$10="Avalanche",Calc!$B$3,Calc!$B$2)),Calc!$B$14=0),"",IF(N(X33)<=0.005,"",IF(Start!$D$10="Avalanche",INDEX(Calc!CH$75:CH$89,Calc!$F$14),INDEX(Calc!CH$50:CH$64,Calc!$D$14)))) | Y34: =IF(Z34="","",N(Z33)*(1+Start!$E$23/12)-Z34) | Z34: =IF(OR(OR(Calc!$B$4=0,$B34>IF(Start!$D$10="Avalanche",Calc!$B$3,Calc!$B$2)),Calc!$B$15=0),"",IF(N(Z33)<=0.005,"",IF(Start!$D$10="Avalanche",INDEX(Calc!CH$75:CH$89,Calc!$F$15),INDEX(Calc!CH$50:CH$64,Calc!$D$15)))) | AA34: =IF(AB34="","",N(AB33)*(1+Start!$E$24/12)-AB34) | AB34: =IF(OR(OR(Calc!$B$4=0,$B34>IF(Start!$D$10="Avalanche",Calc!$B$3,Calc!$B$2)),Calc!$B$16=0),"",IF(N(AB33)<=0.005,"",IF(Start!$D$10="Avalanche",INDEX(Calc!CH$75:CH$89,Calc!$F$16),INDEX(Calc!CH$50:CH$64,Calc!$D$16)))) | AC34: =IF(AD34="","",N(AD33)*(1+Start!$E$25/12)-AD34) | AD34: =IF(OR(OR(Calc!$B$4=0,$B34>IF(Start!$D$10="Avalanche",Calc!$B$3,Calc!$B$2)),Calc!$B$17=0),"",IF(N(AD33)<=0.005,"",IF(Start!$D$10="Avalanche",INDEX(Calc!CH$75:CH$89,Calc!$F$17),INDEX(Calc!CH$50:CH$64,Calc!$D$17)))) | AE34: =IF(AF34="","",N(AF33)*(1+Start!$E$26/12)-AF34) | AF34: =IF(OR(OR(Calc!$B$4=0,$B34>IF(Start!$D$10="Avalanche",Calc!$B$3,Calc!$B$2)),Calc!$B$18=0),"",IF(N(AF33)<=0.005,"",IF(Start!$D$10="Avalanche",INDEX(Calc!CH$75:CH$89,Calc!$F$18),INDEX(Calc!CH$50:CH$64,Calc!$D$18)))) | AG34: =IF(AH34="","",N(AH33)*(1+Start!$E$27/12)-AH34) | AH34: =IF(OR(OR(Calc!$B$4=0,$B34>IF(Start!$D$10="Avalanche",Calc!$B$3,Calc!$B$2)),Calc!$B$19=0),"",IF(N(AH33)<=0.005,"",IF(Start!$D$10="Avalanche",INDEX(Calc!CH$75:CH$89,Calc!$F$19),INDEX(Calc!CH$50:CH$64,Calc!$D$19)))) | AI34: =IF(AJ34="","",N(AJ33)*(1+Start!$E$28/12)-AJ34) | AJ34: =IF(OR(OR(Calc!$B$4=0,$B34>IF(Start!$D$10="Avalanche",Calc!$B$3,Calc!$B$2)),Calc!$B$20=0),"",IF(N(AJ33)<=0.005,"",IF(Start!$D$10="Avalanche",INDEX(Calc!CH$75:CH$89,Calc!$F$20),INDEX(Calc!CH$50:CH$64,Calc!$D$20))))
B35: 29 | C35: =IF(Calc!$B$4=0,"",EDATE(Start!$D$11,28)) | D35: =IF(OR(Calc!$B$4=0,$B35>IF(Start!$D$10="Avalanche",Calc!$B$3,Calc!$B$2)),"",SUM(G35,I35,K35,M35,O35,Q35,S35,U35,W35,Y35,AA35,AC35,AE35,AG35,AI35)) | E35: =IF(OR(Calc!$B$4=0,$B35>IF(Start!$D$10="Avalanche",Calc!$B$3,Calc!$B$2)),"",IF(Start!$D$10="Avalanche",Calc!CI$72,Calc!CI$47)) | F35: =IF(Calc!$B$4=0,"",IF($B35>IF(Start!$D$10="Avalanche",Calc!$B$3,Calc!$B$2),NA(),SUM(H35,J35,L35,N35,P35,R35,T35,V35,X35,Z35,AB35,AD35,AF35,AH35,AJ35))) | G35: =IF(H35="","",N(H34)*(1+Start!$E$14/12)-H35) | H35: =IF(OR(OR(Calc!$B$4=0,$B35>IF(Start!$D$10="Avalanche",Calc!$B$3,Calc!$B$2)),Calc!$B$6=0),"",IF(N(H34)<=0.005,"",IF(Start!$D$10="Avalanche",INDEX(Calc!CK$75:CK$89,Calc!$F$6),INDEX(Calc!CK$50:CK$64,Calc!$D$6)))) | I35: =IF(J35="","",N(J34)*(1+Start!$E$15/12)-J35) | J35: =IF(OR(OR(Calc!$B$4=0,$B35>IF(Start!$D$10="Avalanche",Calc!$B$3,Calc!$B$2)),Calc!$B$7=0),"",IF(N(J34)<=0.005,"",IF(Start!$D$10="Avalanche",INDEX(Calc!CK$75:CK$89,Calc!$F$7),INDEX(Calc!CK$50:CK$64,Calc!$D$7)))) | K35: =IF(L35="","",N(L34)*(1+Start!$E$16/12)-L35) | L35: =IF(OR(OR(Calc!$B$4=0,$B35>IF(Start!$D$10="Avalanche",Calc!$B$3,Calc!$B$2)),Calc!$B$8=0),"",IF(N(L34)<=0.005,"",IF(Start!$D$10="Avalanche",INDEX(Calc!CK$75:CK$89,Calc!$F$8),INDEX(Calc!CK$50:CK$64,Calc!$D$8)))) | M35: =IF(N35="","",N(N34)*(1+Start!$E$17/12)-N35) | N35: =IF(OR(OR(Calc!$B$4=0,$B35>IF(Start!$D$10="Avalanche",Calc!$B$3,Calc!$B$2)),Calc!$B$9=0),"",IF(N(N34)<=0.005,"",IF(Start!$D$10="Avalanche",INDEX(Calc!CK$75:CK$89,Calc!$F$9),INDEX(Calc!CK$50:CK$64,Calc!$D$9)))) | O35: =IF(P35="","",N(P34)*(1+Start!$E$18/12)-P35) | P35: =IF(OR(OR(Calc!$B$4=0,$B35>IF(Start!$D$10="Avalanche",Calc!$B$3,Calc!$B$2)),Calc!$B$10=0),"",IF(N(P34)<=0.005,"",IF(Start!$D$10="Avalanche",INDEX(Calc!CK$75:CK$89,Calc!$F$10),INDEX(Calc!CK$50:CK$64,Calc!$D$10)))) | Q35: =IF(R35="","",N(R34)*(1+Start!$E$19/12)-R35) | R35: =IF(OR(OR(Calc!$B$4=0,$B35>IF(Start!$D$10="Avalanche",Calc!$B$3,Calc!$B$2)),Calc!$B$11=0),"",IF(N(R34)<=0.005,"",IF(Start!$D$10="Avalanche",INDEX(Calc!CK$75:CK$89,Calc!$F$11),INDEX(Calc!CK$50:CK$64,Calc!$D$11)))) | S35: =IF(T35="","",N(T34)*(1+Start!$E$20/12)-T35) | T35: =IF(OR(OR(Calc!$B$4=0,$B35>IF(Start!$D$10="Avalanche",Calc!$B$3,Calc!$B$2)),Calc!$B$12=0),"",IF(N(T34)<=0.005,"",IF(Start!$D$10="Avalanche",INDEX(Calc!CK$75:CK$89,Calc!$F$12),INDEX(Calc!CK$50:CK$64,Calc!$D$12)))) | U35: =IF(V35="","",N(V34)*(1+Start!$E$21/12)-V35) | V35: =IF(OR(OR(Calc!$B$4=0,$B35>IF(Start!$D$10="Avalanche",Calc!$B$3,Calc!$B$2)),Calc!$B$13=0),"",IF(N(V34)<=0.005,"",IF(Start!$D$10="Avalanche",INDEX(Calc!CK$75:CK$89,Calc!$F$13),INDEX(Calc!CK$50:CK$64,Calc!$D$13)))) | W35: =IF(X35="","",N(X34)*(1+Start!$E$22/12)-X35) | X35: =IF(OR(OR(Calc!$B$4=0,$B35>IF(Start!$D$10="Avalanche",Calc!$B$3,Calc!$B$2)),Calc!$B$14=0),"",IF(N(X34)<=0.005,"",IF(Start!$D$10="Avalanche",INDEX(Calc!CK$75:CK$89,Calc!$F$14),INDEX(Calc!CK$50:CK$64,Calc!$D$14)))) | Y35: =IF(Z35="","",N(Z34)*(1+Start!$E$23/12)-Z35) | Z35: =IF(OR(OR(Calc!$B$4=0,$B35>IF(Start!$D$10="Avalanche",Calc!$B$3,Calc!$B$2)),Calc!$B$15=0),"",IF(N(Z34)<=0.005,"",IF(Start!$D$10="Avalanche",INDEX(Calc!CK$75:CK$89,Calc!$F$15),INDEX(Calc!CK$50:CK$64,Calc!$D$15)))) | AA35: =IF(AB35="","",N(AB34)*(1+Start!$E$24/12)-AB35) | AB35: =IF(OR(OR(Calc!$B$4=0,$B35>IF(Start!$D$10="Avalanche",Calc!$B$3,Calc!$B$2)),Calc!$B$16=0),"",IF(N(AB34)<=0.005,"",IF(Start!$D$10="Avalanche",INDEX(Calc!CK$75:CK$89,Calc!$F$16),INDEX(Calc!CK$50:CK$64,Calc!$D$16)))) | AC35: =IF(AD35="","",N(AD34)*(1+Start!$E$25/12)-AD35) | AD35: =IF(OR(OR(Calc!$B$4=0,$B35>IF(Start!$D$10="Avalanche",Calc!$B$3,Calc!$B$2)),Calc!$B$17=0),"",IF(N(AD34)<=0.005,"",IF(Start!$D$10="Avalanche",INDEX(Calc!CK$75:CK$89,Calc!$F$17),INDEX(Calc!CK$50:CK$64,Calc!$D$17)))) | AE35: =IF(AF35="","",N(AF34)*(1+Start!$E$26/12)-AF35) | AF35: =IF(OR(OR(Calc!$B$4=0,$B35>IF(Start!$D$10="Avalanche",Calc!$B$3,Calc!$B$2)),Calc!$B$18=0),"",IF(N(AF34)<=0.005,"",IF(Start!$D$10="Avalanche",INDEX(Calc!CK$75:CK$89,Calc!$F$18),INDEX(Calc!CK$50:CK$64,Calc!$D$18)))) | AG35: =IF(AH35="","",N(AH34)*(1+Start!$E$27/12)-AH35) | AH35: =IF(OR(OR(Calc!$B$4=0,$B35>IF(Start!$D$10="Avalanche",Calc!$B$3,Calc!$B$2)),Calc!$B$19=0),"",IF(N(AH34)<=0.005,"",IF(Start!$D$10="Avalanche",INDEX(Calc!CK$75:CK$89,Calc!$F$19),INDEX(Calc!CK$50:CK$64,Calc!$D$19)))) | AI35: =IF(AJ35="","",N(AJ34)*(1+Start!$E$28/12)-AJ35) | AJ35: =IF(OR(OR(Calc!$B$4=0,$B35>IF(Start!$D$10="Avalanche",Calc!$B$3,Calc!$B$2)),Calc!$B$20=0),"",IF(N(AJ34)<=0.005,"",IF(Start!$D$10="Avalanche",INDEX(Calc!CK$75:CK$89,Calc!$F$20),INDEX(Calc!CK$50:CK$64,Calc!$D$20))))
B36: 30 | C36: =IF(Calc!$B$4=0,"",EDATE(Start!$D$11,29)) | D36: =IF(OR(Calc!$B$4=0,$B36>IF(Start!$D$10="Avalanche",Calc!$B$3,Calc!$B$2)),"",SUM(G36,I36,K36,M36,O36,Q36,S36,U36,W36,Y36,AA36,AC36,AE36,AG36,AI36)) | E36: =IF(OR(Calc!$B$4=0,$B36>IF(Start!$D$10="Avalanche",Calc!$B$3,Calc!$B$2)),"",IF(Start!$D$10="Avalanche",Calc!CL$72,Calc!CL$47)) | F36: =IF(Calc!$B$4=0,"",IF($B36>IF(Start!$D$10="Avalanche",Calc!$B$3,Calc!$B$2),NA(),SUM(H36,J36,L36,N36,P36,R36,T36,V36,X36,Z36,AB36,AD36,AF36,AH36,AJ36))) | G36: =IF(H36="","",N(H35)*(1+Start!$E$14/12)-H36) | H36: =IF(OR(OR(Calc!$B$4=0,$B36>IF(Start!$D$10="Avalanche",Calc!$B$3,Calc!$B$2)),Calc!$B$6=0),"",IF(N(H35)<=0.005,"",IF(Start!$D$10="Avalanche",INDEX(Calc!CN$75:CN$89,Calc!$F$6),INDEX(Calc!CN$50:CN$64,Calc!$D$6)))) | I36: =IF(J36="","",N(J35)*(1+Start!$E$15/12)-J36) | J36: =IF(OR(OR(Calc!$B$4=0,$B36>IF(Start!$D$10="Avalanche",Calc!$B$3,Calc!$B$2)),Calc!$B$7=0),"",IF(N(J35)<=0.005,"",IF(Start!$D$10="Avalanche",INDEX(Calc!CN$75:CN$89,Calc!$F$7),INDEX(Calc!CN$50:CN$64,Calc!$D$7)))) | K36: =IF(L36="","",N(L35)*(1+Start!$E$16/12)-L36) | L36: =IF(OR(OR(Calc!$B$4=0,$B36>IF(Start!$D$10="Avalanche",Calc!$B$3,Calc!$B$2)),Calc!$B$8=0),"",IF(N(L35)<=0.005,"",IF(Start!$D$10="Avalanche",INDEX(Calc!CN$75:CN$89,Calc!$F$8),INDEX(Calc!CN$50:CN$64,Calc!$D$8)))) | M36: =IF(N36="","",N(N35)*(1+Start!$E$17/12)-N36) | N36: =IF(OR(OR(Calc!$B$4=0,$B36>IF(Start!$D$10="Avalanche",Calc!$B$3,Calc!$B$2)),Calc!$B$9=0),"",IF(N(N35)<=0.005,"",IF(Start!$D$10="Avalanche",INDEX(Calc!CN$75:CN$89,Calc!$F$9),INDEX(Calc!CN$50:CN$64,Calc!$D$9)))) | O36: =IF(P36="","",N(P35)*(1+Start!$E$18/12)-P36) | P36: =IF(OR(OR(Calc!$B$4=0,$B36>IF(Start!$D$10="Avalanche",Calc!$B$3,Calc!$B$2)),Calc!$B$10=0),"",IF(N(P35)<=0.005,"",IF(Start!$D$10="Avalanche",INDEX(Calc!CN$75:CN$89,Calc!$F$10),INDEX(Calc!CN$50:CN$64,Calc!$D$10)))) | Q36: =IF(R36="","",N(R35)*(1+Start!$E$19/12)-R36) | R36: =IF(OR(OR(Calc!$B$4=0,$B36>IF(Start!$D$10="Avalanche",Calc!$B$3,Calc!$B$2)),Calc!$B$11=0),"",IF(N(R35)<=0.005,"",IF(Start!$D$10="Avalanche",INDEX(Calc!CN$75:CN$89,Calc!$F$11),INDEX(Calc!CN$50:CN$64,Calc!$D$11)))) | S36: =IF(T36="","",N(T35)*(1+Start!$E$20/12)-T36) | T36: =IF(OR(OR(Calc!$B$4=0,$B36>IF(Start!$D$10="Avalanche",Calc!$B$3,Calc!$B$2)),Calc!$B$12=0),"",IF(N(T35)<=0.005,"",IF(Start!$D$10="Avalanche",INDEX(Calc!CN$75:CN$89,Calc!$F$12),INDEX(Calc!CN$50:CN$64,Calc!$D$12)))) | U36: =IF(V36="","",N(V35)*(1+Start!$E$21/12)-V36) | V36: =IF(OR(OR(Calc!$B$4=0,$B36>IF(Start!$D$10="Avalanche",Calc!$B$3,Calc!$B$2)),Calc!$B$13=0),"",IF(N(V35)<=0.005,"",IF(Start!$D$10="Avalanche",INDEX(Calc!CN$75:CN$89,Calc!$F$13),INDEX(Calc!CN$50:CN$64,Calc!$D$13)))) | W36: =IF(X36="","",N(X35)*(1+Start!$E$22/12)-X36) | X36: =IF(OR(OR(Calc!$B$4=0,$B36>IF(Start!$D$10="Avalanche",Calc!$B$3,Calc!$B$2)),Calc!$B$14=0),"",IF(N(X35)<=0.005,"",IF(Start!$D$10="Avalanche",INDEX(Calc!CN$75:CN$89,Calc!$F$14),INDEX(Calc!CN$50:CN$64,Calc!$D$14)))) | Y36: =IF(Z36="","",N(Z35)*(1+Start!$E$23/12)-Z36) | Z36: =IF(OR(OR(Calc!$B$4=0,$B36>IF(Start!$D$10="Avalanche",Calc!$B$3,Calc!$B$2)),Calc!$B$15=0),"",IF(N(Z35)<=0.005,"",IF(Start!$D$10="Avalanche",INDEX(Calc!CN$75:CN$89,Calc!$F$15),INDEX(Calc!CN$50:CN$64,Calc!$D$15)))) | AA36: =IF(AB36="","",N(AB35)*(1+Start!$E$24/12)-AB36) | AB36: =IF(OR(OR(Calc!$B$4=0,$B36>IF(Start!$D$10="Avalanche",Calc!$B$3,Calc!$B$2)),Calc!$B$16=0),"",IF(N(AB35)<=0.005,"",IF(Start!$D$10="Avalanche",INDEX(Calc!CN$75:CN$89,Calc!$F$16),INDEX(Calc!CN$50:CN$64,Calc!$D$16)))) | AC36: =IF(AD36="","",N(AD35)*(1+Start!$E$25/12)-AD36) | AD36: =IF(OR(OR(Calc!$B$4=0,$B36>IF(Start!$D$10="Avalanche",Calc!$B$3,Calc!$B$2)),Calc!$B$17=0),"",IF(N(AD35)<=0.005,"",IF(Start!$D$10="Avalanche",INDEX(Calc!CN$75:CN$89,Calc!$F$17),INDEX(Calc!CN$50:CN$64,Calc!$D$17)))) | AE36: =IF(AF36="","",N(AF35)*(1+Start!$E$26/12)-AF36) | AF36: =IF(OR(OR(Calc!$B$4=0,$B36>IF(Start!$D$10="Avalanche",Calc!$B$3,Calc!$B$2)),Calc!$B$18=0),"",IF(N(AF35)<=0.005,"",IF(Start!$D$10="Avalanche",INDEX(Calc!CN$75:CN$89,Calc!$F$18),INDEX(Calc!CN$50:CN$64,Calc!$D$18)))) | AG36: =IF(AH36="","",N(AH35)*(1+Start!$E$27/12)-AH36) | AH36: =IF(OR(OR(Calc!$B$4=0,$B36>IF(Start!$D$10="Avalanche",Calc!$B$3,Calc!$B$2)),Calc!$B$19=0),"",IF(N(AH35)<=0.005,"",IF(Start!$D$10="Avalanche",INDEX(Calc!CN$75:CN$89,Calc!$F$19),INDEX(Calc!CN$50:CN$64,Calc!$D$19)))) | AI36: =IF(AJ36="","",N(AJ35)*(1+Start!$E$28/12)-AJ36) | AJ36: =IF(OR(OR(Calc!$B$4=0,$B36>IF(Start!$D$10="Avalanche",Calc!$B$3,Calc!$B$2)),Calc!$B$20=0),"",IF(N(AJ35)<=0.005,"",IF(Start!$D$10="Avalanche",INDEX(Calc!CN$75:CN$89,Calc!$F$20),INDEX(Calc!CN$50:CN$64,Calc!$D$20))))
B37: 31 | C37: =IF(Calc!$B$4=0,"",EDATE(Start!$D$11,30)) | D37: =IF(OR(Calc!$B$4=0,$B37>IF(Start!$D$10="Avalanche",Calc!$B$3,Calc!$B$2)),"",SUM(G37,I37,K37,M37,O37,Q37,S37,U37,W37,Y37,AA37,AC37,AE37,AG37,AI37)) | E37: =IF(OR(Calc!$B$4=0,$B37>IF(Start!$D$10="Avalanche",Calc!$B$3,Calc!$B$2)),"",IF(Start!$D$10="Avalanche",Calc!CO$72,Calc!CO$47)) | F37: =IF(Calc!$B$4=0,"",IF($B37>IF(Start!$D$10="Avalanche",Calc!$B$3,Calc!$B$2),NA(),SUM(H37,J37,L37,N37,P37,R37,T37,V37,X37,Z37,AB37,AD37,AF37,AH37,AJ37))) | G37: =IF(H37="","",N(H36)*(1+Start!$E$14/12)-H37) | H37: =IF(OR(OR(Calc!$B$4=0,$B37>IF(Start!$D$10="Avalanche",Calc!$B$3,Calc!$B$2)),Calc!$B$6=0),"",IF(N(H36)<=0.005,"",IF(Start!$D$10="Avalanche",INDEX(Calc!CQ$75:CQ$89,Calc!$F$6),INDEX(Calc!CQ$50:CQ$64,Calc!$D$6)))) | I37: =IF(J37="","",N(J36)*(1+Start!$E$15/12)-J37) | J37: =IF(OR(OR(Calc!$B$4=0,$B37>IF(Start!$D$10="Avalanche",Calc!$B$3,Calc!$B$2)),Calc!$B$7=0),"",IF(N(J36)<=0.005,"",IF(Start!$D$10="Avalanche",INDEX(Calc!CQ$75:CQ$89,Calc!$F$7),INDEX(Calc!CQ$50:CQ$64,Calc!$D$7)))) | K37: =IF(L37="","",N(L36)*(1+Start!$E$16/12)-L37) | L37: =IF(OR(OR(Calc!$B$4=0,$B37>IF(Start!$D$10="Avalanche",Calc!$B$3,Calc!$B$2)),Calc!$B$8=0),"",IF(N(L36)<=0.005,"",IF(Start!$D$10="Avalanche",INDEX(Calc!CQ$75:CQ$89,Calc!$F$8),INDEX(Calc!CQ$50:CQ$64,Calc!$D$8)))) | M37: =IF(N37="","",N(N36)*(1+Start!$E$17/12)-N37) | N37: =IF(OR(OR(Calc!$B$4=0,$B37>IF(Start!$D$10="Avalanche",Calc!$B$3,Calc!$B$2)),Calc!$B$9=0),"",IF(N(N36)<=0.005,"",IF(Start!$D$10="Avalanche",INDEX(Calc!CQ$75:CQ$89,Calc!$F$9),INDEX(Calc!CQ$50:CQ$64,Calc!$D$9)))) | O37: =IF(P37="","",N(P36)*(1+Start!$E$18/12)-P37) | P37: =IF(OR(OR(Calc!$B$4=0,$B37>IF(Start!$D$10="Avalanche",Calc!$B$3,Calc!$B$2)),Calc!$B$10=0),"",IF(N(P36)<=0.005,"",IF(Start!$D$10="Avalanche",INDEX(Calc!CQ$75:CQ$89,Calc!$F$10),INDEX(Calc!CQ$50:CQ$64,Calc!$D$10)))) | Q37: =IF(R37="","",N(R36)*(1+Start!$E$19/12)-R37) | R37: =IF(OR(OR(Calc!$B$4=0,$B37>IF(Start!$D$10="Avalanche",Calc!$B$3,Calc!$B$2)),Calc!$B$11=0),"",IF(N(R36)<=0.005,"",IF(Start!$D$10="Avalanche",INDEX(Calc!CQ$75:CQ$89,Calc!$F$11),INDEX(Calc!CQ$50:CQ$64,Calc!$D$11)))) | S37: =IF(T37="","",N(T36)*(1+Start!$E$20/12)-T37) | T37: =IF(OR(OR(Calc!$B$4=0,$B37>IF(Start!$D$10="Avalanche",Calc!$B$3,Calc!$B$2)),Calc!$B$12=0),"",IF(N(T36)<=0.005,"",IF(Start!$D$10="Avalanche",INDEX(Calc!CQ$75:CQ$89,Calc!$F$12),INDEX(Calc!CQ$50:CQ$64,Calc!$D$12)))) | U37: =IF(V37="","",N(V36)*(1+Start!$E$21/12)-V37) | V37: =IF(OR(OR(Calc!$B$4=0,$B37>IF(Start!$D$10="Avalanche",Calc!$B$3,Calc!$B$2)),Calc!$B$13=0),"",IF(N(V36)<=0.005,"",IF(Start!$D$10="Avalanche",INDEX(Calc!CQ$75:CQ$89,Calc!$F$13),INDEX(Calc!CQ$50:CQ$64,Calc!$D$13)))) | W37: =IF(X37="","",N(X36)*(1+Start!$E$22/12)-X37) | X37: =IF(OR(OR(Calc!$B$4=0,$B37>IF(Start!$D$10="Avalanche",Calc!$B$3,Calc!$B$2)),Calc!$B$14=0),"",IF(N(X36)<=0.005,"",IF(Start!$D$10="Avalanche",INDEX(Calc!CQ$75:CQ$89,Calc!$F$14),INDEX(Calc!CQ$50:CQ$64,Calc!$D$14)))) | Y37: =IF(Z37="","",N(Z36)*(1+Start!$E$23/12)-Z37) | Z37: =IF(OR(OR(Calc!$B$4=0,$B37>IF(Start!$D$10="Avalanche",Calc!$B$3,Calc!$B$2)),Calc!$B$15=0),"",IF(N(Z36)<=0.005,"",IF(Start!$D$10="Avalanche",INDEX(Calc!CQ$75:CQ$89,Calc!$F$15),INDEX(Calc!CQ$50:CQ$64,Calc!$D$15)))) | AA37: =IF(AB37="","",N(AB36)*(1+Start!$E$24/12)-AB37) | AB37: =IF(OR(OR(Calc!$B$4=0,$B37>IF(Start!$D$10="Avalanche",Calc!$B$3,Calc!$B$2)),Calc!$B$16=0),"",IF(N(AB36)<=0.005,"",IF(Start!$D$10="Avalanche",INDEX(Calc!CQ$75:CQ$89,Calc!$F$16),INDEX(Calc!CQ$50:CQ$64,Calc!$D$16)))) | AC37: =IF(AD37="","",N(AD36)*(1+Start!$E$25/12)-AD37) | AD37: =IF(OR(OR(Calc!$B$4=0,$B37>IF(Start!$D$10="Avalanche",Calc!$B$3,Calc!$B$2)),Calc!$B$17=0),"",IF(N(AD36)<=0.005,"",IF(Start!$D$10="Avalanche",INDEX(Calc!CQ$75:CQ$89,Calc!$F$17),INDEX(Calc!CQ$50:CQ$64,Calc!$D$17)))) | AE37: =IF(AF37="","",N(AF36)*(1+Start!$E$26/12)-AF37) | AF37: =IF(OR(OR(Calc!$B$4=0,$B37>IF(Start!$D$10="Avalanche",Calc!$B$3,Calc!$B$2)),Calc!$B$18=0),"",IF(N(AF36)<=0.005,"",IF(Start!$D$10="Avalanche",INDEX(Calc!CQ$75:CQ$89,Calc!$F$18),INDEX(Calc!CQ$50:CQ$64,Calc!$D$18)))) | AG37: =IF(AH37="","",N(AH36)*(1+Start!$E$27/12)-AH37) | AH37: =IF(OR(OR(Calc!$B$4=0,$B37>IF(Start!$D$10="Avalanche",Calc!$B$3,Calc!$B$2)),Calc!$B$19=0),"",IF(N(AH36)<=0.005,"",IF(Start!$D$10="Avalanche",INDEX(Calc!CQ$75:CQ$89,Calc!$F$19),INDEX(Calc!CQ$50:CQ$64,Calc!$D$19)))) | AI37: =IF(AJ37="","",N(AJ36)*(1+Start!$E$28/12)-AJ37) | AJ37: =IF(OR(OR(Calc!$B$4=0,$B37>IF(Start!$D$10="Avalanche",Calc!$B$3,Calc!$B$2)),Calc!$B$20=0),"",IF(N(AJ36)<=0.005,"",IF(Start!$D$10="Avalanche",INDEX(Calc!CQ$75:CQ$89,Calc!$F$20),INDEX(Calc!CQ$50:CQ$64,Calc!$D$20))))
B38: 32 | C38: =IF(Calc!$B$4=0,"",EDATE(Start!$D$11,31)) | D38: =IF(OR(Calc!$B$4=0,$B38>IF(Start!$D$10="Avalanche",Calc!$B$3,Calc!$B$2)),"",SUM(G38,I38,K38,M38,O38,Q38,S38,U38,W38,Y38,AA38,AC38,AE38,AG38,AI38)) | E38: =IF(OR(Calc!$B$4=0,$B38>IF(Start!$D$10="Avalanche",Calc!$B$3,Calc!$B$2)),"",IF(Start!$D$10="Avalanche",Calc!CR$72,Calc!CR$47)) | F38: =IF(Calc!$B$4=0,"",IF($B38>IF(Start!$D$10="Avalanche",Calc!$B$3,Calc!$B$2),NA(),SUM(H38,J38,L38,N38,P38,R38,T38,V38,X38,Z38,AB38,AD38,AF38,AH38,AJ38))) | G38: =IF(H38="","",N(H37)*(1+Start!$E$14/12)-H38) | H38: =IF(OR(OR(Calc!$B$4=0,$B38>IF(Start!$D$10="Avalanche",Calc!$B$3,Calc!$B$2)),Calc!$B$6=0),"",IF(N(H37)<=0.005,"",IF(Start!$D$10="Avalanche",INDEX(Calc!CT$75:CT$89,Calc!$F$6),INDEX(Calc!CT$50:CT$64,Calc!$D$6)))) | I38: =IF(J38="","",N(J37)*(1+Start!$E$15/12)-J38) | J38: =IF(OR(OR(Calc!$B$4=0,$B38>IF(Start!$D$10="Avalanche",Calc!$B$3,Calc!$B$2)),Calc!$B$7=0),"",IF(N(J37)<=0.005,"",IF(Start!$D$10="Avalanche",INDEX(Calc!CT$75:CT$89,Calc!$F$7),INDEX(Calc!CT$50:CT$64,Calc!$D$7)))) | K38: =IF(L38="","",N(L37)*(1+Start!$E$16/12)-L38) | L38: =IF(OR(OR(Calc!$B$4=0,$B38>IF(Start!$D$10="Avalanche",Calc!$B$3,Calc!$B$2)),Calc!$B$8=0),"",IF(N(L37)<=0.005,"",IF(Start!$D$10="Avalanche",INDEX(Calc!CT$75:CT$89,Calc!$F$8),INDEX(Calc!CT$50:CT$64,Calc!$D$8)))) | M38: =IF(N38="","",N(N37)*(1+Start!$E$17/12)-N38) | N38: =IF(OR(OR(Calc!$B$4=0,$B38>IF(Start!$D$10="Avalanche",Calc!$B$3,Calc!$B$2)),Calc!$B$9=0),"",IF(N(N37)<=0.005,"",IF(Start!$D$10="Avalanche",INDEX(Calc!CT$75:CT$89,Calc!$F$9),INDEX(Calc!CT$50:CT$64,Calc!$D$9)))) | O38: =IF(P38="","",N(P37)*(1+Start!$E$18/12)-P38) | P38: =IF(OR(OR(Calc!$B$4=0,$B38>IF(Start!$D$10="Avalanche",Calc!$B$3,Calc!$B$2)),Calc!$B$10=0),"",IF(N(P37)<=0.005,"",IF(Start!$D$10="Avalanche",INDEX(Calc!CT$75:CT$89,Calc!$F$10),INDEX(Calc!CT$50:CT$64,Calc!$D$10)))) | Q38: =IF(R38="","",N(R37)*(1+Start!$E$19/12)-R38) | R38: =IF(OR(OR(Calc!$B$4=0,$B38>IF(Start!$D$10="Avalanche",Calc!$B$3,Calc!$B$2)),Calc!$B$11=0),"",IF(N(R37)<=0.005,"",IF(Start!$D$10="Avalanche",INDEX(Calc!CT$75:CT$89,Calc!$F$11),INDEX(Calc!CT$50:CT$64,Calc!$D$11)))) | S38: =IF(T38="","",N(T37)*(1+Start!$E$20/12)-T38) | T38: =IF(OR(OR(Calc!$B$4=0,$B38>IF(Start!$D$10="Avalanche",Calc!$B$3,Calc!$B$2)),Calc!$B$12=0),"",IF(N(T37)<=0.005,"",IF(Start!$D$10="Avalanche",INDEX(Calc!CT$75:CT$89,Calc!$F$12),INDEX(Calc!CT$50:CT$64,Calc!$D$12)))) | U38: =IF(V38="","",N(V37)*(1+Start!$E$21/12)-V38) | V38: =IF(OR(OR(Calc!$B$4=0,$B38>IF(Start!$D$10="Avalanche",Calc!$B$3,Calc!$B$2)),Calc!$B$13=0),"",IF(N(V37)<=0.005,"",IF(Start!$D$10="Avalanche",INDEX(Calc!CT$75:CT$89,Calc!$F$13),INDEX(Calc!CT$50:CT$64,Calc!$D$13)))) | W38: =IF(X38="","",N(X37)*(1+Start!$E$22/12)-X38) | X38: =IF(OR(OR(Calc!$B$4=0,$B38>IF(Start!$D$10="Avalanche",Calc!$B$3,Calc!$B$2)),Calc!$B$14=0),"",IF(N(X37)<=0.005,"",IF(Start!$D$10="Avalanche",INDEX(Calc!CT$75:CT$89,Calc!$F$14),INDEX(Calc!CT$50:CT$64,Calc!$D$14)))) | Y38: =IF(Z38="","",N(Z37)*(1+Start!$E$23/12)-Z38) | Z38: =IF(OR(OR(Calc!$B$4=0,$B38>IF(Start!$D$10="Avalanche",Calc!$B$3,Calc!$B$2)),Calc!$B$15=0),"",IF(N(Z37)<=0.005,"",IF(Start!$D$10="Avalanche",INDEX(Calc!CT$75:CT$89,Calc!$F$15),INDEX(Calc!CT$50:CT$64,Calc!$D$15)))) | AA38: =IF(AB38="","",N(AB37)*(1+Start!$E$24/12)-AB38) | AB38: =IF(OR(OR(Calc!$B$4=0,$B38>IF(Start!$D$10="Avalanche",Calc!$B$3,Calc!$B$2)),Calc!$B$16=0),"",IF(N(AB37)<=0.005,"",IF(Start!$D$10="Avalanche",INDEX(Calc!CT$75:CT$89,Calc!$F$16),INDEX(Calc!CT$50:CT$64,Calc!$D$16)))) | AC38: =IF(AD38="","",N(AD37)*(1+Start!$E$25/12)-AD38) | AD38: =IF(OR(OR(Calc!$B$4=0,$B38>IF(Start!$D$10="Avalanche",Calc!$B$3,Calc!$B$2)),Calc!$B$17=0),"",IF(N(AD37)<=0.005,"",IF(Start!$D$10="Avalanche",INDEX(Calc!CT$75:CT$89,Calc!$F$17),INDEX(Calc!CT$50:CT$64,Calc!$D$17)))) | AE38: =IF(AF38="","",N(AF37)*(1+Start!$E$26/12)-AF38) | AF38: =IF(OR(OR(Calc!$B$4=0,$B38>IF(Start!$D$10="Avalanche",Calc!$B$3,Calc!$B$2)),Calc!$B$18=0),"",IF(N(AF37)<=0.005,"",IF(Start!$D$10="Avalanche",INDEX(Calc!CT$75:CT$89,Calc!$F$18),INDEX(Calc!CT$50:CT$64,Calc!$D$18)))) | AG38: =IF(AH38="","",N(AH37)*(1+Start!$E$27/12)-AH38) | AH38: =IF(OR(OR(Calc!$B$4=0,$B38>IF(Start!$D$10="Avalanche",Calc!$B$3,Calc!$B$2)),Calc!$B$19=0),"",IF(N(AH37)<=0.005,"",IF(Start!$D$10="Avalanche",INDEX(Calc!CT$75:CT$89,Calc!$F$19),INDEX(Calc!CT$50:CT$64,Calc!$D$19)))) | AI38: =IF(AJ38="","",N(AJ37)*(1+Start!$E$28/12)-AJ38) | AJ38: =IF(OR(OR(Calc!$B$4=0,$B38>IF(Start!$D$10="Avalanche",Calc!$B$3,Calc!$B$2)),Calc!$B$20=0),"",IF(N(AJ37)<=0.005,"",IF(Start!$D$10="Avalanche",INDEX(Calc!CT$75:CT$89,Calc!$F$20),INDEX(Calc!CT$50:CT$64,Calc!$D$20))))
B39: 33 | C39: =IF(Calc!$B$4=0,"",EDATE(Start!$D$11,32)) | D39: =IF(OR(Calc!$B$4=0,$B39>IF(Start!$D$10="Avalanche",Calc!$B$3,Calc!$B$2)),"",SUM(G39,I39,K39,M39,O39,Q39,S39,U39,W39,Y39,AA39,AC39,AE39,AG39,AI39)) | E39: =IF(OR(Calc!$B$4=0,$B39>IF(Start!$D$10="Avalanche",Calc!$B$3,Calc!$B$2)),"",IF(Start!$D$10="Avalanche",Calc!CU$72,Calc!CU$47)) | F39: =IF(Calc!$B$4=0,"",IF($B39>IF(Start!$D$10="Avalanche",Calc!$B$3,Calc!$B$2),NA(),SUM(H39,J39,L39,N39,P39,R39,T39,V39,X39,Z39,AB39,AD39,AF39,AH39,AJ39))) | G39: =IF(H39="","",N(H38)*(1+Start!$E$14/12)-H39) | H39: =IF(OR(OR(Calc!$B$4=0,$B39>IF(Start!$D$10="Avalanche",Calc!$B$3,Calc!$B$2)),Calc!$B$6=0),"",IF(N(H38)<=0.005,"",IF(Start!$D$10="Avalanche",INDEX(Calc!CW$75:CW$89,Calc!$F$6),INDEX(Calc!CW$50:CW$64,Calc!$D$6)))) | I39: =IF(J39="","",N(J38)*(1+Start!$E$15/12)-J39) | J39: =IF(OR(OR(Calc!$B$4=0,$B39>IF(Start!$D$10="Avalanche",Calc!$B$3,Calc!$B$2)),Calc!$B$7=0),"",IF(N(J38)<=0.005,"",IF(Start!$D$10="Avalanche",INDEX(Calc!CW$75:CW$89,Calc!$F$7),INDEX(Calc!CW$50:CW$64,Calc!$D$7)))) | K39: =IF(L39="","",N(L38)*(1+Start!$E$16/12)-L39) | L39: =IF(OR(OR(Calc!$B$4=0,$B39>IF(Start!$D$10="Avalanche",Calc!$B$3,Calc!$B$2)),Calc!$B$8=0),"",IF(N(L38)<=0.005,"",IF(Start!$D$10="Avalanche",INDEX(Calc!CW$75:CW$89,Calc!$F$8),INDEX(Calc!CW$50:CW$64,Calc!$D$8)))) | M39: =IF(N39="","",N(N38)*(1+Start!$E$17/12)-N39) | N39: =IF(OR(OR(Calc!$B$4=0,$B39>IF(Start!$D$10="Avalanche",Calc!$B$3,Calc!$B$2)),Calc!$B$9=0),"",IF(N(N38)<=0.005,"",IF(Start!$D$10="Avalanche",INDEX(Calc!CW$75:CW$89,Calc!$F$9),INDEX(Calc!CW$50:CW$64,Calc!$D$9)))) | O39: =IF(P39="","",N(P38)*(1+Start!$E$18/12)-P39) | P39: =IF(OR(OR(Calc!$B$4=0,$B39>IF(Start!$D$10="Avalanche",Calc!$B$3,Calc!$B$2)),Calc!$B$10=0),"",IF(N(P38)<=0.005,"",IF(Start!$D$10="Avalanche",INDEX(Calc!CW$75:CW$89,Calc!$F$10),INDEX(Calc!CW$50:CW$64,Calc!$D$10)))) | Q39: =IF(R39="","",N(R38)*(1+Start!$E$19/12)-R39) | R39: =IF(OR(OR(Calc!$B$4=0,$B39>IF(Start!$D$10="Avalanche",Calc!$B$3,Calc!$B$2)),Calc!$B$11=0),"",IF(N(R38)<=0.005,"",IF(Start!$D$10="Avalanche",INDEX(Calc!CW$75:CW$89,Calc!$F$11),INDEX(Calc!CW$50:CW$64,Calc!$D$11)))) | S39: =IF(T39="","",N(T38)*(1+Start!$E$20/12)-T39) | T39: =IF(OR(OR(Calc!$B$4=0,$B39>IF(Start!$D$10="Avalanche",Calc!$B$3,Calc!$B$2)),Calc!$B$12=0),"",IF(N(T38)<=0.005,"",IF(Start!$D$10="Avalanche",INDEX(Calc!CW$75:CW$89,Calc!$F$12),INDEX(Calc!CW$50:CW$64,Calc!$D$12)))) | U39: =IF(V39="","",N(V38)*(1+Start!$E$21/12)-V39) | V39: =IF(OR(OR(Calc!$B$4=0,$B39>IF(Start!$D$10="Avalanche",Calc!$B$3,Calc!$B$2)),Calc!$B$13=0),"",IF(N(V38)<=0.005,"",IF(Start!$D$10="Avalanche",INDEX(Calc!CW$75:CW$89,Calc!$F$13),INDEX(Calc!CW$50:CW$64,Calc!$D$13)))) | W39: =IF(X39="","",N(X38)*(1+Start!$E$22/12)-X39) | X39: =IF(OR(OR(Calc!$B$4=0,$B39>IF(Start!$D$10="Avalanche",Calc!$B$3,Calc!$B$2)),Calc!$B$14=0),"",IF(N(X38)<=0.005,"",IF(Start!$D$10="Avalanche",INDEX(Calc!CW$75:CW$89,Calc!$F$14),INDEX(Calc!CW$50:CW$64,Calc!$D$14)))) | Y39: =IF(Z39="","",N(Z38)*(1+Start!$E$23/12)-Z39) | Z39: =IF(OR(OR(Calc!$B$4=0,$B39>IF(Start!$D$10="Avalanche",Calc!$B$3,Calc!$B$2)),Calc!$B$15=0),"",IF(N(Z38)<=0.005,"",IF(Start!$D$10="Avalanche",INDEX(Calc!CW$75:CW$89,Calc!$F$15),INDEX(Calc!CW$50:CW$64,Calc!$D$15)))) | AA39: =IF(AB39="","",N(AB38)*(1+Start!$E$24/12)-AB39) | AB39: =IF(OR(OR(Calc!$B$4=0,$B39>IF(Start!$D$10="Avalanche",Calc!$B$3,Calc!$B$2)),Calc!$B$16=0),"",IF(N(AB38)<=0.005,"",IF(Start!$D$10="Avalanche",INDEX(Calc!CW$75:CW$89,Calc!$F$16),INDEX(Calc!CW$50:CW$64,Calc!$D$16)))) | AC39: =IF(AD39="","",N(AD38)*(1+Start!$E$25/12)-AD39) | AD39: =IF(OR(OR(Calc!$B$4=0,$B39>IF(Start!$D$10="Avalanche",Calc!$B$3,Calc!$B$2)),Calc!$B$17=0),"",IF(N(AD38)<=0.005,"",IF(Start!$D$10="Avalanche",INDEX(Calc!CW$75:CW$89,Calc!$F$17),INDEX(Calc!CW$50:CW$64,Calc!$D$17)))) | AE39: =IF(AF39="","",N(AF38)*(1+Start!$E$26/12)-AF39) | AF39: =IF(OR(OR(Calc!$B$4=0,$B39>IF(Start!$D$10="Avalanche",Calc!$B$3,Calc!$B$2)),Calc!$B$18=0),"",IF(N(AF38)<=0.005,"",IF(Start!$D$10="Avalanche",INDEX(Calc!CW$75:CW$89,Calc!$F$18),INDEX(Calc!CW$50:CW$64,Calc!$D$18)))) | AG39: =IF(AH39="","",N(AH38)*(1+Start!$E$27/12)-AH39) | AH39: =IF(OR(OR(Calc!$B$4=0,$B39>IF(Start!$D$10="Avalanche",Calc!$B$3,Calc!$B$2)),Calc!$B$19=0),"",IF(N(AH38)<=0.005,"",IF(Start!$D$10="Avalanche",INDEX(Calc!CW$75:CW$89,Calc!$F$19),INDEX(Calc!CW$50:CW$64,Calc!$D$19)))) | AI39: =IF(AJ39="","",N(AJ38)*(1+Start!$E$28/12)-AJ39) | AJ39: =IF(OR(OR(Calc!$B$4=0,$B39>IF(Start!$D$10="Avalanche",Calc!$B$3,Calc!$B$2)),Calc!$B$20=0),"",IF(N(AJ38)<=0.005,"",IF(Start!$D$10="Avalanche",INDEX(Calc!CW$75:CW$89,Calc!$F$20),INDEX(Calc!CW$50:CW$64,Calc!$D$20))))
B40: 34 | C40: =IF(Calc!$B$4=0,"",EDATE(Start!$D$11,33)) | D40: =IF(OR(Calc!$B$4=0,$B40>IF(Start!$D$10="Avalanche",Calc!$B$3,Calc!$B$2)),"",SUM(G40,I40,K40,M40,O40,Q40,S40,U40,W40,Y40,AA40,AC40,AE40,AG40,AI40)) | E40: =IF(OR(Calc!$B$4=0,$B40>IF(Start!$D$10="Avalanche",Calc!$B$3,Calc!$B$2)),"",IF(Start!$D$10="Avalanche",Calc!CX$72,Calc!CX$47)) | F40: =IF(Calc!$B$4=0,"",IF($B40>IF(Start!$D$10="Avalanche",Calc!$B$3,Calc!$B$2),NA(),SUM(H40,J40,L40,N40,P40,R40,T40,V40,X40,Z40,AB40,AD40,AF40,AH40,AJ40))) | G40: =IF(H40="","",N(H39)*(1+Start!$E$14/12)-H40) | H40: =IF(OR(OR(Calc!$B$4=0,$B40>IF(Start!$D$10="Avalanche",Calc!$B$3,Calc!$B$2)),Calc!$B$6=0),"",IF(N(H39)<=0.005,"",IF(Start!$D$10="Avalanche",INDEX(Calc!CZ$75:CZ$89,Calc!$F$6),INDEX(Calc!CZ$50:CZ$64,Calc!$D$6)))) | I40: =IF(J40="","",N(J39)*(1+Start!$E$15/12)-J40) | J40: =IF(OR(OR(Calc!$B$4=0,$B40>IF(Start!$D$10="Avalanche",Calc!$B$3,Calc!$B$2)),Calc!$B$7=0),"",IF(N(J39)<=0.005,"",IF(Start!$D$10="Avalanche",INDEX(Calc!CZ$75:CZ$89,Calc!$F$7),INDEX(Calc!CZ$50:CZ$64,Calc!$D$7)))) | K40: =IF(L40="","",N(L39)*(1+Start!$E$16/12)-L40) | L40: =IF(OR(OR(Calc!$B$4=0,$B40>IF(Start!$D$10="Avalanche",Calc!$B$3,Calc!$B$2)),Calc!$B$8=0),"",IF(N(L39)<=0.005,"",IF(Start!$D$10="Avalanche",INDEX(Calc!CZ$75:CZ$89,Calc!$F$8),INDEX(Calc!CZ$50:CZ$64,Calc!$D$8)))) | M40: =IF(N40="","",N(N39)*(1+Start!$E$17/12)-N40) | N40: =IF(OR(OR(Calc!$B$4=0,$B40>IF(Start!$D$10="Avalanche",Calc!$B$3,Calc!$B$2)),Calc!$B$9=0),"",IF(N(N39)<=0.005,"",IF(Start!$D$10="Avalanche",INDEX(Calc!CZ$75:CZ$89,Calc!$F$9),INDEX(Calc!CZ$50:CZ$64,Calc!$D$9)))) | O40: =IF(P40="","",N(P39)*(1+Start!$E$18/12)-P40) | P40: =IF(OR(OR(Calc!$B$4=0,$B40>IF(Start!$D$10="Avalanche",Calc!$B$3,Calc!$B$2)),Calc!$B$10=0),"",IF(N(P39)<=0.005,"",IF(Start!$D$10="Avalanche",INDEX(Calc!CZ$75:CZ$89,Calc!$F$10),INDEX(Calc!CZ$50:CZ$64,Calc!$D$10)))) | Q40: =IF(R40="","",N(R39)*(1+Start!$E$19/12)-R40) | R40: =IF(OR(OR(Calc!$B$4=0,$B40>IF(Start!$D$10="Avalanche",Calc!$B$3,Calc!$B$2)),Calc!$B$11=0),"",IF(N(R39)<=0.005,"",IF(Start!$D$10="Avalanche",INDEX(Calc!CZ$75:CZ$89,Calc!$F$11),INDEX(Calc!CZ$50:CZ$64,Calc!$D$11)))) | S40: =IF(T40="","",N(T39)*(1+Start!$E$20/12)-T40) | T40: =IF(OR(OR(Calc!$B$4=0,$B40>IF(Start!$D$10="Avalanche",Calc!$B$3,Calc!$B$2)),Calc!$B$12=0),"",IF(N(T39)<=0.005,"",IF(Start!$D$10="Avalanche",INDEX(Calc!CZ$75:CZ$89,Calc!$F$12),INDEX(Calc!CZ$50:CZ$64,Calc!$D$12)))) | U40: =IF(V40="","",N(V39)*(1+Start!$E$21/12)-V40) | V40: =IF(OR(OR(Calc!$B$4=0,$B40>IF(Start!$D$10="Avalanche",Calc!$B$3,Calc!$B$2)),Calc!$B$13=0),"",IF(N(V39)<=0.005,"",IF(Start!$D$10="Avalanche",INDEX(Calc!CZ$75:CZ$89,Calc!$F$13),INDEX(Calc!CZ$50:CZ$64,Calc!$D$13)))) | W40: =IF(X40="","",N(X39)*(1+Start!$E$22/12)-X40) | X40: =IF(OR(OR(Calc!$B$4=0,$B40>IF(Start!$D$10="Avalanche",Calc!$B$3,Calc!$B$2)),Calc!$B$14=0),"",IF(N(X39)<=0.005,"",IF(Start!$D$10="Avalanche",INDEX(Calc!CZ$75:CZ$89,Calc!$F$14),INDEX(Calc!CZ$50:CZ$64,Calc!$D$14)))) | Y40: =IF(Z40="","",N(Z39)*(1+Start!$E$23/12)-Z40) | Z40: =IF(OR(OR(Calc!$B$4=0,$B40>IF(Start!$D$10="Avalanche",Calc!$B$3,Calc!$B$2)),Calc!$B$15=0),"",IF(N(Z39)<=0.005,"",IF(Start!$D$10="Avalanche",INDEX(Calc!CZ$75:CZ$89,Calc!$F$15),INDEX(Calc!CZ$50:CZ$64,Calc!$D$15)))) | AA40: =IF(AB40="","",N(AB39)*(1+Start!$E$24/12)-AB40) | AB40: =IF(OR(OR(Calc!$B$4=0,$B40>IF(Start!$D$10="Avalanche",Calc!$B$3,Calc!$B$2)),Calc!$B$16=0),"",IF(N(AB39)<=0.005,"",IF(Start!$D$10="Avalanche",INDEX(Calc!CZ$75:CZ$89,Calc!$F$16),INDEX(Calc!CZ$50:CZ$64,Calc!$D$16)))) | AC40: =IF(AD40="","",N(AD39)*(1+Start!$E$25/12)-AD40) | AD40: =IF(OR(OR(Calc!$B$4=0,$B40>IF(Start!$D$10="Avalanche",Calc!$B$3,Calc!$B$2)),Calc!$B$17=0),"",IF(N(AD39)<=0.005,"",IF(Start!$D$10="Avalanche",INDEX(Calc!CZ$75:CZ$89,Calc!$F$17),INDEX(Calc!CZ$50:CZ$64,Calc!$D$17)))) | AE40: =IF(AF40="","",N(AF39)*(1+Start!$E$26/12)-AF40) | AF40: =IF(OR(OR(Calc!$B$4=0,$B40>IF(Start!$D$10="Avalanche",Calc!$B$3,Calc!$B$2)),Calc!$B$18=0),"",IF(N(AF39)<=0.005,"",IF(Start!$D$10="Avalanche",INDEX(Calc!CZ$75:CZ$89,Calc!$F$18),INDEX(Calc!CZ$50:CZ$64,Calc!$D$18)))) | AG40: =IF(AH40="","",N(AH39)*(1+Start!$E$27/12)-AH40) | AH40: =IF(OR(OR(Calc!$B$4=0,$B40>IF(Start!$D$10="Avalanche",Calc!$B$3,Calc!$B$2)),Calc!$B$19=0),"",IF(N(AH39)<=0.005,"",IF(Start!$D$10="Avalanche",INDEX(Calc!CZ$75:CZ$89,Calc!$F$19),INDEX(Calc!CZ$50:CZ$64,Calc!$D$19)))) | AI40: =IF(AJ40="","",N(AJ39)*(1+Start!$E$28/12)-AJ40) | AJ40: =IF(OR(OR(Calc!$B$4=0,$B40>IF(Start!$D$10="Avalanche",Calc!$B$3,Calc!$B$2)),Calc!$B$20=0),"",IF(N(AJ39)<=0.005,"",IF(Start!$D$10="Avalanche",INDEX(Calc!CZ$75:CZ$89,Calc!$F$20),INDEX(Calc!CZ$50:CZ$64,Calc!$D$20))))
B41: 35 | C41: =IF(Calc!$B$4=0,"",EDATE(Start!$D$11,34)) | D41: =IF(OR(Calc!$B$4=0,$B41>IF(Start!$D$10="Avalanche",Calc!$B$3,Calc!$B$2)),"",SUM(G41,I41,K41,M41,O41,Q41,S41,U41,W41,Y41,AA41,AC41,AE41,AG41,AI41)) | E41: =IF(OR(Calc!$B$4=0,$B41>IF(Start!$D$10="Avalanche",Calc!$B$3,Calc!$B$2)),"",IF(Start!$D$10="Avalanche",Calc!DA$72,Calc!DA$47)) | F41: =IF(Calc!$B$4=0,"",IF($B41>IF(Start!$D$10="Avalanche",Calc!$B$3,Calc!$B$2),NA(),SUM(H41,J41,L41,N41,P41,R41,T41,V41,X41,Z41,AB41,AD41,AF41,AH41,AJ41))) | G41: =IF(H41="","",N(H40)*(1+Start!$E$14/12)-H41) | H41: =IF(OR(OR(Calc!$B$4=0,$B41>IF(Start!$D$10="Avalanche",Calc!$B$3,Calc!$B$2)),Calc!$B$6=0),"",IF(N(H40)<=0.005,"",IF(Start!$D$10="Avalanche",INDEX(Calc!DC$75:DC$89,Calc!$F$6),INDEX(Calc!DC$50:DC$64,Calc!$D$6)))) | I41: =IF(J41="","",N(J40)*(1+Start!$E$15/12)-J41) | J41: =IF(OR(OR(Calc!$B$4=0,$B41>IF(Start!$D$10="Avalanche",Calc!$B$3,Calc!$B$2)),Calc!$B$7=0),"",IF(N(J40)<=0.005,"",IF(Start!$D$10="Avalanche",INDEX(Calc!DC$75:DC$89,Calc!$F$7),INDEX(Calc!DC$50:DC$64,Calc!$D$7)))) | K41: =IF(L41="","",N(L40)*(1+Start!$E$16/12)-L41) | L41: =IF(OR(OR(Calc!$B$4=0,$B41>IF(Start!$D$10="Avalanche",Calc!$B$3,Calc!$B$2)),Calc!$B$8=0),"",IF(N(L40)<=0.005,"",IF(Start!$D$10="Avalanche",INDEX(Calc!DC$75:DC$89,Calc!$F$8),INDEX(Calc!DC$50:DC$64,Calc!$D$8)))) | M41: =IF(N41="","",N(N40)*(1+Start!$E$17/12)-N41) | N41: =IF(OR(OR(Calc!$B$4=0,$B41>IF(Start!$D$10="Avalanche",Calc!$B$3,Calc!$B$2)),Calc!$B$9=0),"",IF(N(N40)<=0.005,"",IF(Start!$D$10="Avalanche",INDEX(Calc!DC$75:DC$89,Calc!$F$9),INDEX(Calc!DC$50:DC$64,Calc!$D$9)))) | O41: =IF(P41="","",N(P40)*(1+Start!$E$18/12)-P41) | P41: =IF(OR(OR(Calc!$B$4=0,$B41>IF(Start!$D$10="Avalanche",Calc!$B$3,Calc!$B$2)),Calc!$B$10=0),"",IF(N(P40)<=0.005,"",IF(Start!$D$10="Avalanche",INDEX(Calc!DC$75:DC$89,Calc!$F$10),INDEX(Calc!DC$50:DC$64,Calc!$D$10)))) | Q41: =IF(R41="","",N(R40)*(1+Start!$E$19/12)-R41) | R41: =IF(OR(OR(Calc!$B$4=0,$B41>IF(Start!$D$10="Avalanche",Calc!$B$3,Calc!$B$2)),Calc!$B$11=0),"",IF(N(R40)<=0.005,"",IF(Start!$D$10="Avalanche",INDEX(Calc!DC$75:DC$89,Calc!$F$11),INDEX(Calc!DC$50:DC$64,Calc!$D$11)))) | S41: =IF(T41="","",N(T40)*(1+Start!$E$20/12)-T41) | T41: =IF(OR(OR(Calc!$B$4=0,$B41>IF(Start!$D$10="Avalanche",Calc!$B$3,Calc!$B$2)),Calc!$B$12=0),"",IF(N(T40)<=0.005,"",IF(Start!$D$10="Avalanche",INDEX(Calc!DC$75:DC$89,Calc!$F$12),INDEX(Calc!DC$50:DC$64,Calc!$D$12)))) | U41: =IF(V41="","",N(V40)*(1+Start!$E$21/12)-V41) | V41: =IF(OR(OR(Calc!$B$4=0,$B41>IF(Start!$D$10="Avalanche",Calc!$B$3,Calc!$B$2)),Calc!$B$13=0),"",IF(N(V40)<=0.005,"",IF(Start!$D$10="Avalanche",INDEX(Calc!DC$75:DC$89,Calc!$F$13),INDEX(Calc!DC$50:DC$64,Calc!$D$13)))) | W41: =IF(X41="","",N(X40)*(1+Start!$E$22/12)-X41) | X41: =IF(OR(OR(Calc!$B$4=0,$B41>IF(Start!$D$10="Avalanche",Calc!$B$3,Calc!$B$2)),Calc!$B$14=0),"",IF(N(X40)<=0.005,"",IF(Start!$D$10="Avalanche",INDEX(Calc!DC$75:DC$89,Calc!$F$14),INDEX(Calc!DC$50:DC$64,Calc!$D$14)))) | Y41: =IF(Z41="","",N(Z40)*(1+Start!$E$23/12)-Z41) | Z41: =IF(OR(OR(Calc!$B$4=0,$B41>IF(Start!$D$10="Avalanche",Calc!$B$3,Calc!$B$2)),Calc!$B$15=0),"",IF(N(Z40)<=0.005,"",IF(Start!$D$10="Avalanche",INDEX(Calc!DC$75:DC$89,Calc!$F$15),INDEX(Calc!DC$50:DC$64,Calc!$D$15)))) | AA41: =IF(AB41="","",N(AB40)*(1+Start!$E$24/12)-AB41) | AB41: =IF(OR(OR(Calc!$B$4=0,$B41>IF(Start!$D$10="Avalanche",Calc!$B$3,Calc!$B$2)),Calc!$B$16=0),"",IF(N(AB40)<=0.005,"",IF(Start!$D$10="Avalanche",INDEX(Calc!DC$75:DC$89,Calc!$F$16),INDEX(Calc!DC$50:DC$64,Calc!$D$16)))) | AC41: =IF(AD41="","",N(AD40)*(1+Start!$E$25/12)-AD41) | AD41: =IF(OR(OR(Calc!$B$4=0,$B41>IF(Start!$D$10="Avalanche",Calc!$B$3,Calc!$B$2)),Calc!$B$17=0),"",IF(N(AD40)<=0.005,"",IF(Start!$D$10="Avalanche",INDEX(Calc!DC$75:DC$89,Calc!$F$17),INDEX(Calc!DC$50:DC$64,Calc!$D$17)))) | AE41: =IF(AF41="","",N(AF40)*(1+Start!$E$26/12)-AF41) | AF41: =IF(OR(OR(Calc!$B$4=0,$B41>IF(Start!$D$10="Avalanche",Calc!$B$3,Calc!$B$2)),Calc!$B$18=0),"",IF(N(AF40)<=0.005,"",IF(Start!$D$10="Avalanche",INDEX(Calc!DC$75:DC$89,Calc!$F$18),INDEX(Calc!DC$50:DC$64,Calc!$D$18)))) | AG41: =IF(AH41="","",N(AH40)*(1+Start!$E$27/12)-AH41) | AH41: =IF(OR(OR(Calc!$B$4=0,$B41>IF(Start!$D$10="Avalanche",Calc!$B$3,Calc!$B$2)),Calc!$B$19=0),"",IF(N(AH40)<=0.005,"",IF(Start!$D$10="Avalanche",INDEX(Calc!DC$75:DC$89,Calc!$F$19),INDEX(Calc!DC$50:DC$64,Calc!$D$19)))) | AI41: =IF(AJ41="","",N(AJ40)*(1+Start!$E$28/12)-AJ41) | AJ41: =IF(OR(OR(Calc!$B$4=0,$B41>IF(Start!$D$10="Avalanche",Calc!$B$3,Calc!$B$2)),Calc!$B$20=0),"",IF(N(AJ40)<=0.005,"",IF(Start!$D$10="Avalanche",INDEX(Calc!DC$75:DC$89,Calc!$F$20),INDEX(Calc!DC$50:DC$64,Calc!$D$20))))
B42: 36 | C42: =IF(Calc!$B$4=0,"",EDATE(Start!$D$11,35)) | D42: =IF(OR(Calc!$B$4=0,$B42>IF(Start!$D$10="Avalanche",Calc!$B$3,Calc!$B$2)),"",SUM(G42,I42,K42,M42,O42,Q42,S42,U42,W42,Y42,AA42,AC42,AE42,AG42,AI42)) | E42: =IF(OR(Calc!$B$4=0,$B42>IF(Start!$D$10="Avalanche",Calc!$B$3,Calc!$B$2)),"",IF(Start!$D$10="Avalanche",Calc!DD$72,Calc!DD$47)) | F42: =IF(Calc!$B$4=0,"",IF($B42>IF(Start!$D$10="Avalanche",Calc!$B$3,Calc!$B$2),NA(),SUM(H42,J42,L42,N42,P42,R42,T42,V42,X42,Z42,AB42,AD42,AF42,AH42,AJ42))) | G42: =IF(H42="","",N(H41)*(1+Start!$E$14/12)-H42) | H42: =IF(OR(OR(Calc!$B$4=0,$B42>IF(Start!$D$10="Avalanche",Calc!$B$3,Calc!$B$2)),Calc!$B$6=0),"",IF(N(H41)<=0.005,"",IF(Start!$D$10="Avalanche",INDEX(Calc!DF$75:DF$89,Calc!$F$6),INDEX(Calc!DF$50:DF$64,Calc!$D$6)))) | I42: =IF(J42="","",N(J41)*(1+Start!$E$15/12)-J42) | J42: =IF(OR(OR(Calc!$B$4=0,$B42>IF(Start!$D$10="Avalanche",Calc!$B$3,Calc!$B$2)),Calc!$B$7=0),"",IF(N(J41)<=0.005,"",IF(Start!$D$10="Avalanche",INDEX(Calc!DF$75:DF$89,Calc!$F$7),INDEX(Calc!DF$50:DF$64,Calc!$D$7)))) | K42: =IF(L42="","",N(L41)*(1+Start!$E$16/12)-L42) | L42: =IF(OR(OR(Calc!$B$4=0,$B42>IF(Start!$D$10="Avalanche",Calc!$B$3,Calc!$B$2)),Calc!$B$8=0),"",IF(N(L41)<=0.005,"",IF(Start!$D$10="Avalanche",INDEX(Calc!DF$75:DF$89,Calc!$F$8),INDEX(Calc!DF$50:DF$64,Calc!$D$8)))) | M42: =IF(N42="","",N(N41)*(1+Start!$E$17/12)-N42) | N42: =IF(OR(OR(Calc!$B$4=0,$B42>IF(Start!$D$10="Avalanche",Calc!$B$3,Calc!$B$2)),Calc!$B$9=0),"",IF(N(N41)<=0.005,"",IF(Start!$D$10="Avalanche",INDEX(Calc!DF$75:DF$89,Calc!$F$9),INDEX(Calc!DF$50:DF$64,Calc!$D$9)))) | O42: =IF(P42="","",N(P41)*(1+Start!$E$18/12)-P42) | P42: =IF(OR(OR(Calc!$B$4=0,$B42>IF(Start!$D$10="Avalanche",Calc!$B$3,Calc!$B$2)),Calc!$B$10=0),"",IF(N(P41)<=0.005,"",IF(Start!$D$10="Avalanche",INDEX(Calc!DF$75:DF$89,Calc!$F$10),INDEX(Calc!DF$50:DF$64,Calc!$D$10)))) | Q42: =IF(R42="","",N(R41)*(1+Start!$E$19/12)-R42) | R42: =IF(OR(OR(Calc!$B$4=0,$B42>IF(Start!$D$10="Avalanche",Calc!$B$3,Calc!$B$2)),Calc!$B$11=0),"",IF(N(R41)<=0.005,"",IF(Start!$D$10="Avalanche",INDEX(Calc!DF$75:DF$89,Calc!$F$11),INDEX(Calc!DF$50:DF$64,Calc!$D$11)))) | S42: =IF(T42="","",N(T41)*(1+Start!$E$20/12)-T42) | T42: =IF(OR(OR(Calc!$B$4=0,$B42>IF(Start!$D$10="Avalanche",Calc!$B$3,Calc!$B$2)),Calc!$B$12=0),"",IF(N(T41)<=0.005,"",IF(Start!$D$10="Avalanche",INDEX(Calc!DF$75:DF$89,Calc!$F$12),INDEX(Calc!DF$50:DF$64,Calc!$D$12)))) | U42: =IF(V42="","",N(V41)*(1+Start!$E$21/12)-V42) | V42: =IF(OR(OR(Calc!$B$4=0,$B42>IF(Start!$D$10="Avalanche",Calc!$B$3,Calc!$B$2)),Calc!$B$13=0),"",IF(N(V41)<=0.005,"",IF(Start!$D$10="Avalanche",INDEX(Calc!DF$75:DF$89,Calc!$F$13),INDEX(Calc!DF$50:DF$64,Calc!$D$13)))) | W42: =IF(X42="","",N(X41)*(1+Start!$E$22/12)-X42) | X42: =IF(OR(OR(Calc!$B$4=0,$B42>IF(Start!$D$10="Avalanche",Calc!$B$3,Calc!$B$2)),Calc!$B$14=0),"",IF(N(X41)<=0.005,"",IF(Start!$D$10="Avalanche",INDEX(Calc!DF$75:DF$89,Calc!$F$14),INDEX(Calc!DF$50:DF$64,Calc!$D$14)))) | Y42: =IF(Z42="","",N(Z41)*(1+Start!$E$23/12)-Z42) | Z42: =IF(OR(OR(Calc!$B$4=0,$B42>IF(Start!$D$10="Avalanche",Calc!$B$3,Calc!$B$2)),Calc!$B$15=0),"",IF(N(Z41)<=0.005,"",IF(Start!$D$10="Avalanche",INDEX(Calc!DF$75:DF$89,Calc!$F$15),INDEX(Calc!DF$50:DF$64,Calc!$D$15)))) | AA42: =IF(AB42="","",N(AB41)*(1+Start!$E$24/12)-AB42) | AB42: =IF(OR(OR(Calc!$B$4=0,$B42>IF(Start!$D$10="Avalanche",Calc!$B$3,Calc!$B$2)),Calc!$B$16=0),"",IF(N(AB41)<=0.005,"",IF(Start!$D$10="Avalanche",INDEX(Calc!DF$75:DF$89,Calc!$F$16),INDEX(Calc!DF$50:DF$64,Calc!$D$16)))) | AC42: =IF(AD42="","",N(AD41)*(1+Start!$E$25/12)-AD42) | AD42: =IF(OR(OR(Calc!$B$4=0,$B42>IF(Start!$D$10="Avalanche",Calc!$B$3,Calc!$B$2)),Calc!$B$17=0),"",IF(N(AD41)<=0.005,"",IF(Start!$D$10="Avalanche",INDEX(Calc!DF$75:DF$89,Calc!$F$17),INDEX(Calc!DF$50:DF$64,Calc!$D$17)))) | AE42: =IF(AF42="","",N(AF41)*(1+Start!$E$26/12)-AF42) | AF42: =IF(OR(OR(Calc!$B$4=0,$B42>IF(Start!$D$10="Avalanche",Calc!$B$3,Calc!$B$2)),Calc!$B$18=0),"",IF(N(AF41)<=0.005,"",IF(Start!$D$10="Avalanche",INDEX(Calc!DF$75:DF$89,Calc!$F$18),INDEX(Calc!DF$50:DF$64,Calc!$D$18)))) | AG42: =IF(AH42="","",N(AH41)*(1+Start!$E$27/12)-AH42) | AH42: =IF(OR(OR(Calc!$B$4=0,$B42>IF(Start!$D$10="Avalanche",Calc!$B$3,Calc!$B$2)),Calc!$B$19=0),"",IF(N(AH41)<=0.005,"",IF(Start!$D$10="Avalanche",INDEX(Calc!DF$75:DF$89,Calc!$F$19),INDEX(Calc!DF$50:DF$64,Calc!$D$19)))) | AI42: =IF(AJ42="","",N(AJ41)*(1+Start!$E$28/12)-AJ42) | AJ42: =IF(OR(OR(Calc!$B$4=0,$B42>IF(Start!$D$10="Avalanche",Calc!$B$3,Calc!$B$2)),Calc!$B$20=0),"",IF(N(AJ41)<=0.005,"",IF(Start!$D$10="Avalanche",INDEX(Calc!DF$75:DF$89,Calc!$F$20),INDEX(Calc!DF$50:DF$64,Calc!$D$20))))
B43: 37 | C43: =IF(Calc!$B$4=0,"",EDATE(Start!$D$11,36)) | D43: =IF(OR(Calc!$B$4=0,$B43>IF(Start!$D$10="Avalanche",Calc!$B$3,Calc!$B$2)),"",SUM(G43,I43,K43,M43,O43,Q43,S43,U43,W43,Y43,AA43,AC43,AE43,AG43,AI43)) | E43: =IF(OR(Calc!$B$4=0,$B43>IF(Start!$D$10="Avalanche",Calc!$B$3,Calc!$B$2)),"",IF(Start!$D$10="Avalanche",Calc!DG$72,Calc!DG$47)) | F43: =IF(Calc!$B$4=0,"",IF($B43>IF(Start!$D$10="Avalanche",Calc!$B$3,Calc!$B$2),NA(),SUM(H43,J43,L43,N43,P43,R43,T43,V43,X43,Z43,AB43,AD43,AF43,AH43,AJ43))) | G43: =IF(H43="","",N(H42)*(1+Start!$E$14/12)-H43) | H43: =IF(OR(OR(Calc!$B$4=0,$B43>IF(Start!$D$10="Avalanche",Calc!$B$3,Calc!$B$2)),Calc!$B$6=0),"",IF(N(H42)<=0.005,"",IF(Start!$D$10="Avalanche",INDEX(Calc!DI$75:DI$89,Calc!$F$6),INDEX(Calc!DI$50:DI$64,Calc!$D$6)))) | I43: =IF(J43="","",N(J42)*(1+Start!$E$15/12)-J43) | J43: =IF(OR(OR(Calc!$B$4=0,$B43>IF(Start!$D$10="Avalanche",Calc!$B$3,Calc!$B$2)),Calc!$B$7=0),"",IF(N(J42)<=0.005,"",IF(Start!$D$10="Avalanche",INDEX(Calc!DI$75:DI$89,Calc!$F$7),INDEX(Calc!DI$50:DI$64,Calc!$D$7)))) | K43: =IF(L43="","",N(L42)*(1+Start!$E$16/12)-L43) | L43: =IF(OR(OR(Calc!$B$4=0,$B43>IF(Start!$D$10="Avalanche",Calc!$B$3,Calc!$B$2)),Calc!$B$8=0),"",IF(N(L42)<=0.005,"",IF(Start!$D$10="Avalanche",INDEX(Calc!DI$75:DI$89,Calc!$F$8),INDEX(Calc!DI$50:DI$64,Calc!$D$8)))) | M43: =IF(N43="","",N(N42)*(1+Start!$E$17/12)-N43) | N43: =IF(OR(OR(Calc!$B$4=0,$B43>IF(Start!$D$10="Avalanche",Calc!$B$3,Calc!$B$2)),Calc!$B$9=0),"",IF(N(N42)<=0.005,"",IF(Start!$D$10="Avalanche",INDEX(Calc!DI$75:DI$89,Calc!$F$9),INDEX(Calc!DI$50:DI$64,Calc!$D$9)))) | O43: =IF(P43="","",N(P42)*(1+Start!$E$18/12)-P43) | P43: =IF(OR(OR(Calc!$B$4=0,$B43>IF(Start!$D$10="Avalanche",Calc!$B$3,Calc!$B$2)),Calc!$B$10=0),"",IF(N(P42)<=0.005,"",IF(Start!$D$10="Avalanche",INDEX(Calc!DI$75:DI$89,Calc!$F$10),INDEX(Calc!DI$50:DI$64,Calc!$D$10)))) | Q43: =IF(R43="","",N(R42)*(1+Start!$E$19/12)-R43) | R43: =IF(OR(OR(Calc!$B$4=0,$B43>IF(Start!$D$10="Avalanche",Calc!$B$3,Calc!$B$2)),Calc!$B$11=0),"",IF(N(R42)<=0.005,"",IF(Start!$D$10="Avalanche",INDEX(Calc!DI$75:DI$89,Calc!$F$11),INDEX(Calc!DI$50:DI$64,Calc!$D$11)))) | S43: =IF(T43="","",N(T42)*(1+Start!$E$20/12)-T43) | T43: =IF(OR(OR(Calc!$B$4=0,$B43>IF(Start!$D$10="Avalanche",Calc!$B$3,Calc!$B$2)),Calc!$B$12=0),"",IF(N(T42)<=0.005,"",IF(Start!$D$10="Avalanche",INDEX(Calc!DI$75:DI$89,Calc!$F$12),INDEX(Calc!DI$50:DI$64,Calc!$D$12)))) | U43: =IF(V43="","",N(V42)*(1+Start!$E$21/12)-V43) | V43: =IF(OR(OR(Calc!$B$4=0,$B43>IF(Start!$D$10="Avalanche",Calc!$B$3,Calc!$B$2)),Calc!$B$13=0),"",IF(N(V42)<=0.005,"",IF(Start!$D$10="Avalanche",INDEX(Calc!DI$75:DI$89,Calc!$F$13),INDEX(Calc!DI$50:DI$64,Calc!$D$13)))) | W43: =IF(X43="","",N(X42)*(1+Start!$E$22/12)-X43) | X43: =IF(OR(OR(Calc!$B$4=0,$B43>IF(Start!$D$10="Avalanche",Calc!$B$3,Calc!$B$2)),Calc!$B$14=0),"",IF(N(X42)<=0.005,"",IF(Start!$D$10="Avalanche",INDEX(Calc!DI$75:DI$89,Calc!$F$14),INDEX(Calc!DI$50:DI$64,Calc!$D$14)))) | Y43: =IF(Z43="","",N(Z42)*(1+Start!$E$23/12)-Z43) | Z43: =IF(OR(OR(Calc!$B$4=0,$B43>IF(Start!$D$10="Avalanche",Calc!$B$3,Calc!$B$2)),Calc!$B$15=0),"",IF(N(Z42)<=0.005,"",IF(Start!$D$10="Avalanche",INDEX(Calc!DI$75:DI$89,Calc!$F$15),INDEX(Calc!DI$50:DI$64,Calc!$D$15)))) | AA43: =IF(AB43="","",N(AB42)*(1+Start!$E$24/12)-AB43) | AB43: =IF(OR(OR(Calc!$B$4=0,$B43>IF(Start!$D$10="Avalanche",Calc!$B$3,Calc!$B$2)),Calc!$B$16=0),"",IF(N(AB42)<=0.005,"",IF(Start!$D$10="Avalanche",INDEX(Calc!DI$75:DI$89,Calc!$F$16),INDEX(Calc!DI$50:DI$64,Calc!$D$16)))) | AC43: =IF(AD43="","",N(AD42)*(1+Start!$E$25/12)-AD43) | AD43: =IF(OR(OR(Calc!$B$4=0,$B43>IF(Start!$D$10="Avalanche",Calc!$B$3,Calc!$B$2)),Calc!$B$17=0),"",IF(N(AD42)<=0.005,"",IF(Start!$D$10="Avalanche",INDEX(Calc!DI$75:DI$89,Calc!$F$17),INDEX(Calc!DI$50:DI$64,Calc!$D$17)))) | AE43: =IF(AF43="","",N(AF42)*(1+Start!$E$26/12)-AF43) | AF43: =IF(OR(OR(Calc!$B$4=0,$B43>IF(Start!$D$10="Avalanche",Calc!$B$3,Calc!$B$2)),Calc!$B$18=0),"",IF(N(AF42)<=0.005,"",IF(Start!$D$10="Avalanche",INDEX(Calc!DI$75:DI$89,Calc!$F$18),INDEX(Calc!DI$50:DI$64,Calc!$D$18)))) | AG43: =IF(AH43="","",N(AH42)*(1+Start!$E$27/12)-AH43) | AH43: =IF(OR(OR(Calc!$B$4=0,$B43>IF(Start!$D$10="Avalanche",Calc!$B$3,Calc!$B$2)),Calc!$B$19=0),"",IF(N(AH42)<=0.005,"",IF(Start!$D$10="Avalanche",INDEX(Calc!DI$75:DI$89,Calc!$F$19),INDEX(Calc!DI$50:DI$64,Calc!$D$19)))) | AI43: =IF(AJ43="","",N(AJ42)*(1+Start!$E$28/12)-AJ43) | AJ43: =IF(OR(OR(Calc!$B$4=0,$B43>IF(Start!$D$10="Avalanche",Calc!$B$3,Calc!$B$2)),Calc!$B$20=0),"",IF(N(AJ42)<=0.005,"",IF(Start!$D$10="Avalanche",INDEX(Calc!DI$75:DI$89,Calc!$F$20),INDEX(Calc!DI$50:DI$64,Calc!$D$20))))
B44: 38 | C44: =IF(Calc!$B$4=0,"",EDATE(Start!$D$11,37)) | D44: =IF(OR(Calc!$B$4=0,$B44>IF(Start!$D$10="Avalanche",Calc!$B$3,Calc!$B$2)),"",SUM(G44,I44,K44,M44,O44,Q44,S44,U44,W44,Y44,AA44,AC44,AE44,AG44,AI44)) | E44: =IF(OR(Calc!$B$4=0,$B44>IF(Start!$D$10="Avalanche",Calc!$B$3,Calc!$B$2)),"",IF(Start!$D$10="Avalanche",Calc!DJ$72,Calc!DJ$47)) | F44: =IF(Calc!$B$4=0,"",IF($B44>IF(Start!$D$10="Avalanche",Calc!$B$3,Calc!$B$2),NA(),SUM(H44,J44,L44,N44,P44,R44,T44,V44,X44,Z44,AB44,AD44,AF44,AH44,AJ44))) | G44: =IF(H44="","",N(H43)*(1+Start!$E$14/12)-H44) | H44: =IF(OR(OR(Calc!$B$4=0,$B44>IF(Start!$D$10="Avalanche",Calc!$B$3,Calc!$B$2)),Calc!$B$6=0),"",IF(N(H43)<=0.005,"",IF(Start!$D$10="Avalanche",INDEX(Calc!DL$75:DL$89,Calc!$F$6),INDEX(Calc!DL$50:DL$64,Calc!$D$6)))) | I44: =IF(J44="","",N(J43)*(1+Start!$E$15/12)-J44) | J44: =IF(OR(OR(Calc!$B$4=0,$B44>IF(Start!$D$10="Avalanche",Calc!$B$3,Calc!$B$2)),Calc!$B$7=0),"",IF(N(J43)<=0.005,"",IF(Start!$D$10="Avalanche",INDEX(Calc!DL$75:DL$89,Calc!$F$7),INDEX(Calc!DL$50:DL$64,Calc!$D$7)))) | K44: =IF(L44="","",N(L43)*(1+Start!$E$16/12)-L44) | L44: =IF(OR(OR(Calc!$B$4=0,$B44>IF(Start!$D$10="Avalanche",Calc!$B$3,Calc!$B$2)),Calc!$B$8=0),"",IF(N(L43)<=0.005,"",IF(Start!$D$10="Avalanche",INDEX(Calc!DL$75:DL$89,Calc!$F$8),INDEX(Calc!DL$50:DL$64,Calc!$D$8)))) | M44: =IF(N44="","",N(N43)*(1+Start!$E$17/12)-N44) | N44: =IF(OR(OR(Calc!$B$4=0,$B44>IF(Start!$D$10="Avalanche",Calc!$B$3,Calc!$B$2)),Calc!$B$9=0),"",IF(N(N43)<=0.005,"",IF(Start!$D$10="Avalanche",INDEX(Calc!DL$75:DL$89,Calc!$F$9),INDEX(Calc!DL$50:DL$64,Calc!$D$9)))) | O44: =IF(P44="","",N(P43)*(1+Start!$E$18/12)-P44) | P44: =IF(OR(OR(Calc!$B$4=0,$B44>IF(Start!$D$10="Avalanche",Calc!$B$3,Calc!$B$2)),Calc!$B$10=0),"",IF(N(P43)<=0.005,"",IF(Start!$D$10="Avalanche",INDEX(Calc!DL$75:DL$89,Calc!$F$10),INDEX(Calc!DL$50:DL$64,Calc!$D$10)))) | Q44: =IF(R44="","",N(R43)*(1+Start!$E$19/12)-R44) | R44: =IF(OR(OR(Calc!$B$4=0,$B44>IF(Start!$D$10="Avalanche",Calc!$B$3,Calc!$B$2)),Calc!$B$11=0),"",IF(N(R43)<=0.005,"",IF(Start!$D$10="Avalanche",INDEX(Calc!DL$75:DL$89,Calc!$F$11),INDEX(Calc!DL$50:DL$64,Calc!$D$11)))) | S44: =IF(T44="","",N(T43)*(1+Start!$E$20/12)-T44) | T44: =IF(OR(OR(Calc!$B$4=0,$B44>IF(Start!$D$10="Avalanche",Calc!$B$3,Calc!$B$2)),Calc!$B$12=0),"",IF(N(T43)<=0.005,"",IF(Start!$D$10="Avalanche",INDEX(Calc!DL$75:DL$89,Calc!$F$12),INDEX(Calc!DL$50:DL$64,Calc!$D$12)))) | U44: =IF(V44="","",N(V43)*(1+Start!$E$21/12)-V44) | V44: =IF(OR(OR(Calc!$B$4=0,$B44>IF(Start!$D$10="Avalanche",Calc!$B$3,Calc!$B$2)),Calc!$B$13=0),"",IF(N(V43)<=0.005,"",IF(Start!$D$10="Avalanche",INDEX(Calc!DL$75:DL$89,Calc!$F$13),INDEX(Calc!DL$50:DL$64,Calc!$D$13)))) | W44: =IF(X44="","",N(X43)*(1+Start!$E$22/12)-X44) | X44: =IF(OR(OR(Calc!$B$4=0,$B44>IF(Start!$D$10="Avalanche",Calc!$B$3,Calc!$B$2)),Calc!$B$14=0),"",IF(N(X43)<=0.005,"",IF(Start!$D$10="Avalanche",INDEX(Calc!DL$75:DL$89,Calc!$F$14),INDEX(Calc!DL$50:DL$64,Calc!$D$14)))) | Y44: =IF(Z44="","",N(Z43)*(1+Start!$E$23/12)-Z44) | Z44: =IF(OR(OR(Calc!$B$4=0,$B44>IF(Start!$D$10="Avalanche",Calc!$B$3,Calc!$B$2)),Calc!$B$15=0),"",IF(N(Z43)<=0.005,"",IF(Start!$D$10="Avalanche",INDEX(Calc!DL$75:DL$89,Calc!$F$15),INDEX(Calc!DL$50:DL$64,Calc!$D$15)))) | AA44: =IF(AB44="","",N(AB43)*(1+Start!$E$24/12)-AB44) | AB44: =IF(OR(OR(Calc!$B$4=0,$B44>IF(Start!$D$10="Avalanche",Calc!$B$3,Calc!$B$2)),Calc!$B$16=0),"",IF(N(AB43)<=0.005,"",IF(Start!$D$10="Avalanche",INDEX(Calc!DL$75:DL$89,Calc!$F$16),INDEX(Calc!DL$50:DL$64,Calc!$D$16)))) | AC44: =IF(AD44="","",N(AD43)*(1+Start!$E$25/12)-AD44) | AD44: =IF(OR(OR(Calc!$B$4=0,$B44>IF(Start!$D$10="Avalanche",Calc!$B$3,Calc!$B$2)),Calc!$B$17=0),"",IF(N(AD43)<=0.005,"",IF(Start!$D$10="Avalanche",INDEX(Calc!DL$75:DL$89,Calc!$F$17),INDEX(Calc!DL$50:DL$64,Calc!$D$17)))) | AE44: =IF(AF44="","",N(AF43)*(1+Start!$E$26/12)-AF44) | AF44: =IF(OR(OR(Calc!$B$4=0,$B44>IF(Start!$D$10="Avalanche",Calc!$B$3,Calc!$B$2)),Calc!$B$18=0),"",IF(N(AF43)<=0.005,"",IF(Start!$D$10="Avalanche",INDEX(Calc!DL$75:DL$89,Calc!$F$18),INDEX(Calc!DL$50:DL$64,Calc!$D$18)))) | AG44: =IF(AH44="","",N(AH43)*(1+Start!$E$27/12)-AH44) | AH44: =IF(OR(OR(Calc!$B$4=0,$B44>IF(Start!$D$10="Avalanche",Calc!$B$3,Calc!$B$2)),Calc!$B$19=0),"",IF(N(AH43)<=0.005,"",IF(Start!$D$10="Avalanche",INDEX(Calc!DL$75:DL$89,Calc!$F$19),INDEX(Calc!DL$50:DL$64,Calc!$D$19)))) | AI44: =IF(AJ44="","",N(AJ43)*(1+Start!$E$28/12)-AJ44) | AJ44: =IF(OR(OR(Calc!$B$4=0,$B44>IF(Start!$D$10="Avalanche",Calc!$B$3,Calc!$B$2)),Calc!$B$20=0),"",IF(N(AJ43)<=0.005,"",IF(Start!$D$10="Avalanche",INDEX(Calc!DL$75:DL$89,Calc!$F$20),INDEX(Calc!DL$50:DL$64,Calc!$D$20))))
B45: 39 | C45: =IF(Calc!$B$4=0,"",EDATE(Start!$D$11,38)) | D45: =IF(OR(Calc!$B$4=0,$B45>IF(Start!$D$10="Avalanche",Calc!$B$3,Calc!$B$2)),"",SUM(G45,I45,K45,M45,O45,Q45,S45,U45,W45,Y45,AA45,AC45,AE45,AG45,AI45)) | E45: =IF(OR(Calc!$B$4=0,$B45>IF(Start!$D$10="Avalanche",Calc!$B$3,Calc!$B$2)),"",IF(Start!$D$10="Avalanche",Calc!DM$72,Calc!DM$47)) | F45: =IF(Calc!$B$4=0,"",IF($B45>IF(Start!$D$10="Avalanche",Calc!$B$3,Calc!$B$2),NA(),SUM(H45,J45,L45,N45,P45,R45,T45,V45,X45,Z45,AB45,AD45,AF45,AH45,AJ45))) | G45: =IF(H45="","",N(H44)*(1+Start!$E$14/12)-H45) | H45: =IF(OR(OR(Calc!$B$4=0,$B45>IF(Start!$D$10="Avalanche",Calc!$B$3,Calc!$B$2)),Calc!$B$6=0),"",IF(N(H44)<=0.005,"",IF(Start!$D$10="Avalanche",INDEX(Calc!DO$75:DO$89,Calc!$F$6),INDEX(Calc!DO$50:DO$64,Calc!$D$6)))) | I45: =IF(J45="","",N(J44)*(1+Start!$E$15/12)-J45) | J45: =IF(OR(OR(Calc!$B$4=0,$B45>IF(Start!$D$10="Avalanche",Calc!$B$3,Calc!$B$2)),Calc!$B$7=0),"",IF(N(J44)<=0.005,"",IF(Start!$D$10="Avalanche",INDEX(Calc!DO$75:DO$89,Calc!$F$7),INDEX(Calc!DO$50:DO$64,Calc!$D$7)))) | K45: =IF(L45="","",N(L44)*(1+Start!$E$16/12)-L45) | L45: =IF(OR(OR(Calc!$B$4=0,$B45>IF(Start!$D$10="Avalanche",Calc!$B$3,Calc!$B$2)),Calc!$B$8=0),"",IF(N(L44)<=0.005,"",IF(Start!$D$10="Avalanche",INDEX(Calc!DO$75:DO$89,Calc!$F$8),INDEX(Calc!DO$50:DO$64,Calc!$D$8)))) | M45: =IF(N45="","",N(N44)*(1+Start!$E$17/12)-N45) | N45: =IF(OR(OR(Calc!$B$4=0,$B45>IF(Start!$D$10="Avalanche",Calc!$B$3,Calc!$B$2)),Calc!$B$9=0),"",IF(N(N44)<=0.005,"",IF(Start!$D$10="Avalanche",INDEX(Calc!DO$75:DO$89,Calc!$F$9),INDEX(Calc!DO$50:DO$64,Calc!$D$9)))) | O45: =IF(P45="","",N(P44)*(1+Start!$E$18/12)-P45) | P45: =IF(OR(OR(Calc!$B$4=0,$B45>IF(Start!$D$10="Avalanche",Calc!$B$3,Calc!$B$2)),Calc!$B$10=0),"",IF(N(P44)<=0.005,"",IF(Start!$D$10="Avalanche",INDEX(Calc!DO$75:DO$89,Calc!$F$10),INDEX(Calc!DO$50:DO$64,Calc!$D$10)))) | Q45: =IF(R45="","",N(R44)*(1+Start!$E$19/12)-R45) | R45: =IF(OR(OR(Calc!$B$4=0,$B45>IF(Start!$D$10="Avalanche",Calc!$B$3,Calc!$B$2)),Calc!$B$11=0),"",IF(N(R44)<=0.005,"",IF(Start!$D$10="Avalanche",INDEX(Calc!DO$75:DO$89,Calc!$F$11),INDEX(Calc!DO$50:DO$64,Calc!$D$11)))) | S45: =IF(T45="","",N(T44)*(1+Start!$E$20/12)-T45) | T45: =IF(OR(OR(Calc!$B$4=0,$B45>IF(Start!$D$10="Avalanche",Calc!$B$3,Calc!$B$2)),Calc!$B$12=0),"",IF(N(T44)<=0.005,"",IF(Start!$D$10="Avalanche",INDEX(Calc!DO$75:DO$89,Calc!$F$12),INDEX(Calc!DO$50:DO$64,Calc!$D$12)))) | U45: =IF(V45="","",N(V44)*(1+Start!$E$21/12)-V45) | V45: =IF(OR(OR(Calc!$B$4=0,$B45>IF(Start!$D$10="Avalanche",Calc!$B$3,Calc!$B$2)),Calc!$B$13=0),"",IF(N(V44)<=0.005,"",IF(Start!$D$10="Avalanche",INDEX(Calc!DO$75:DO$89,Calc!$F$13),INDEX(Calc!DO$50:DO$64,Calc!$D$13)))) | W45: =IF(X45="","",N(X44)*(1+Start!$E$22/12)-X45) | X45: =IF(OR(OR(Calc!$B$4=0,$B45>IF(Start!$D$10="Avalanche",Calc!$B$3,Calc!$B$2)),Calc!$B$14=0),"",IF(N(X44)<=0.005,"",IF(Start!$D$10="Avalanche",INDEX(Calc!DO$75:DO$89,Calc!$F$14),INDEX(Calc!DO$50:DO$64,Calc!$D$14)))) | Y45: =IF(Z45="","",N(Z44)*(1+Start!$E$23/12)-Z45) | Z45: =IF(OR(OR(Calc!$B$4=0,$B45>IF(Start!$D$10="Avalanche",Calc!$B$3,Calc!$B$2)),Calc!$B$15=0),"",IF(N(Z44)<=0.005,"",IF(Start!$D$10="Avalanche",INDEX(Calc!DO$75:DO$89,Calc!$F$15),INDEX(Calc!DO$50:DO$64,Calc!$D$15)))) | AA45: =IF(AB45="","",N(AB44)*(1+Start!$E$24/12)-AB45) | AB45: =IF(OR(OR(Calc!$B$4=0,$B45>IF(Start!$D$10="Avalanche",Calc!$B$3,Calc!$B$2)),Calc!$B$16=0),"",IF(N(AB44)<=0.005,"",IF(Start!$D$10="Avalanche",INDEX(Calc!DO$75:DO$89,Calc!$F$16),INDEX(Calc!DO$50:DO$64,Calc!$D$16)))) | AC45: =IF(AD45="","",N(AD44)*(1+Start!$E$25/12)-AD45) | AD45: =IF(OR(OR(Calc!$B$4=0,$B45>IF(Start!$D$10="Avalanche",Calc!$B$3,Calc!$B$2)),Calc!$B$17=0),"",IF(N(AD44)<=0.005,"",IF(Start!$D$10="Avalanche",INDEX(Calc!DO$75:DO$89,Calc!$F$17),INDEX(Calc!DO$50:DO$64,Calc!$D$17)))) | AE45: =IF(AF45="","",N(AF44)*(1+Start!$E$26/12)-AF45) | AF45: =IF(OR(OR(Calc!$B$4=0,$B45>IF(Start!$D$10="Avalanche",Calc!$B$3,Calc!$B$2)),Calc!$B$18=0),"",IF(N(AF44)<=0.005,"",IF(Start!$D$10="Avalanche",INDEX(Calc!DO$75:DO$89,Calc!$F$18),INDEX(Calc!DO$50:DO$64,Calc!$D$18)))) | AG45: =IF(AH45="","",N(AH44)*(1+Start!$E$27/12)-AH45) | AH45: =IF(OR(OR(Calc!$B$4=0,$B45>IF(Start!$D$10="Avalanche",Calc!$B$3,Calc!$B$2)),Calc!$B$19=0),"",IF(N(AH44)<=0.005,"",IF(Start!$D$10="Avalanche",INDEX(Calc!DO$75:DO$89,Calc!$F$19),INDEX(Calc!DO$50:DO$64,Calc!$D$19)))) | AI45: =IF(AJ45="","",N(AJ44)*(1+Start!$E$28/12)-AJ45) | AJ45: =IF(OR(OR(Calc!$B$4=0,$B45>IF(Start!$D$10="Avalanche",Calc!$B$3,Calc!$B$2)),Calc!$B$20=0),"",IF(N(AJ44)<=0.005,"",IF(Start!$D$10="Avalanche",INDEX(Calc!DO$75:DO$89,Calc!$F$20),INDEX(Calc!DO$50:DO$64,Calc!$D$20))))
B46: 40 | C46: =IF(Calc!$B$4=0,"",EDATE(Start!$D$11,39)) | D46: =IF(OR(Calc!$B$4=0,$B46>IF(Start!$D$10="Avalanche",Calc!$B$3,Calc!$B$2)),"",SUM(G46,I46,K46,M46,O46,Q46,S46,U46,W46,Y46,AA46,AC46,AE46,AG46,AI46)) | E46: =IF(OR(Calc!$B$4=0,$B46>IF(Start!$D$10="Avalanche",Calc!$B$3,Calc!$B$2)),"",IF(Start!$D$10="Avalanche",Calc!DP$72,Calc!DP$47)) | F46: =IF(Calc!$B$4=0,"",IF($B46>IF(Start!$D$10="Avalanche",Calc!$B$3,Calc!$B$2),NA(),SUM(H46,J46,L46,N46,P46,R46,T46,V46,X46,Z46,AB46,AD46,AF46,AH46,AJ46))) | G46: =IF(H46="","",N(H45)*(1+Start!$E$14/12)-H46) | H46: =IF(OR(OR(Calc!$B$4=0,$B46>IF(Start!$D$10="Avalanche",Calc!$B$3,Calc!$B$2)),Calc!$B$6=0),"",IF(N(H45)<=0.005,"",IF(Start!$D$10="Avalanche",INDEX(Calc!DR$75:DR$89,Calc!$F$6),INDEX(Calc!DR$50:DR$64,Calc!$D$6)))) | I46: =IF(J46="","",N(J45)*(1+Start!$E$15/12)-J46) | J46: =IF(OR(OR(Calc!$B$4=0,$B46>IF(Start!$D$10="Avalanche",Calc!$B$3,Calc!$B$2)),Calc!$B$7=0),"",IF(N(J45)<=0.005,"",IF(Start!$D$10="Avalanche",INDEX(Calc!DR$75:DR$89,Calc!$F$7),INDEX(Calc!DR$50:DR$64,Calc!$D$7)))) | K46: =IF(L46="","",N(L45)*(1+Start!$E$16/12)-L46) | L46: =IF(OR(OR(Calc!$B$4=0,$B46>IF(Start!$D$10="Avalanche",Calc!$B$3,Calc!$B$2)),Calc!$B$8=0),"",IF(N(L45)<=0.005,"",IF(Start!$D$10="Avalanche",INDEX(Calc!DR$75:DR$89,Calc!$F$8),INDEX(Calc!DR$50:DR$64,Calc!$D$8)))) | M46: =IF(N46="","",N(N45)*(1+Start!$E$17/12)-N46) | N46: =IF(OR(OR(Calc!$B$4=0,$B46>IF(Start!$D$10="Avalanche",Calc!$B$3,Calc!$B$2)),Calc!$B$9=0),"",IF(N(N45)<=0.005,"",IF(Start!$D$10="Avalanche",INDEX(Calc!DR$75:DR$89,Calc!$F$9),INDEX(Calc!DR$50:DR$64,Calc!$D$9)))) | O46: =IF(P46="","",N(P45)*(1+Start!$E$18/12)-P46) | P46: =IF(OR(OR(Calc!$B$4=0,$B46>IF(Start!$D$10="Avalanche",Calc!$B$3,Calc!$B$2)),Calc!$B$10=0),"",IF(N(P45)<=0.005,"",IF(Start!$D$10="Avalanche",INDEX(Calc!DR$75:DR$89,Calc!$F$10),INDEX(Calc!DR$50:DR$64,Calc!$D$10)))) | Q46: =IF(R46="","",N(R45)*(1+Start!$E$19/12)-R46) | R46: =IF(OR(OR(Calc!$B$4=0,$B46>IF(Start!$D$10="Avalanche",Calc!$B$3,Calc!$B$2)),Calc!$B$11=0),"",IF(N(R45)<=0.005,"",IF(Start!$D$10="Avalanche",INDEX(Calc!DR$75:DR$89,Calc!$F$11),INDEX(Calc!DR$50:DR$64,Calc!$D$11)))) | S46: =IF(T46="","",N(T45)*(1+Start!$E$20/12)-T46) | T46: =IF(OR(OR(Calc!$B$4=0,$B46>IF(Start!$D$10="Avalanche",Calc!$B$3,Calc!$B$2)),Calc!$B$12=0),"",IF(N(T45)<=0.005,"",IF(Start!$D$10="Avalanche",INDEX(Calc!DR$75:DR$89,Calc!$F$12),INDEX(Calc!DR$50:DR$64,Calc!$D$12)))) | U46: =IF(V46="","",N(V45)*(1+Start!$E$21/12)-V46) | V46: =IF(OR(OR(Calc!$B$4=0,$B46>IF(Start!$D$10="Avalanche",Calc!$B$3,Calc!$B$2)),Calc!$B$13=0),"",IF(N(V45)<=0.005,"",IF(Start!$D$10="Avalanche",INDEX(Calc!DR$75:DR$89,Calc!$F$13),INDEX(Calc!DR$50:DR$64,Calc!$D$13)))) | W46: =IF(X46="","",N(X45)*(1+Start!$E$22/12)-X46) | X46: =IF(OR(OR(Calc!$B$4=0,$B46>IF(Start!$D$10="Avalanche",Calc!$B$3,Calc!$B$2)),Calc!$B$14=0),"",IF(N(X45)<=0.005,"",IF(Start!$D$10="Avalanche",INDEX(Calc!DR$75:DR$89,Calc!$F$14),INDEX(Calc!DR$50:DR$64,Calc!$D$14)))) | Y46: =IF(Z46="","",N(Z45)*(1+Start!$E$23/12)-Z46) | Z46: =IF(OR(OR(Calc!$B$4=0,$B46>IF(Start!$D$10="Avalanche",Calc!$B$3,Calc!$B$2)),Calc!$B$15=0),"",IF(N(Z45)<=0.005,"",IF(Start!$D$10="Avalanche",INDEX(Calc!DR$75:DR$89,Calc!$F$15),INDEX(Calc!DR$50:DR$64,Calc!$D$15)))) | AA46: =IF(AB46="","",N(AB45)*(1+Start!$E$24/12)-AB46) | AB46: =IF(OR(OR(Calc!$B$4=0,$B46>IF(Start!$D$10="Avalanche",Calc!$B$3,Calc!$B$2)),Calc!$B$16=0),"",IF(N(AB45)<=0.005,"",IF(Start!$D$10="Avalanche",INDEX(Calc!DR$75:DR$89,Calc!$F$16),INDEX(Calc!DR$50:DR$64,Calc!$D$16)))) | AC46: =IF(AD46="","",N(AD45)*(1+Start!$E$25/12)-AD46) | AD46: =IF(OR(OR(Calc!$B$4=0,$B46>IF(Start!$D$10="Avalanche",Calc!$B$3,Calc!$B$2)),Calc!$B$17=0),"",IF(N(AD45)<=0.005,"",IF(Start!$D$10="Avalanche",INDEX(Calc!DR$75:DR$89,Calc!$F$17),INDEX(Calc!DR$50:DR$64,Calc!$D$17)))) | AE46: =IF(AF46="","",N(AF45)*(1+Start!$E$26/12)-AF46) | AF46: =IF(OR(OR(Calc!$B$4=0,$B46>IF(Start!$D$10="Avalanche",Calc!$B$3,Calc!$B$2)),Calc!$B$18=0),"",IF(N(AF45)<=0.005,"",IF(Start!$D$10="Avalanche",INDEX(Calc!DR$75:DR$89,Calc!$F$18),INDEX(Calc!DR$50:DR$64,Calc!$D$18)))) | AG46: =IF(AH46="","",N(AH45)*(1+Start!$E$27/12)-AH46) | AH46: =IF(OR(OR(Calc!$B$4=0,$B46>IF(Start!$D$10="Avalanche",Calc!$B$3,Calc!$B$2)),Calc!$B$19=0),"",IF(N(AH45)<=0.005,"",IF(Start!$D$10="Avalanche",INDEX(Calc!DR$75:DR$89,Calc!$F$19),INDEX(Calc!DR$50:DR$64,Calc!$D$19)))) | AI46: =IF(AJ46="","",N(AJ45)*(1+Start!$E$28/12)-AJ46) | AJ46: =IF(OR(OR(Calc!$B$4=0,$B46>IF(Start!$D$10="Avalanche",Calc!$B$3,Calc!$B$2)),Calc!$B$20=0),"",IF(N(AJ45)<=0.005,"",IF(Start!$D$10="Avalanche",INDEX(Calc!DR$75:DR$89,Calc!$F$20),INDEX(Calc!DR$50:DR$64,Calc!$D$20))))
B47: 41 | C47: =IF(Calc!$B$4=0,"",EDATE(Start!$D$11,40)) | D47: =IF(OR(Calc!$B$4=0,$B47>IF(Start!$D$10="Avalanche",Calc!$B$3,Calc!$B$2)),"",SUM(G47,I47,K47,M47,O47,Q47,S47,U47,W47,Y47,AA47,AC47,AE47,AG47,AI47)) | E47: =IF(OR(Calc!$B$4=0,$B47>IF(Start!$D$10="Avalanche",Calc!$B$3,Calc!$B$2)),"",IF(Start!$D$10="Avalanche",Calc!DS$72,Calc!DS$47)) | F47: =IF(Calc!$B$4=0,"",IF($B47>IF(Start!$D$10="Avalanche",Calc!$B$3,Calc!$B$2),NA(),SUM(H47,J47,L47,N47,P47,R47,T47,V47,X47,Z47,AB47,AD47,AF47,AH47,AJ47))) | G47: =IF(H47="","",N(H46)*(1+Start!$E$14/12)-H47) | H47: =IF(OR(OR(Calc!$B$4=0,$B47>IF(Start!$D$10="Avalanche",Calc!$B$3,Calc!$B$2)),Calc!$B$6=0),"",IF(N(H46)<=0.005,"",IF(Start!$D$10="Avalanche",INDEX(Calc!DU$75:DU$89,Calc!$F$6),INDEX(Calc!DU$50:DU$64,Calc!$D$6)))) | I47: =IF(J47="","",N(J46)*(1+Start!$E$15/12)-J47) | J47: =IF(OR(OR(Calc!$B$4=0,$B47>IF(Start!$D$10="Avalanche",Calc!$B$3,Calc!$B$2)),Calc!$B$7=0),"",IF(N(J46)<=0.005,"",IF(Start!$D$10="Avalanche",INDEX(Calc!DU$75:DU$89,Calc!$F$7),INDEX(Calc!DU$50:DU$64,Calc!$D$7)))) | K47: =IF(L47="","",N(L46)*(1+Start!$E$16/12)-L47) | L47: =IF(OR(OR(Calc!$B$4=0,$B47>IF(Start!$D$10="Avalanche",Calc!$B$3,Calc!$B$2)),Calc!$B$8=0),"",IF(N(L46)<=0.005,"",IF(Start!$D$10="Avalanche",INDEX(Calc!DU$75:DU$89,Calc!$F$8),INDEX(Calc!DU$50:DU$64,Calc!$D$8)))) | M47: =IF(N47="","",N(N46)*(1+Start!$E$17/12)-N47) | N47: =IF(OR(OR(Calc!$B$4=0,$B47>IF(Start!$D$10="Avalanche",Calc!$B$3,Calc!$B$2)),Calc!$B$9=0),"",IF(N(N46)<=0.005,"",IF(Start!$D$10="Avalanche",INDEX(Calc!DU$75:DU$89,Calc!$F$9),INDEX(Calc!DU$50:DU$64,Calc!$D$9)))) | O47: =IF(P47="","",N(P46)*(1+Start!$E$18/12)-P47) | P47: =IF(OR(OR(Calc!$B$4=0,$B47>IF(Start!$D$10="Avalanche",Calc!$B$3,Calc!$B$2)),Calc!$B$10=0),"",IF(N(P46)<=0.005,"",IF(Start!$D$10="Avalanche",INDEX(Calc!DU$75:DU$89,Calc!$F$10),INDEX(Calc!DU$50:DU$64,Calc!$D$10)))) | Q47: =IF(R47="","",N(R46)*(1+Start!$E$19/12)-R47) | R47: =IF(OR(OR(Calc!$B$4=0,$B47>IF(Start!$D$10="Avalanche",Calc!$B$3,Calc!$B$2)),Calc!$B$11=0),"",IF(N(R46)<=0.005,"",IF(Start!$D$10="Avalanche",INDEX(Calc!DU$75:DU$89,Calc!$F$11),INDEX(Calc!DU$50:DU$64,Calc!$D$11)))) | S47: =IF(T47="","",N(T46)*(1+Start!$E$20/12)-T47) | T47: =IF(OR(OR(Calc!$B$4=0,$B47>IF(Start!$D$10="Avalanche",Calc!$B$3,Calc!$B$2)),Calc!$B$12=0),"",IF(N(T46)<=0.005,"",IF(Start!$D$10="Avalanche",INDEX(Calc!DU$75:DU$89,Calc!$F$12),INDEX(Calc!DU$50:DU$64,Calc!$D$12)))) | U47: =IF(V47="","",N(V46)*(1+Start!$E$21/12)-V47) | V47: =IF(OR(OR(Calc!$B$4=0,$B47>IF(Start!$D$10="Avalanche",Calc!$B$3,Calc!$B$2)),Calc!$B$13=0),"",IF(N(V46)<=0.005,"",IF(Start!$D$10="Avalanche",INDEX(Calc!DU$75:DU$89,Calc!$F$13),INDEX(Calc!DU$50:DU$64,Calc!$D$13)))) | W47: =IF(X47="","",N(X46)*(1+Start!$E$22/12)-X47) | X47: =IF(OR(OR(Calc!$B$4=0,$B47>IF(Start!$D$10="Avalanche",Calc!$B$3,Calc!$B$2)),Calc!$B$14=0),"",IF(N(X46)<=0.005,"",IF(Start!$D$10="Avalanche",INDEX(Calc!DU$75:DU$89,Calc!$F$14),INDEX(Calc!DU$50:DU$64,Calc!$D$14)))) | Y47: =IF(Z47="","",N(Z46)*(1+Start!$E$23/12)-Z47) | Z47: =IF(OR(OR(Calc!$B$4=0,$B47>IF(Start!$D$10="Avalanche",Calc!$B$3,Calc!$B$2)),Calc!$B$15=0),"",IF(N(Z46)<=0.005,"",IF(Start!$D$10="Avalanche",INDEX(Calc!DU$75:DU$89,Calc!$F$15),INDEX(Calc!DU$50:DU$64,Calc!$D$15)))) | AA47: =IF(AB47="","",N(AB46)*(1+Start!$E$24/12)-AB47) | AB47: =IF(OR(OR(Calc!$B$4=0,$B47>IF(Start!$D$10="Avalanche",Calc!$B$3,Calc!$B$2)),Calc!$B$16=0),"",IF(N(AB46)<=0.005,"",IF(Start!$D$10="Avalanche",INDEX(Calc!DU$75:DU$89,Calc!$F$16),INDEX(Calc!DU$50:DU$64,Calc!$D$16)))) | AC47: =IF(AD47="","",N(AD46)*(1+Start!$E$25/12)-AD47) | AD47: =IF(OR(OR(Calc!$B$4=0,$B47>IF(Start!$D$10="Avalanche",Calc!$B$3,Calc!$B$2)),Calc!$B$17=0),"",IF(N(AD46)<=0.005,"",IF(Start!$D$10="Avalanche",INDEX(Calc!DU$75:DU$89,Calc!$F$17),INDEX(Calc!DU$50:DU$64,Calc!$D$17)))) | AE47: =IF(AF47="","",N(AF46)*(1+Start!$E$26/12)-AF47) | AF47: =IF(OR(OR(Calc!$B$4=0,$B47>IF(Start!$D$10="Avalanche",Calc!$B$3,Calc!$B$2)),Calc!$B$18=0),"",IF(N(AF46)<=0.005,"",IF(Start!$D$10="Avalanche",INDEX(Calc!DU$75:DU$89,Calc!$F$18),INDEX(Calc!DU$50:DU$64,Calc!$D$18)))) | AG47: =IF(AH47="","",N(AH46)*(1+Start!$E$27/12)-AH47) | AH47: =IF(OR(OR(Calc!$B$4=0,$B47>IF(Start!$D$10="Avalanche",Calc!$B$3,Calc!$B$2)),Calc!$B$19=0),"",IF(N(AH46)<=0.005,"",IF(Start!$D$10="Avalanche",INDEX(Calc!DU$75:DU$89,Calc!$F$19),INDEX(Calc!DU$50:DU$64,Calc!$D$19)))) | AI47: =IF(AJ47="","",N(AJ46)*(1+Start!$E$28/12)-AJ47) | AJ47: =IF(OR(OR(Calc!$B$4=0,$B47>IF(Start!$D$10="Avalanche",Calc!$B$3,Calc!$B$2)),Calc!$B$20=0),"",IF(N(AJ46)<=0.005,"",IF(Start!$D$10="Avalanche",INDEX(Calc!DU$75:DU$89,Calc!$F$20),INDEX(Calc!DU$50:DU$64,Calc!$D$20))))
B48: 42 | C48: =IF(Calc!$B$4=0,"",EDATE(Start!$D$11,41)) | D48: =IF(OR(Calc!$B$4=0,$B48>IF(Start!$D$10="Avalanche",Calc!$B$3,Calc!$B$2)),"",SUM(G48,I48,K48,M48,O48,Q48,S48,U48,W48,Y48,AA48,AC48,AE48,AG48,AI48)) | E48: =IF(OR(Calc!$B$4=0,$B48>IF(Start!$D$10="Avalanche",Calc!$B$3,Calc!$B$2)),"",IF(Start!$D$10="Avalanche",Calc!DV$72,Calc!DV$47)) | F48: =IF(Calc!$B$4=0,"",IF($B48>IF(Start!$D$10="Avalanche",Calc!$B$3,Calc!$B$2),NA(),SUM(H48,J48,L48,N48,P48,R48,T48,V48,X48,Z48,AB48,AD48,AF48,AH48,AJ48))) | G48: =IF(H48="","",N(H47)*(1+Start!$E$14/12)-H48) | H48: =IF(OR(OR(Calc!$B$4=0,$B48>IF(Start!$D$10="Avalanche",Calc!$B$3,Calc!$B$2)),Calc!$B$6=0),"",IF(N(H47)<=0.005,"",IF(Start!$D$10="Avalanche",INDEX(Calc!DX$75:DX$89,Calc!$F$6),INDEX(Calc!DX$50:DX$64,Calc!$D$6)))) | I48: =IF(J48="","",N(J47)*(1+Start!$E$15/12)-J48) | J48: =IF(OR(OR(Calc!$B$4=0,$B48>IF(Start!$D$10="Avalanche",Calc!$B$3,Calc!$B$2)),Calc!$B$7=0),"",IF(N(J47)<=0.005,"",IF(Start!$D$10="Avalanche",INDEX(Calc!DX$75:DX$89,Calc!$F$7),INDEX(Calc!DX$50:DX$64,Calc!$D$7)))) | K48: =IF(L48="","",N(L47)*(1+Start!$E$16/12)-L48) | L48: =IF(OR(OR(Calc!$B$4=0,$B48>IF(Start!$D$10="Avalanche",Calc!$B$3,Calc!$B$2)),Calc!$B$8=0),"",IF(N(L47)<=0.005,"",IF(Start!$D$10="Avalanche",INDEX(Calc!DX$75:DX$89,Calc!$F$8),INDEX(Calc!DX$50:DX$64,Calc!$D$8)))) | M48: =IF(N48="","",N(N47)*(1+Start!$E$17/12)-N48) | N48: =IF(OR(OR(Calc!$B$4=0,$B48>IF(Start!$D$10="Avalanche",Calc!$B$3,Calc!$B$2)),Calc!$B$9=0),"",IF(N(N47)<=0.005,"",IF(Start!$D$10="Avalanche",INDEX(Calc!DX$75:DX$89,Calc!$F$9),INDEX(Calc!DX$50:DX$64,Calc!$D$9)))) | O48: =IF(P48="","",N(P47)*(1+Start!$E$18/12)-P48) | P48: =IF(OR(OR(Calc!$B$4=0,$B48>IF(Start!$D$10="Avalanche",Calc!$B$3,Calc!$B$2)),Calc!$B$10=0),"",IF(N(P47)<=0.005,"",IF(Start!$D$10="Avalanche",INDEX(Calc!DX$75:DX$89,Calc!$F$10),INDEX(Calc!DX$50:DX$64,Calc!$D$10)))) | Q48: =IF(R48="","",N(R47)*(1+Start!$E$19/12)-R48) | R48: =IF(OR(OR(Calc!$B$4=0,$B48>IF(Start!$D$10="Avalanche",Calc!$B$3,Calc!$B$2)),Calc!$B$11=0),"",IF(N(R47)<=0.005,"",IF(Start!$D$10="Avalanche",INDEX(Calc!DX$75:DX$89,Calc!$F$11),INDEX(Calc!DX$50:DX$64,Calc!$D$11)))) | S48: =IF(T48="","",N(T47)*(1+Start!$E$20/12)-T48) | T48: =IF(OR(OR(Calc!$B$4=0,$B48>IF(Start!$D$10="Avalanche",Calc!$B$3,Calc!$B$2)),Calc!$B$12=0),"",IF(N(T47)<=0.005,"",IF(Start!$D$10="Avalanche",INDEX(Calc!DX$75:DX$89,Calc!$F$12),INDEX(Calc!DX$50:DX$64,Calc!$D$12)))) | U48: =IF(V48="","",N(V47)*(1+Start!$E$21/12)-V48) | V48: =IF(OR(OR(Calc!$B$4=0,$B48>IF(Start!$D$10="Avalanche",Calc!$B$3,Calc!$B$2)),Calc!$B$13=0),"",IF(N(V47)<=0.005,"",IF(Start!$D$10="Avalanche",INDEX(Calc!DX$75:DX$89,Calc!$F$13),INDEX(Calc!DX$50:DX$64,Calc!$D$13)))) | W48: =IF(X48="","",N(X47)*(1+Start!$E$22/12)-X48) | X48: =IF(OR(OR(Calc!$B$4=0,$B48>IF(Start!$D$10="Avalanche",Calc!$B$3,Calc!$B$2)),Calc!$B$14=0),"",IF(N(X47)<=0.005,"",IF(Start!$D$10="Avalanche",INDEX(Calc!DX$75:DX$89,Calc!$F$14),INDEX(Calc!DX$50:DX$64,Calc!$D$14)))) | Y48: =IF(Z48="","",N(Z47)*(1+Start!$E$23/12)-Z48) | Z48: =IF(OR(OR(Calc!$B$4=0,$B48>IF(Start!$D$10="Avalanche",Calc!$B$3,Calc!$B$2)),Calc!$B$15=0),"",IF(N(Z47)<=0.005,"",IF(Start!$D$10="Avalanche",INDEX(Calc!DX$75:DX$89,Calc!$F$15),INDEX(Calc!DX$50:DX$64,Calc!$D$15)))) | AA48: =IF(AB48="","",N(AB47)*(1+Start!$E$24/12)-AB48) | AB48: =IF(OR(OR(Calc!$B$4=0,$B48>IF(Start!$D$10="Avalanche",Calc!$B$3,Calc!$B$2)),Calc!$B$16=0),"",IF(N(AB47)<=0.005,"",IF(Start!$D$10="Avalanche",INDEX(Calc!DX$75:DX$89,Calc!$F$16),INDEX(Calc!DX$50:DX$64,Calc!$D$16)))) | AC48: =IF(AD48="","",N(AD47)*(1+Start!$E$25/12)-AD48) | AD48: =IF(OR(OR(Calc!$B$4=0,$B48>IF(Start!$D$10="Avalanche",Calc!$B$3,Calc!$B$2)),Calc!$B$17=0),"",IF(N(AD47)<=0.005,"",IF(Start!$D$10="Avalanche",INDEX(Calc!DX$75:DX$89,Calc!$F$17),INDEX(Calc!DX$50:DX$64,Calc!$D$17)))) | AE48: =IF(AF48="","",N(AF47)*(1+Start!$E$26/12)-AF48) | AF48: =IF(OR(OR(Calc!$B$4=0,$B48>IF(Start!$D$10="Avalanche",Calc!$B$3,Calc!$B$2)),Calc!$B$18=0),"",IF(N(AF47)<=0.005,"",IF(Start!$D$10="Avalanche",INDEX(Calc!DX$75:DX$89,Calc!$F$18),INDEX(Calc!DX$50:DX$64,Calc!$D$18)))) | AG48: =IF(AH48="","",N(AH47)*(1+Start!$E$27/12)-AH48) | AH48: =IF(OR(OR(Calc!$B$4=0,$B48>IF(Start!$D$10="Avalanche",Calc!$B$3,Calc!$B$2)),Calc!$B$19=0),"",IF(N(AH47)<=0.005,"",IF(Start!$D$10="Avalanche",INDEX(Calc!DX$75:DX$89,Calc!$F$19),INDEX(Calc!DX$50:DX$64,Calc!$D$19)))) | AI48: =IF(AJ48="","",N(AJ47)*(1+Start!$E$28/12)-AJ48) | AJ48: =IF(OR(OR(Calc!$B$4=0,$B48>IF(Start!$D$10="Avalanche",Calc!$B$3,Calc!$B$2)),Calc!$B$20=0),"",IF(N(AJ47)<=0.005,"",IF(Start!$D$10="Avalanche",INDEX(Calc!DX$75:DX$89,Calc!$F$20),INDEX(Calc!DX$50:DX$64,Calc!$D$20))))
